Workbook
Name Slicer_DepartmentType: #N/A
Name Slicer_GenderCode: #N/A
Name Slicer_MaritalDesc: #N/A
Name Slicer_PayZone: #N/A
Name Slicer_Performance_Score: #N/A

Sheet employee_data
A1: EmpID | B1: FirstName | C1: LastName | D1: StartDate | E1: ExitDate | F1: Title | G1: Supervisor | H1: ADEmail | I1: BusinessUnit | J1: EmployeeStatus | K1: EmployeeType | L1: PayZone | M1: EmployeeClassificationType | N1: TerminationType | O1: TerminationDescription | P1: DepartmentType | Q1: Division | R1: DOB | S1: State | T1: JobFunctionDescription | U1: GenderCode | V1: LocationCode | W1: RaceDesc | X1: MaritalDesc | Y1: Performance Score | Z1: Current Employee Rating
A2: 3427 | B2: Uriah | C2: Bridges | D2: 43728 | F2: Production Technician I | G2: Peter Oneill | H2: uriah.bridges@bilearner.com | I2: CCDR | J2: Active | K2: Contract | L2: Zone C | M2: Temporary | N2: Unk | P2: Production | Q2: Finance & Accounting | R2: 25483 | S2: MA | T2: Accounting | U2: Female | V2: 34904 | W2: White | X2: Widowed | Y2: Fully Meets | Z2: 4
A3: 3428 | B3: Paula | C3: Small | D3: 44968 | F3: Production Technician I | G3: Renee Mccormick | H3: paula.small@bilearner.com | I3: EW | J3: Active | K3: Contract | L3: Zone A | M3: Part-Time | N3: Unk | P3: Production | Q3: Aerial | R3: 23984 | S3: MA | T3: Labor | U3: Male | V3: 6593 | W3: Hispanic | X3: Widowed | Y3: Fully Meets | Z3: 3
A4: 3429 | B4: Edward | C4: Buck | D4: 43444 | F4: Area Sales Manager | G4: Crystal Walker | H4: edward.buck@bilearner.com | I4: PL | J4: Active | K4: Full-Time | L4: Zone B | M4: Part-Time | N4: Unk | P4: Sales | Q4: General - Sga | R4: 33517 | S4: MA | T4: Assistant | U4: Male | V4: 2330 | W4: Hispanic | X4: Widowed | Y4: Fully Meets | Z4: 4
A5: 3430 | B5: Michael | C5: Riordan | D5: 44368 | F5: Area Sales Manager | G5: Rebekah Wright | H5: michael.riordan@bilearner.com | I5: CCDR | J5: Active | K5: Contract | L5: Zone A | M5: Full-Time | N5: Unk | P5: Sales | Q5: Finance & Accounting | R5: 35889 | S5: ND | T5: Clerk | U5: Male | V5: 58782 | W5: Other | X5: Single | Y5: Fully Meets | Z5: 2
A6: 3431 | B6: Jasmine | C6: Onque | D6: 43645 | F6: Area Sales Manager | G6: Jason Kim | H6: jasmine.onque@bilearner.com | I6: TNS | J6: Active | K6: Contract | L6: Zone A | M6: Temporary | N6: Unk | P6: Sales | Q6: General - Con | R6: 25444 | S6: FL | T6: Laborer | U6: Female | V6: 33174 | W6: Other | X6: Married | Y6: Fully Meets | Z6: 3
A7: 3432 | B7: Maruk | C7: Fraval | D7: 43847 | F7: Area Sales Manager | G7: Sheri Campos | H7: maruk.fraval@bilearner.com | I7: BPC | J7: Active | K7: Contract | L7: Zone B | M7: Full-Time | N7: Unk | P7: Sales | Q7: Field Operations | R7: 17991 | S7: CT | T7: Driver | U7: Male | V7: 6050 | W7: Black | X7: Married | Y7: Fully Meets | Z7: 3
A8: 3433 | B8: Latia | C8: Costa | D8: 44657 | E8: 45110 | F8: Area Sales Manager | G8: Jacob Braun | H8: latia.costa@bilearner.com | I8: WBL | J8: Active | K8: Full-Time | L8: Zone B | M8: Temporary | N8: Involuntary | O8: Me see picture nature degree benefit. | P8: Sales | Q8: General - Eng | R8: 15523 | S8: CA | T8: Technician | U8: Female | V8: 90007 | W8: Hispanic | X8: Divorced | Y8: Exceeds | Z8: 4
A9: 3434 | B9: Sharlene | C9: Terry | D9: 44141 | E9: 44955 | F9: Area Sales Manager | G9: Tracy Marquez | H9: sharlene.terry@bilearner.com | I9: CCDR | J9: Active | K9: Contract | L9: Zone C | M9: Full-Time | N9: Involuntary | O9: Blue community type skill story. | P9: Sales | Q9: Engineers | R9: 20886 | S9: OR | T9: Engineer | U9: Female | V9: 97756 | W9: White | X9: Divorced | Y9: Fully Meets | Z9: 2
A10: 3435 | B10: Jac | C10: McKinzie | D10: 43330 | F10: Area Sales Manager | G10: Sharon Becker | H10: jac.mckinzie@bilearner.com | I10: NEL | J10: Active | K10: Contract | L10: Zone B | M10: Part-Time | N10: Unk | P10: Sales | Q10: Executive | R10: 27164 | S10: TX | T10: Executive Assistant | U10: Male | V10: 78789 | W10: Black | X10: Widowed | Y10: Exceeds | Z10: 3
A11: 3436 | B11: Joseph | C11: Martins | D11: 44582 | E11: 45106 | F11: Area Sales Manager | G11: George Jenkins | H11: joseph.martins@bilearner.com | I11: BPC | J11: Active | K11: Part-Time | L11: Zone B | M11: Temporary | N11: Resignation | O11: Summer personal bag. | P11: Sales | Q11: Engineers | R11: 18213 | S11: TX | T11: Engineer | U11: Male | V11: 78207 | W11: Asian | X11: Widowed | Y11: Fully Meets | Z11: 5
A12: 3437 | B12: Myriam | C12: Givens | D12: 45142 | F12: Area Sales Manager | G12: Troy White | H12: myriam.givens@bilearner.com | I12: SVG | J12: Active | K12: Contract | L12: Zone B | M12: Temporary | N12: Unk | P12: Sales | Q12: Field Operations | R12: 23402 | S12: IN | T12: Technician | U12: Female | V12: 46204 | W12: Other | X12: Single | Y12: Fully Meets | Z12: 5
A13: 3438 | B13: Dheepa | C13: Nguyen | D13: 43322 | E13: 43773 | F13: Area Sales Manager | G13: Brian Miller | H13: dheepa.nguyen@bilearner.com | I13: MSC | J13: Active | K13: Full-Time | L13: Zone C | M13: Temporary | N13: Retirement | O13: Alone once than. More condition pay far. | P13: Sales | Q13: General - Con | R13: 17629 | S13: GA | T13: Technician | U13: Female | V13: 30428 | W13: Asian | X13: Married | Y13: Fully Meets | Z13: 3
A14: 3439 | B14: Bartholemew | C14: Khemmich | D14: 44706 | E14: 44892 | F14: Area Sales Manager | G14: Charles Parks | H14: bartholemew.khemmich@bilearner.com | I14: EW | J14: Active | K14: Full-Time | L14: Zone A | M14: Temporary | N14: Involuntary | O14: Foot in theory minute recognize test. | P14: Sales | Q14: Splicing | R14: 29914 | S14: CO | T14: Splicer | U14: Male | V14: 80820 | W14: Other | X14: Single | Y14: Fully Meets | Z14: 3
A15: 3440 | B15: Xana | C15: Potts | D15: 43804 | E15: 44974 | F15: Area Sales Manager | G15: Gregory Walker | H15: xana.potts@bilearner.com | I15: CCDR | J15: Active | K15: Contract | L15: Zone A | M15: Full-Time | N15: Resignation | O15: Degree wish science when thing week old. | P15: Sales | Q15: Finance & Accounting | R15: 18938 | S15: KY | T15: Controller | U15: Female | V15: 40220 | W15: White | X15: Divorced | Y15: Fully Meets | Z15: 3
A16: 3441 | B16: Prater | C16: Jeremy | D16: 43583 | F16: Area Sales Manager | G16: Tyler Lewis | H16: prater.jeremy@bilearner.com | I16: BPC | J16: Active | K16: Part-Time | L16: Zone A | M16: Part-Time | N16: Unk | P16: Sales | Q16: General - Con | R16: 32833 | S16: NV | T16: Lineman | U16: Male | V16: 89139 | W16: Asian | X16: Widowed | Y16: Exceeds | Z16: 4
A17: 3442 | B17: Kaylah | C17: Moon | D17: 43655 | E17: 44728 | F17: Area Sales Manager | G17: Ashley Scott | H17: kaylah.moon@bilearner.com | I17: PYZ | J17: Active | K17: Full-Time | L17: Zone A | M17: Full-Time | N17: Retirement | O17: Fear particular method stage. | P17: IT/IS | Q17: Field Operations | R17: 19322 | S17: MA | T17: Laborer | U17: Male | V17: 2810 | W17: Black | X17: Single | Y17: Exceeds | Z17: 2
A18: 3443 | B18: Kristen | C18: Tate | D18: 44291 | E18: 45058 | F18: Area Sales Manager | G18: Lauren Jones | H18: kristen.tate@bilearner.com | I18: WBL | J18: Active | K18: Full-Time | L18: Zone C | M18: Part-Time | N18: Voluntary | O18: Wall body wonder successful. | P18: IT/IS | Q18: Project Management - Con | R18: 34432 | S18: KY | T18: Coordinator | U18: Male | V18: 2621 | W18: Asian | X18: Widowed | Y18: Fully Meets | Z18: 3
A19: 3444 | B19: Bobby | C19: Rodgers | D19: 44528 | E19: 44596 | F19: Area Sales Manager | G19: Matthew Jackson | H19: bobby.rodgers@bilearner.com | I19: NEL | J19: Active | K19: Contract | L19: Zone A | M19: Part-Time | N19: Voluntary | O19: Visit foot nearly radio treatment. | P19: Sales | Q19: Engineers | R19: 30635 | S19: KY | T19: Director | U19: Male | V19: 44553 | W19: Other | X19: Widowed | Y19: Fully Meets | Z19: 3
A20: 3445 | B20: Reid | C20: Park | D20: 44212 | F20: Area Sales Manager | G20: Michelle Mitchell | H20: reid.park@bilearner.com | I20: PL | J20: Active | K20: Contract | L20: Zone C | M20: Full-Time | N20: Unk | P20: Sales | Q20: Project Management - Con | R20: 31388 | S20: KY | T20: Supervisor | U20: Female | V20: 5360 | W20: Other | X20: Married | Y20: Exceeds | Z20: 4
A21: 3446 | B21: Hector | C21: Dalton | D21: 44432 | F21: Area Sales Manager | G21: Sydney French | H21: hector.dalton@bilearner.com | I21: BPC | J21: Active | K21: Part-Time | L21: Zone A | M21: Part-Time | N21: Unk | P21: Sales | Q21: Field Operations | R21: 35186 | S21: TX | T21: Driller | U21: Female | V21: 16325 | W21: White | X21: Divorced | Y21: Exceeds | Z21: 2
A22: 3447 | B22: Mariela | C22: Schultz | D22: 43977 | E22: 45095 | F22: Area Sales Manager | G22: Michelle Evans MD | H22: mariela.schultz@bilearner.com | I22: CCDR | J22: Future Start | K22: Part-Time | L22: Zone C | M22: Part-Time | N22: Involuntary | O22: Unit pass office southern break one. | P22: Sales | Q22: General - Con | R22: 23424 | S22: TX | T22: Technician | U22: Female | V22: 43481 | W22: Asian | X22: Widowed | Y22: Fully Meets | Z22: 3
A23: 3448 | B23: Angela | C23: Molina | D23: 43739 | E23: 44141 | F23: Area Sales Manager | G23: Patricia Cook | H23: angela.molina@bilearner.com | I23: SVG | J23: Future Start | K23: Full-Time | L23: Zone A | M23: Temporary | N23: Retirement | O23: List class mind. | P23: Sales | Q23: Engineers | R23: 21317 | S23: TX | T23: Specialist | U23: Male | V23: 50705 | W23: Asian | X23: Widowed | Y23: Fully Meets | Z23: 3
A24: 3449 | B24: Gerald | C24: Preston | D24: 45056 | E24: 45073 | F24: Area Sales Manager | G24: Ashley Reeves | H24: gerald.preston@bilearner.com | I24: EW | J24: Future Start | K24: Contract | L24: Zone B | M24: Temporary | N24: Involuntary | O24: Price third parent evening. | P24: Sales | Q24: General - Eng | R24: 33865 | S24: CO | T24: Technician | U24: Male | V24: 5168 | W24: Black | X24: Single | Y24: Fully Meets | Z24: 5
A25: 3450 | B25: Reilly | C25: Moyer | D25: 44075 | E25: 44899 | F25: Area Sales Manager | G25: Stanley Harvey | H25: reilly.moyer@bilearner.com | I25: MSC | J25: Active | K25: Contract | L25: Zone C | M25: Temporary | N25: Resignation | O25: Cause military a sense. Doctor property may. | P25: Sales | Q25: Field Operations | R25: 34557 | S25: CO | T25: Operator | U25: Male | V25: 11765 | W25: Other | X25: Single | Y25: Exceeds | Z25: 2
A26: 3451 | B26: Carlee | C26: French | D26: 44245 | E26: 44876 | F26: Area Sales Manager | G26: Michael Bradshaw | H26: carlee.french@bilearner.com | I26: TNS | J26: Active | K26: Contract | L26: Zone C | M26: Full-Time | N26: Voluntary | O26: Station another son positive. | P26: Sales | Q26: General - Con | R26: 24852 | S26: CO | T26: Technician | U26: Male | V26: 71071 | W26: Other | X26: Divorced | Y26: Exceeds | Z26: 3
A27: 3452 | B27: Jaydon | C27: Blackburn | D27: 44873 | F27: Area Sales Manager | G27: Debbie Crosby | H27: jaydon.blackburn@bilearner.com | I27: PYZ | J27: Active | K27: Part-Time | L27: Zone A | M27: Part-Time | N27: Unk | P27: Sales | Q27: General - Con | R27: 17174 | S27: IN | T27: Foreman | U27: Male | V27: 12122 | W27: Black | X27: Divorced | Y27: Fully Meets | Z27: 2
A28: 3453 | B28: Bridger | C28: Carter | D28: 44847 | F28: Area Sales Manager | G28: Elizabeth Taylor | H28: bridger.carter@bilearner.com | I28: WBL | J28: Active | K28: Contract | L28: Zone C | M28: Part-Time | N28: Unk | P28: Sales | Q28: Fielders | R28: 30048 | S28: MA | T28: Engineer | U28: Male | V28: 87065 | W28: White | X28: Widowed | Y28: Fully Meets | Z28: 4
A29: 3454 | B29: Leon | C29: Beard | D29: 44815 | F29: Area Sales Manager | G29: Brian Dunlap | H29: leon.beard@bilearner.com | I29: PYZ | J29: Active | K29: Full-Time | L29: Zone C | M29: Full-Time | N29: Unk | P29: IT/IS | Q29: General - Con | R29: 25597 | S29: KY | T29: Foreman | U29: Male | V29: 10415 | W29: Hispanic | X29: Married | Y29: Needs Improvement | Z29: 4
A30: 3455 | B30: Charity | C30: Miranda | D30: 44376 | E30: 44747 | F30: Area Sales Manager | G30: Daniel Rodriguez | H30: charity.miranda@bilearner.com | I30: WBL | J30: Active | K30: Full-Time | L30: Zone C | M30: Temporary | N30: Resignation | O30: Pm local take example fund. Small heavy listen. | P30: Sales | Q30: Project Management - Eng | R30: 36178 | S30: KY | T30: Manager | U30: Male | V30: 3763 | W30: Other | X30: Widowed | Y30: Exceeds | Z30: 4
A31: 3456 | B31: Axel | C31: Howe | D31: 44991 | F31: Area Sales Manager | G31: Martin Hammond | H31: axel.howe@bilearner.com | I31: NEL | J31: Active | K31: Full-Time | L31: Zone A | M31: Temporary | N31: Unk | P31: Sales | Q31: Field Operations | R31: 17070 | S31: KY | T31: Technician | U31: Female | V31: 79623 | W31: Black | X31: Divorced | Y31: Fully Meets | Z31: 3
A32: 3457 | B32: Milton | C32: Wall | D32: 44099 | F32: Area Sales Manager | G32: Sara Bell | H32: milton.wall@bilearner.com | I32: PL | J32: Active | K32: Full-Time | L32: Zone B | M32: Temporary | N32: Unk | P32: Sales | Q32: Engineers | R32: 17402 | S32: KY | T32: Technician | U32: Female | V32: 69189 | W32: White | X32: Divorced | Y32: Needs Improvement | Z32: 3
A33: 3458 | B33: Cory | C33: Robinson | D33: 44679 | E33: 45070 | F33: Area Sales Manager | G33: Elizabeth Anderson | H33: cory.robinson@bilearner.com | I33: BPC | J33: Future Start | K33: Contract | L33: Zone A | M33: Full-Time | N33: Voluntary | O33: Several young whether that expert. | P33: Sales | Q33: Field Operations | R33: 35289 | S33: TX | T33: Laborer | U33: Female | V33: 5194 | W33: Hispanic | X33: Single | Y33: Needs Improvement | Z33: 3
A34: 3459 | B34: Saniya | C34: Yu | D34: 44304 | E34: 44733 | F34: Area Sales Manager | G34: Erin Bailey | H34: saniya.yu@bilearner.com | I34: CCDR | J34: Future Start | K34: Part-Time | L34: Zone A | M34: Full-Time | N34: Retirement | O34: Science end approach democratic treatment. | P34: Sales | Q34: General - Con | R34: 16111 | S34: TX | T34: Splicer | U34: Male | V34: 8779 | W34: Black | X34: Widowed | Y34: Exceeds | Z34: 2
A35: 3460 | B35: Alisa | C35: James | D35: 43880 | F35: Area Sales Manager | G35: Dennis Henderson | H35: alisa.james@bilearner.com | I35: SVG | J35: Active | K35: Full-Time | L35: Zone A | M35: Full-Time | N35: Unk | P35: Sales | Q35: Aerial | R35: 16112 | S35: TX | T35: Lineman | U35: Male | V35: 74682 | W35: Asian | X35: Married | Y35: Fully Meets | Z35: 3
A36: 3461 | B36: Lincoln | C36: Compton | D36: 43664 | E36: 44470 | F36: Area Sales Manager | G36: Tammy Conner | H36: lincoln.compton@bilearner.com | I36: EW | J36: Future Start | K36: Full-Time | L36: Zone C | M36: Part-Time | N36: Resignation | O36: Base scene central unit per argue. Might last of. | P36: Sales | Q36: General - Con | R36: 35793 | S36: CO | T36: Foreman | U36: Male | V36: 78046 | W36: Hispanic | X36: Married | Y36: Needs Improvement | Z36: 1
A37: 3462 | B37: Aliana | C37: Nolan | D37: 43356 | E37: 44456 | F37: Area Sales Manager | G37: Brianna Mathews | H37: aliana.nolan@bilearner.com | I37: MSC | J37: Active | K37: Contract | L37: Zone A | M37: Full-Time | N37: Involuntary | O37: Yourself book budget product. | P37: Sales | Q37: Field Operations | R37: 15562 | S37: CO | T37: Coordinator | U37: Male | V37: 27270 | W37: Hispanic | X37: Divorced | Y37: Needs Improvement | Z37: 3
A38: 3463 | B38: Kayden | C38: Dodson | D38: 43951 | E38: 44395 | F38: Area Sales Manager | G38: Jessica Peters | H38: kayden.dodson@bilearner.com | I38: TNS | J38: Active | K38: Part-Time | L38: Zone A | M38: Temporary | N38: Retirement | O38: Paper can score else investment. | P38: Sales | Q38: Field Operations | R38: 18800 | S38: IN | T38: Tower Hand | U38: Male | V38: 12703 | W38: Hispanic | X38: Single | Y38: Fully Meets | Z38: 1
A39: 3464 | B39: James | C39: Duke | D39: 43437 | E39: 44813 | F39: Area Sales Manager | G39: Mark Harris | H39: james.duke@bilearner.com | I39: PYZ | J39: Active | K39: Contract | L39: Zone B | M39: Full-Time | N39: Involuntary | O39: Stuff different color how. | P39: Sales | Q39: Shop (Fleet) | R39: 35963 | S39: MA | T39: Mechanic | U39: Male | V39: 66835 | W39: Black | X39: Widowed | Y39: Needs Improvement | Z39: 5
A40: 3465 | B40: Willow | C40: Stuart | D40: 44508 | F40: Area Sales Manager | G40: Elizabeth Tapia | H40: willow.stuart@bilearner.com | I40: WBL | J40: Active | K40: Full-Time | L40: Zone B | M40: Full-Time | N40: Unk | P40: Sales | Q40: General - Con | R40: 22653 | S40: MA | T40: Flagger | U40: Male | V40: 66150 | W40: Asian | X40: Divorced | Y40: Needs Improvement | Z40: 3
A41: 3466 | B41: Clayton | C41: Walker | D41: 44664 | E41: 45026 | F41: Area Sales Manager | G41: Jon Holden | H41: clayton.walker@bilearner.com | I41: PYZ | J41: Active | K41: Part-Time | L41: Zone C | M41: Full-Time | N41: Retirement | O41: Sign figure employee card education. | P41: IT/IS | Q41: Aerial | R41: 28881 | S41: KY | T41: Supervisor | U41: Male | V41: 64288 | W41: Other | X41: Married | Y41: Exceeds | Z41: 4
A42: 3467 | B42: Celia | C42: Curtis | D42: 43957 | F42: Area Sales Manager | G42: Michael Odonnell | H42: celia.curtis@bilearner.com | I42: WBL | J42: Active | K42: Contract | L42: Zone A | M42: Part-Time | N42: Unk | P42: Sales | Q42: Fielders | R42: 31911 | S42: KY | T42: Engineer | U42: Female | V42: 94333 | W42: Asian | X42: Divorced | Y42: Exceeds | Z42: 1
A43: 3468 | B43: Valentin | C43: Reilly | D43: 43717 | F43: Area Sales Manager | G43: Andres Parker | H43: valentin.reilly@bilearner.com | I43: NEL | J43: Active | K43: Contract | L43: Zone B | M43: Temporary | N43: Unk | P43: Sales | Q43: Wireline Construction | R43: 35911 | S43: KY | T43: Foreman | U43: Female | V43: 45453 | W43: Black | X43: Single | Y43: Fully Meets | Z43: 4
A44: 3469 | B44: Ryland | C44: Shepherd | D44: 44041 | E44: 44931 | F44: Area Sales Manager | G44: James Berry | H44: ryland.shepherd@bilearner.com | I44: PL | J44: Future Start | K44: Contract | L44: Zone B | M44: Full-Time | N44: Resignation | O44: Right cut matter arrive difference. | P44: Sales | Q44: Field Operations | R44: 16489 | S44: TX | T44: Driver | U44: Female | V44: 81905 | W44: Asian | X44: Divorced | Y44: Needs Improvement | Z44: 3
A45: 3470 | B45: Esteban | C45: Gilbert | D45: 43418 | E45: 43766 | F45: Area Sales Manager | G45: Gail Ali | H45: esteban.gilbert@bilearner.com | I45: BPC | J45: Future Start | K45: Contract | L45: Zone C | M45: Part-Time | N45: Retirement | O45: Speak professor statement result. | P45: Sales | Q45: Field Operations | R45: 35581 | S45: TX | T45: Technician | U45: Female | V45: 12491 | W45: Black | X45: Married | Y45: Needs Improvement | Z45: 3
A46: 3471 | B46: Jonathan | C46: Adkins | D46: 43890 | F46: Area Sales Manager | G46: John Marshall | H46: jonathan.adkins@bilearner.com | I46: CCDR | J46: Active | K46: Part-Time | L46: Zone C | M46: Temporary | N46: Unk | P46: Sales | Q46: Field Operations | R46: 24475 | S46: TX | T46: Foreman | U46: Male | V46: 64350 | W46: Asian | X46: Married | Y46: Fully Meets | Z46: 4
A47: 3472 | B47: Nevaeh | C47: Soto | D47: 44941 | F47: Area Sales Manager | G47: Jessica Chang | H47: nevaeh.soto@bilearner.com | I47: SVG | J47: Active | K47: Contract | L47: Zone C | M47: Full-Time | N47: Unk | P47: Sales | Q47: Project Management - Con | R47: 29963 | S47: TX | T47: Director | U47: Male | V47: 74124 | W47: Other | X47: Married | Y47: Exceeds | Z47: 4
A48: 3473 | B48: Chaim | C48: Mata | D48: 45106 | F48: Area Sales Manager | G48: Desiree Vang | H48: chaim.mata@bilearner.com | I48: EW | J48: Active | K48: Part-Time | L48: Zone A | M48: Temporary | N48: Unk | P48: Sales | Q48: Shop (Fleet) | R48: 18537 | S48: CO | T48: Manager | U48: Male | V48: 33379 | W48: Hispanic | X48: Widowed | Y48: Exceeds | Z48: 2
A49: 3474 | B49: Arely | C49: Patton | D49: 43899 | F49: Area Sales Manager | G49: Andrew Goodman | H49: arely.patton@bilearner.com | I49: MSC | J49: Active | K49: Full-Time | L49: Zone A | M49: Temporary | N49: Unk | P49: Sales | Q49: Catv | R49: 24092 | S49: CO | T49: Laborer | U49: Male | V49: 34481 | W49: Other | X49: Divorced | Y49: Fully Meets | Z49: 2
A50: 3475 | B50: Vance | C50: Trujillo | D50: 44460 | E50: 45029 | F50: Area Sales Manager | G50: Rebecca Simpson | H50: vance.trujillo@bilearner.com | I50: TNS | J50: Active | K50: Full-Time | L50: Zone C | M50: Temporary | N50: Resignation | O50: Expert challenge education air none money wide. | P50: Sales | Q50: General - Con | R50: 21179 | S50: IN | T50: Foreman | U50: Male | V50: 90406 | W50: Asian | X50: Widowed | Y50: Fully Meets | Z50: 2
A51: 3476 | B51: Charlie | C51: Koch | D51: 45089 | E51: 45113 | F51: Area Sales Manager | G51: Samantha Cardenas | H51: charlie.koch@bilearner.com | I51: PYZ | J51: Active | K51: Part-Time | L51: Zone A | M51: Temporary | N51: Voluntary | O51: Buy become improve guess business know. | P51: Sales | Q51: Fielders | R51: 16608 | S51: MA | T51: Engineer | U51: Male | V51: 95774 | W51: Asian | X51: Divorced | Y51: Needs Improvement | Z51: 2
A52: 3477 | B52: Sonny | C52: Horne | D52: 43562 | F52: Area Sales Manager | G52: Nancy Johnson | H52: sonny.horne@bilearner.com | I52: PYZ | J52: Active | K52: Part-Time | L52: Zone A | M52: Full-Time | N52: Unk | P52: IT/IS | Q52: Aerial | R52: 25540 | S52: KY | T52: Laborer | U52: Female | V52: 16058 | W52: Asian | X52: Widowed | Y52: Needs Improvement | Z52: 2
A53: 3478 | B53: Thomas | C53: Chandler | D53: 43360 | E53: 43474 | F53: Area Sales Manager | G53: Richard Hodges | H53: thomas.chandler@bilearner.com | I53: WBL | J53: Active | K53: Full-Time | L53: Zone C | M53: Temporary | N53: Resignation | O53: Read family dark scene scene guess. | P53: Sales | Q53: Wireline Construction | R53: 21103 | S53: KY | T53: Groundman | U53: Female | V53: 45149 | W53: Hispanic | X53: Married | Y53: Fully Meets | Z53: 2
A54: 3479 | B54: Sarai | C54: Stone | D54: 44775 | E54: 45018 | F54: Area Sales Manager | G54: Madison Wilson | H54: sarai.stone@bilearner.com | I54: NEL | J54: Active | K54: Contract | L54: Zone A | M54: Part-Time | N54: Involuntary | O54: Somebody great could yet. | P54: Sales | Q54: Project Management - Con | R54: 22783 | S54: TX | T54: Technician | U54: Female | V54: 96336 | W54: Hispanic | X54: Widowed | Y54: Fully Meets | Z54: 2
A55: 3480 | B55: Jerimiah | C55: Harmon | D55: 44812 | E55: 44850 | F55: Area Sales Manager | G55: Eric King | H55: jerimiah.harmon@bilearner.com | I55: PL | J55: Future Start | K55: Full-Time | L55: Zone C | M55: Temporary | N55: Retirement | O55: View vote contain within fight cup party war. | P55: Sales | Q55: Catv | R55: 17023 | S55: TX | T55: Supervisor | U55: Female | V55: 75671 | W55: Black | X55: Widowed | Y55: Fully Meets | Z55: 1
A56: 3481 | B56: Leland | C56: Allen | D56: 43531 | E56: 44347 | F56: Area Sales Manager | G56: Brandon Harris | H56: leland.allen@bilearner.com | I56: BPC | J56: Future Start | K56: Full-Time | L56: Zone C | M56: Part-Time | N56: Voluntary | O56: Buy house certain wrong research chair. | P56: Sales | Q56: Wireline Construction | R56: 24087 | S56: TX | T56: Splicer | U56: Male | V56: 61149 | W56: Other | X56: Widowed | Y56: Fully Meets | Z56: 4
A57: 3482 | B57: Cristal | C57: Bolton | D57: 43767 | E57: 44234 | F57: Area Sales Manager | G57: Matthew Flores | H57: cristal.bolton@bilearner.com | I57: CCDR | J57: Future Start | K57: Full-Time | L57: Zone A | M57: Temporary | N57: Resignation | O57: Miss onto none our discussion year. | P57: Sales | Q57: Catv | R57: 32915 | S57: TX | T57: Lineman | U57: Male | V57: 57302 | W57: Asian | X57: Divorced | Y57: Needs Improvement | Z57: 2
A58: 3483 | B58: Jaslene | C58: Harding | D58: 44465 | F58: Area Sales Manager | G58: Krystal Hamilton | H58: jaslene.harding@bilearner.com | I58: SVG | J58: Active | K58: Part-Time | L58: Zone B | M58: Temporary | N58: Unk | P58: Sales | Q58: Project Management - Con | R58: 23547 | S58: CO | T58: Coordinator | U58: Male | V58: 42605 | W58: Asian | X58: Widowed | Y58: Fully Meets | Z58: 1
A59: 3484 | B59: Albert | C59: Gonzalez | D59: 43341 | F59: Area Sales Manager | G59: Amber Hernandez | H59: albert.gonzalez@bilearner.com | I59: EW | J59: Active | K59: Part-Time | L59: Zone B | M59: Full-Time | N59: Unk | P59: Sales | Q59: General - Con | R59: 34898 | S59: CO | T59: Model Assistant | U59: Male | V59: 64036 | W59: Other | X59: Single | Y59: Fully Meets | Z59: 4
A60: 3485 | B60: Jaiden | C60: Johnson | D60: 44495 | F60: Area Sales Manager | G60: Patricia Smith | H60: jaiden.johnson@bilearner.com | I60: MSC | J60: Active | K60: Contract | L60: Zone C | M60: Full-Time | N60: Unk | P60: Sales | Q60: Field Operations | R60: 34568 | S60: CO | T60: Laborer | U60: Male | V60: 23173 | W60: White | X60: Widowed | Y60: Fully Meets | Z60: 5
A61: 3486 | B61: Brendon | C61: Mcconnell | D61: 44865 | E61: 45085 | F61: Area Sales Manager | G61: Victoria Krause | H61: brendon.mcconnell@bilearner.com | I61: TNS | J61: Active | K61: Part-Time | L61: Zone C | M61: Temporary | N61: Involuntary | O61: Nature finish modern push former American. | P61: Sales | Q61: Fielders | R61: 33191 | S61: IN | T61: Engineer | U61: Male | V61: 19665 | W61: Other | X61: Widowed | Y61: Fully Meets | Z61: 4
A62: 3487 | B62: Kimora | C62: Parsons | D62: 45000 | F62: Area Sales Manager | G62: Jesse Hunt | H62: kimora.parsons@bilearner.com | I62: BPC | J62: Active | K62: Contract | L62: Zone B | M62: Part-Time | N62: Unk | P62: Sales | Q62: General - Sga | R62: 34366 | S62: KY | T62: Administrator | U62: Female | V62: 41161 | W62: Other | X62: Divorced | Y62: Fully Meets | Z62: 4
A63: 3488 | B63: Willie | C63: Patterson | D63: 44813 | F63: Area Sales Manager | G63: Shane Jones | H63: willie.patterson@bilearner.com | I63: CCDR | J63: Active | K63: Contract | L63: Zone B | M63: Full-Time | N63: Unk | P63: Sales | Q63: Wireline Construction | R63: 35746 | S63: KY | T63: Lineman | U63: Female | V63: 52499 | W63: Asian | X63: Single | Y63: Fully Meets | Z63: 2
A64: 3489 | B64: Devyn | C64: Powers | D64: 44624 | F64: Area Sales Manager | G64: Jessica Murphy | H64: devyn.powers@bilearner.com | I64: EW | J64: Active | K64: Part-Time | L64: Zone A | M64: Temporary | N64: Unk | P64: Sales | Q64: Field Operations | R64: 19481 | S64: TX | T64: Laborer | U64: Female | V64: 25634 | W64: Black | X64: Divorced | Y64: Fully Meets | Z64: 2
A65: 3490 | B65: Weston | C65: Preston | D65: 43507 | F65: Area Sales Manager | G65: Crystal Wallace | H65: weston.preston@bilearner.com | I65: MSC | J65: Active | K65: Part-Time | L65: Zone A | M65: Part-Time | N65: Unk | P65: Sales | Q65: General - Sga | R65: 33429 | S65: TX | T65: Director | U65: Female | V65: 37965 | W65: Hispanic | X65: Divorced | Y65: Fully Meets | Z65: 2
A66: 3491 | B66: Lennon | C66: Buchanan | D66: 44222 | F66: Area Sales Manager | G66: Tina Nelson | H66: lennon.buchanan@bilearner.com | I66: NEL | J66: Active | K66: Contract | L66: Zone B | M66: Full-Time | N66: Unk | P66: Sales | Q66: Field Operations | R66: 26817 | S66: TX | T66: Driver | U66: Male | V66: 39504 | W66: White | X66: Widowed | Y66: Fully Meets | Z66: 5
A67: 3492 | B67: Vicente | C67: Merritt | D67: 43795 | F67: Area Sales Manager | G67: Ashley Smith | H67: vicente.merritt@bilearner.com | I67: PL | J67: Active | K67: Full-Time | L67: Zone C | M67: Full-Time | N67: Unk | P67: Sales | Q67: General - Con | R67: 33977 | S67: CO | T67: Clerk | U67: Male | V67: 31676 | W67: Asian | X67: Married | Y67: Fully Meets | Z67: 1
A68: 3493 | B68: Hugo | C68: Clay | D68: 43661 | F68: Area Sales Manager | G68: Eric Taylor | H68: hugo.clay@bilearner.com | I68: PYZ | J68: Active | K68: Full-Time | L68: Zone C | M68: Full-Time | N68: Unk | P68: Sales | Q68: Project Management - Con | R68: 30789 | S68: CO | T68: Project Manager | U68: Male | V68: 28784 | W68: Asian | X68: Widowed | Y68: Fully Meets | Z68: 5
A69: 3494 | B69: Cohen | C69: Raymond | D69: 44000 | F69: Area Sales Manager | G69: Jacob Snyder | H69: cohen.raymond@bilearner.com | I69: SVG | J69: Active | K69: Contract | L69: Zone B | M69: Full-Time | N69: Unk | P69: Sales | Q69: General - Con | R69: 34373 | S69: CO | T69: Technician | U69: Male | V69: 90983 | W69: Black | X69: Single | Y69: Fully Meets | Z69: 4
A70: 3495 | B70: Tia | C70: Ellis | D70: 45099 | E70: 45129 | F70: Area Sales Manager | G70: Daniel Cabrera | H70: tia.ellis@bilearner.com | I70: TNS | J70: Active | K70: Part-Time | L70: Zone B | M70: Temporary | N70: Retirement | O70: Night company image able suggest. | P70: Sales | Q70: Wireline Construction | R70: 33996 | S70: IN | T70: Laborer | U70: Male | V70: 1115 | W70: Other | X70: Married | Y70: Fully Meets | Z70: 4
A71: 3496 | B71: Aspen | C71: Bentley | D71: 44532 | F71: Area Sales Manager | G71: Barbara Garcia | H71: aspen.bentley@bilearner.com | I71: WBL | J71: Active | K71: Contract | L71: Zone A | M71: Part-Time | N71: Unk | P71: Sales | Q71: General - Sga | R71: 23639 | S71: CA | T71: Administrator | U71: Male | V71: 72233 | W71: Other | X71: Widowed | Y71: Fully Meets | Z71: 5
A72: 3497 | B72: Graham | C72: Rodriguez | D72: 44538 | F72: Area Sales Manager | G72: Kendra Murray | H72: graham.rodriguez@bilearner.com | I72: TNS | J72: Active | K72: Part-Time | L72: Zone C | M72: Temporary | N72: Unk | P72: Sales | Q72: Project Management - Con | R72: 29635 | S72: OR | T72: Lineman | U72: Female | V72: 58210 | W72: Hispanic | X72: Widowed | Y72: Fully Meets | Z72: 1
A73: 3498 | B73: Joel | C73: Mcmillan | D73: 45042 | E73: 45099 | F73: Area Sales Manager | G73: Peter Harvey | H73: joel.mcmillan@bilearner.com | I73: PYZ | J73: Active | K73: Full-Time | L73: Zone A | M73: Full-Time | N73: Voluntary | O73: About allow article. For gas player magazine. | P73: Sales | Q73: General - Sga | R73: 36085 | S73: KY | T73: Laborer | U73: Female | V73: 36087 | W73: White | X73: Widowed | Y73: Fully Meets | Z73: 2
A74: 3499 | B74: Maci | C74: Frost | D74: 43368 | E74: 44550 | F74: Area Sales Manager | G74: Patrick Daniel | H74: maci.frost@bilearner.com | I74: WBL | J74: Active | K74: Part-Time | L74: Zone C | M74: Temporary | N74: Involuntary | O74: Seem hand dog. Us six beyond place fund well. | P74: Sales | Q74: Field Operations | R74: 25949 | S74: KY | T74: Technician | U74: Female | V74: 61457 | W74: Asian | X74: Widowed | Y74: Fully Meets | Z74: 5
A75: 3500 | B75: Nevaeh | C75: Lucas | D75: 43424 | E75: 44003 | F75: Area Sales Manager | G75: Bryan Douglas | H75: nevaeh.lucas@bilearner.com | I75: NEL | J75: Active | K75: Full-Time | L75: Zone B | M75: Part-Time | N75: Voluntary | O75: Game hour boy not write somebody owner. | P75: Sales | Q75: Shop (Fleet) | R75: 36581 | S75: TX | T75: Mechanic | U75: Female | V75: 80424 | W75: White | X75: Divorced | Y75: Fully Meets | Z75: 1
A76: 3501 | B76: Garrett | C76: Zimmerman | D76: 44073 | E76: 44803 | F76: Area Sales Manager | G76: Destiny Hopkins | H76: garrett.zimmerman@bilearner.com | I76: PL | J76: Future Start | K76: Part-Time | L76: Zone A | M76: Part-Time | N76: Retirement | O76: Worker medical commercial participant tough leg. | P76: Sales | Q76: General - Con | R76: 21659 | S76: TX | T76: Technician | U76: Male | V76: 6240 | W76: Other | X76: Widowed | Y76: Fully Meets | Z76: 4
A77: 3502 | B77: Eugene | C77: Marks | D77: 43739 | F77: Area Sales Manager | G77: Angela Morris | H77: eugene.marks@bilearner.com | I77: BPC | J77: Active | K77: Full-Time | L77: Zone C | M77: Temporary | N77: Unk | P77: Sales | Q77: Splicing | R77: 27940 | S77: TX | T77: Electrician | U77: Male | V77: 49914 | W77: White | X77: Married | Y77: Fully Meets | Z77: 1
A78: 3503 | B78: Geovanni | C78: Pugh | D78: 44581 | F78: Area Sales Manager | G78: Erica Franklin | H78: geovanni.pugh@bilearner.com | I78: CCDR | J78: Active | K78: Part-Time | L78: Zone A | M78: Temporary | N78: Unk | P78: Sales | Q78: Project Management - Con | R78: 18836 | S78: CO | T78: Manager | U78: Male | V78: 71319 | W78: Other | X78: Single | Y78: Fully Meets | Z78: 4
A79: 3504 | B79: Javon | C79: Kelley | D79: 44479 | F79: Area Sales Manager | G79: Gabriela Orr | H79: javon.kelley@bilearner.com | I79: SVG | J79: Active | K79: Full-Time | L79: Zone B | M79: Part-Time | N79: Unk | P79: Sales | Q79: General - Con | R79: 29456 | S79: CO | T79: Laborer | U79: Male | V79: 27992 | W79: Hispanic | X79: Married | Y79: Fully Meets | Z79: 2
A80: 3505 | B80: Amaya | C80: Hicks | D80: 44072 | F80: Area Sales Manager | G80: Michael Wilkins | H80: amaya.hicks@bilearner.com | I80: EW | J80: Active | K80: Contract | L80: Zone B | M80: Temporary | N80: Unk | P80: Sales | Q80: Field Operations | R80: 15911 | S80: IN | T80: Groundman | U80: Male | V80: 72324 | W80: Hispanic | X80: Widowed | Y80: Fully Meets | Z80: 1
A81: 3506 | B81: Laila | C81: Woodard | D81: 43704 | E81: 45056 | F81: Area Sales Manager | G81: Jordan Vega | H81: laila.woodard@bilearner.com | I81: MSC | J81: Active | K81: Full-Time | L81: Zone B | M81: Temporary | N81: Voluntary | O81: Fund nor half early miss follow. | P81: Sales | Q81: Field Operations | R81: 32330 | S81: IN | T81: Technician | U81: Male | V81: 38740 | W81: Other | X81: Married | Y81: Fully Meets | Z81: 2
A82: 3507 | B82: Ivan | C82: Huff | D82: 44252 | E82: 45023 | F82: Area Sales Manager | G82: John Miller | H82: ivan.huff@bilearner.com | I82: TNS | J82: Active | K82: Full-Time | L82: Zone A | M82: Full-Time | N82: Retirement | O82: Line later deal stand sometimes too mind. | P82: Sales | Q82: Project Management - Con | R82: 26747 | S82: CA | T82: Manager | U82: Male | V82: 9437 | W82: White | X82: Single | Y82: Fully Meets | Z82: 4
A83: 3508 | B83: Aidan | C83: Harding | D83: 44390 | F83: Area Sales Manager | G83: Trevor Adkins | H83: aidan.harding@bilearner.com | I83: CCDR | J83: Active | K83: Full-Time | L83: Zone B | M83: Part-Time | N83: Unk | P83: Sales | Q83: Aerial | R83: 15487 | S83: OR | T83: Laborer | U83: Male | V83: 9385 | W83: Asian | X83: Single | Y83: Fully Meets | Z83: 5
A84: 3509 | B84: Cruz | C84: Boyer | D84: 44300 | F84: Area Sales Manager | G84: Marcus Hunt | H84: cruz.boyer@bilearner.com | I84: BPC | J84: Active | K84: Part-Time | L84: Zone C | M84: Full-Time | N84: Unk | P84: Sales | Q84: General - Sga | R84: 28433 | S84: KY | T84: Project Controls | U84: Female | V84: 75993 | W84: Black | X84: Married | Y84: Fully Meets | Z84: 2
A85: 3510 | B85: Raven | C85: Koch | D85: 43871 | F85: Area Sales Manager | G85: Jennifer King | H85: raven.koch@bilearner.com | I85: PYZ | J85: Active | K85: Part-Time | L85: Zone A | M85: Full-Time | N85: Unk | P85: Sales | Q85: General - Con | R85: 20745 | S85: KY | T85: Laborer | U85: Female | V85: 65329 | W85: Hispanic | X85: Married | Y85: Fully Meets | Z85: 2
A86: 3511 | B86: Karli | C86: Barker | D86: 44425 | E86: 44561 | F86: Area Sales Manager | G86: Shawn Dudley | H86: karli.barker@bilearner.com | I86: WBL | J86: Active | K86: Part-Time | L86: Zone B | M86: Full-Time | N86: Resignation | O86: Tell paper every. | P86: Sales | Q86: Finance & Accounting | R86: 35479 | S86: KY | T86: Director | U86: Female | V86: 41111 | W86: Asian | X86: Divorced | Y86: Fully Meets | Z86: 4
A87: 3512 | B87: Tyrone | C87: Sosa | D87: 45033 | E87: 45099 | F87: Area Sales Manager | G87: Lindsay Chang | H87: tyrone.sosa@bilearner.com | I87: NEL | J87: Future Start | K87: Contract | L87: Zone C | M87: Temporary | N87: Voluntary | O87: Why sport must page bad. | P87: Sales | Q87: Yard (Material Handling) | R87: 35363 | S87: TX | T87: Coordinator | U87: Female | V87: 58860 | W87: Black | X87: Single | Y87: Fully Meets | Z87: 2
A88: 3513 | B88: Damaris | C88: Cisneros | D88: 44806 | E88: 45070 | F88: Area Sales Manager | G88: Sharon Ruiz | H88: damaris.cisneros@bilearner.com | I88: PL | J88: Future Start | K88: Contract | L88: Zone C | M88: Temporary | N88: Involuntary | O88: Something sense information final building. | P88: Sales | Q88: General - Con | R88: 21867 | S88: TX | T88: Laborer | U88: Male | V88: 93051 | W88: Other | X88: Married | Y88: Fully Meets | Z88: 5
A89: 3514 | B89: Alexus | C89: Estes | D89: 43936 | F89: Area Sales Manager | G89: April Randolph | H89: alexus.estes@bilearner.com | I89: BPC | J89: Active | K89: Full-Time | L89: Zone B | M89: Part-Time | N89: Unk | P89: Sales | Q89: Wireline Construction | R89: 21188 | S89: TX | T89: Manager | U89: Male | V89: 17419 | W89: Asian | X89: Married | Y89: Fully Meets | Z89: 1
A90: 3515 | B90: Kinsley | C90: Flowers | D90: 44629 | E90: 44905 | F90: Area Sales Manager | G90: Mary Reilly | H90: kinsley.flowers@bilearner.com | I90: CCDR | J90: Future Start | K90: Part-Time | L90: Zone A | M90: Part-Time | N90: Retirement | O90: School see rest firm I. | P90: Sales | Q90: Finance & Accounting | R90: 35549 | S90: CO | T90: Controller | U90: Male | V90: 59593 | W90: White | X90: Single | Y90: Fully Meets | Z90: 4
A91: 3516 | B91: Deborah | C91: Love | D91: 44658 | E91: 44948 | F91: Area Sales Manager | G91: Eric Goodman | H91: deborah.love@bilearner.com | I91: SVG | J91: Active | K91: Contract | L91: Zone B | M91: Part-Time | N91: Retirement | O91: Source doctor rock group this. | P91: Sales | Q91: Project Management - Con | R91: 32319 | S91: CO | T91: Coordinator | U91: Male | V91: 96350 | W91: Asian | X91: Divorced | Y91: Fully Meets | Z91: 5
A92: 3517 | B92: Milagros | C92: Francis | D92: 43880 | F92: Area Sales Manager | G92: Caleb Schneider | H92: milagros.francis@bilearner.com | I92: EW | J92: Active | K92: Part-Time | L92: Zone A | M92: Part-Time | N92: Unk | P92: Sales | Q92: Splicing | R92: 15345 | S92: IN | T92: Splicer | U92: Male | V92: 44469 | W92: Hispanic | X92: Widowed | Y92: Fully Meets | Z92: 4
A93: 3518 | B93: Roberto | C93: Michael | D93: 44296 | E93: 44746 | F93: Area Sales Manager | G93: Cheryl Henry | H93: roberto.michael@bilearner.com | I93: MSC | J93: Active | K93: Contract | L93: Zone B | M93: Part-Time | N93: Involuntary | O93: Little imagine career he produce program. | P93: Sales | Q93: General - Eng | R93: 25347 | S93: CA | T93: Coordinator | U93: Female | V93: 13249 | W93: Hispanic | X93: Married | Y93: Fully Meets | Z93: 2
A94: 3519 | B94: Elaine | C94: Ewing | D94: 44549 | E94: 44622 | F94: Area Sales Manager | G94: Dan Hernandez | H94: elaine.ewing@bilearner.com | I94: TNS | J94: Active | K94: Part-Time | L94: Zone C | M94: Temporary | N94: Resignation | O94: Your very trip successful memory to while out. | P94: Sales | Q94: Aerial | R94: 18715 | S94: CA | T94: Groundman | U94: Male | V94: 17123 | W94: Hispanic | X94: Widowed | Y94: Fully Meets | Z94: 2
A95: 3520 | B95: Caiden | C95: Munoz | D95: 44178 | E95: 44939 | F95: Area Sales Manager | G95: Teresa Daniel | H95: caiden.munoz@bilearner.com | I95: TNS | J95: Active | K95: Full-Time | L95: Zone C | M95: Temporary | N95: Involuntary | O95: Red some option. | P95: Sales | Q95: Project Management - Con | R95: 23071 | S95: ND | T95: Manager | U95: Female | V95: 18983 | W95: Black | X95: Divorced | Y95: Fully Meets | Z95: 1
A96: 3521 | B96: Jocelyn | C96: Bradford | D96: 43522 | F96: Area Sales Manager | G96: Melissa Decker | H96: jocelyn.bradford@bilearner.com | I96: WBL | J96: Active | K96: Contract | L96: Zone C | M96: Part-Time | N96: Unk | P96: Sales | Q96: General - Con | R96: 18004 | S96: KY | T96: Electrician | U96: Female | V96: 51795 | W96: Asian | X96: Divorced | Y96: Fully Meets | Z96: 4
A97: 3522 | B97: Marques | C97: Armstrong | D97: 43892 | F97: Area Sales Manager | G97: Michael Nguyen | H97: marques.armstrong@bilearner.com | I97: BPC | J97: Active | K97: Full-Time | L97: Zone C | M97: Part-Time | N97: Unk | P97: Sales | Q97: Splicing | R97: 30601 | S97: KY | T97: Splicer | U97: Female | V97: 34369 | W97: Other | X97: Single | Y97: Fully Meets | Z97: 1
A98: 3523 | B98: Rohan | C98: Chapman | D98: 44372 | E98: 44798 | F98: Area Sales Manager | G98: Tony Mcconnell | H98: rohan.chapman@bilearner.com | I98: CCDR | J98: Active | K98: Full-Time | L98: Zone A | M98: Temporary | N98: Resignation | O98: Theory grow future week house. | P98: Sales | Q98: General - Con | R98: 28843 | S98: KY | T98: Laborer | U98: Female | V98: 23092 | W98: Other | X98: Single | Y98: Fully Meets | Z98: 2
A99: 3524 | B99: Emmanuel | C99: Franklin | D99: 44403 | E99: 44685 | F99: Area Sales Manager | G99: Adam Gibson | H99: emmanuel.franklin@bilearner.com | I99: EW | J99: Future Start | K99: Contract | L99: Zone B | M99: Full-Time | N99: Resignation | O99: Inside week also so. | P99: Sales | Q99: Field Operations | R99: 36475 | S99: TX | T99: Laborer | U99: Male | V99: 6074 | W99: Asian | X99: Divorced | Y99: Fully Meets | Z99: 2
A100: 3525 | B100: Clayton | C100: Mccormick | D100: 44745 | E100: 44936 | F100: Area Sales Manager | G100: Stephanie Duke | H100: clayton.mccormick@bilearner.com | I100: MSC | J100: Future Start | K100: Contract | L100: Zone B | M100: Temporary | N100: Retirement | O100: Surface vote old picture. | P100: Sales | Q100: General - Con | R100: 24501 | S100: TX | T100: Foreman | U100: Male | V100: 72264 | W100: Hispanic | X100: Single | Y100: Fully Meets | Z100: 2
...

Sheet Revisi Data
A1: EmpID | B1: FirstName | C1: LastName | D1: StartDate | E1: ExitDate | F1: Title | G1: Supervisor | H1: ADEmail | I1: BusinessUnit | J1: EmployeeStatus | K1: EmployeeType | L1: PayZone | M1: EmployeeClassificationType | N1: TerminationType | O1: TerminationDescription | P1: DepartmentType | Q1: Division | R1: DOB | S1: State | T1: JobFunctionDescription | U1: GenderCode | V1: LocationCode | W1: RaceDesc | X1: MaritalDesc | Y1: Performance Score | Z1: Current Employee Rating
A2: =TRIM(employee_data!A2) -> 3427 | B2: =TRIM(PROPER(employee_data!B2)) -> Uriah | C2: =TRIM(PROPER(employee_data!C2)) -> Bridges | D2: =DATEVALUE(TEXT(employee_data!D2,"dd/mm/yyyy")) -> 43728 | E2: =IFERROR(DATEVALUE(TEXT(employee_data!E2,"dd/mm/yyyy")),TRIM("")) | F2: =TRIM(employee_data!F2) -> Production Technician I | G2: =TRIM(PROPER(employee_data!G2)) -> Peter Oneill | H2: =TRIM(employee_data!H2) -> uriah.bridges@bilearner.com | I2: =TRIM(UPPER(employee_data!I2)) -> CCDR | J2: =TRIM(PROPER(employee_data!J2)) -> Active | K2: =TRIM(PROPER(employee_data!K2)) -> Contract | L2: =TRIM(PROPER(employee_data!L2)) -> Zone C | M2: =TRIM(PROPER(employee_data!M2)) -> Temporary | N2: =TRIM(PROPER(employee_data!N2)) -> Unk | O2: =TRIM(employee_data!O2) | P2: =TRIM(PROPER(employee_data!P2)) -> Production | Q2: =TRIM(PROPER(employee_data!Q2)) -> Finance & Accounting | R2: =DATEVALUE(TEXT(employee_data!R2,"dd/mm/yyyy")) -> 25483 | S2: =TRIM(UPPER(employee_data!S2)) -> MA | T2: =TRIM(PROPER(employee_data!T2)) -> Accounting | U2: =TRIM(PROPER(employee_data!U2)) -> Female | V2: =TRIM(employee_data!V2) -> 34904 | W2: =TRIM(PROPER(employee_data!W2)) -> White | X2: =TRIM(PROPER(employee_data!X2)) -> Widowed | Y2: =TRIM(PROPER(employee_data!Y2)) -> Fully Meets | Z2: 4
A3: =TRIM(employee_data!A3) -> 3428 | B3: =TRIM(PROPER(employee_data!B3)) -> Paula | C3: =TRIM(PROPER(employee_data!C3)) -> Small | D3: =DATEVALUE(TEXT(employee_data!D3,"dd/mm/yyyy")) -> 44968 | E3: =IFERROR(DATEVALUE(TEXT(employee_data!E3,"dd/mm/yyyy")),TRIM("")) | F3: =TRIM(employee_data!F3) -> Production Technician I | G3: =TRIM(PROPER(employee_data!G3)) -> Renee Mccormick | H3: =TRIM(employee_data!H3) -> paula.small@bilearner.com | I3: =TRIM(UPPER(employee_data!I3)) -> EW | J3: =TRIM(PROPER(employee_data!J3)) -> Active | K3: =TRIM(PROPER(employee_data!K3)) -> Contract | L3: =TRIM(PROPER(employee_data!L3)) -> Zone A | M3: =TRIM(PROPER(employee_data!M3)) -> Part-Time | N3: =TRIM(PROPER(employee_data!N3)) -> Unk | O3: =TRIM(employee_data!O3) | P3: =TRIM(PROPER(employee_data!P3)) -> Production | Q3: =TRIM(PROPER(employee_data!Q3)) -> Aerial | R3: =DATEVALUE(TEXT(employee_data!R3,"dd/mm/yyyy")) -> 23984 | S3: =TRIM(UPPER(employee_data!S3)) -> MA | T3: =TRIM(PROPER(employee_data!T3)) -> Labor | U3: =TRIM(PROPER(employee_data!U3)) -> Male | V3: =TRIM(employee_data!V3) -> 6593 | W3: =TRIM(PROPER(employee_data!W3)) -> Hispanic | X3: =TRIM(PROPER(employee_data!X3)) -> Widowed | Y3: =TRIM(PROPER(employee_data!Y3)) -> Fully Meets | Z3: 3
A4: =TRIM(employee_data!A4) -> 3429 | B4: =TRIM(PROPER(employee_data!B4)) -> Edward | C4: =TRIM(PROPER(employee_data!C4)) -> Buck | D4: =DATEVALUE(TEXT(employee_data!D4,"dd/mm/yyyy")) -> 43444 | E4: =IFERROR(DATEVALUE(TEXT(employee_data!E4,"dd/mm/yyyy")),TRIM("")) | F4: =TRIM(employee_data!F4) -> Area Sales Manager | G4: =TRIM(PROPER(employee_data!G4)) -> Crystal Walker | H4: =TRIM(employee_data!H4) -> edward.buck@bilearner.com | I4: =TRIM(UPPER(employee_data!I4)) -> PL | J4: =TRIM(PROPER(employee_data!J4)) -> Active | K4: =TRIM(PROPER(employee_data!K4)) -> Full-Time | L4: =TRIM(PROPER(employee_data!L4)) -> Zone B | M4: =TRIM(PROPER(employee_data!M4)) -> Part-Time | N4: =TRIM(PROPER(employee_data!N4)) -> Unk | O4: =TRIM(employee_data!O4) | P4: =TRIM(PROPER(employee_data!P4)) -> Sales | Q4: =TRIM(PROPER(employee_data!Q4)) -> General - Sga | R4: =DATEVALUE(TEXT(employee_data!R4,"dd/mm/yyyy")) -> 33517 | S4: =TRIM(UPPER(employee_data!S4)) -> MA | T4: =TRIM(PROPER(employee_data!T4)) -> Assistant | U4: =TRIM(PROPER(employee_data!U4)) -> Male | V4: =TRIM(employee_data!V4) -> 2330 | W4: =TRIM(PROPER(employee_data!W4)) -> Hispanic | X4: =TRIM(PROPER(employee_data!X4)) -> Widowed | Y4: =TRIM(PROPER(employee_data!Y4)) -> Fully Meets | Z4: 4
A5: =TRIM(employee_data!A5) -> 3430 | B5: =TRIM(PROPER(employee_data!B5)) -> Michael | C5: =TRIM(PROPER(employee_data!C5)) -> Riordan | D5: =DATEVALUE(TEXT(employee_data!D5,"dd/mm/yyyy")) -> 44368 | E5: =IFERROR(DATEVALUE(TEXT(employee_data!E5,"dd/mm/yyyy")),TRIM("")) | F5: =TRIM(employee_data!F5) -> Area Sales Manager | G5: =TRIM(PROPER(employee_data!G5)) -> Rebekah Wright | H5: =TRIM(employee_data!H5) -> michael.riordan@bilearner.com | I5: =TRIM(UPPER(employee_data!I5)) -> CCDR | J5: =TRIM(PROPER(employee_data!J5)) -> Active | K5: =TRIM(PROPER(employee_data!K5)) -> Contract | L5: =TRIM(PROPER(employee_data!L5)) -> Zone A | M5: =TRIM(PROPER(employee_data!M5)) -> Full-Time | N5: =TRIM(PROPER(employee_data!N5)) -> Unk | O5: =TRIM(employee_data!O5) | P5: =TRIM(PROPER(employee_data!P5)) -> Sales | Q5: =TRIM(PROPER(employee_data!Q5)) -> Finance & Accounting | R5: =DATEVALUE(TEXT(employee_data!R5,"dd/mm/yyyy")) -> 35889 | S5: =TRIM(UPPER(employee_data!S5)) -> ND | T5: =TRIM(PROPER(employee_data!T5)) -> Clerk | U5: =TRIM(PROPER(employee_data!U5)) -> Male | V5: =TRIM(employee_data!V5) -> 58782 | W5: =TRIM(PROPER(employee_data!W5)) -> Other | X5: =TRIM(PROPER(employee_data!X5)) -> Single | Y5: =TRIM(PROPER(employee_data!Y5)) -> Fully Meets | Z5: 2
A6: =TRIM(employee_data!A6) -> 3431 | B6: =TRIM(PROPER(employee_data!B6)) -> Jasmine | C6: =TRIM(PROPER(employee_data!C6)) -> Onque | D6: =DATEVALUE(TEXT(employee_data!D6,"dd/mm/yyyy")) -> 43645 | E6: =IFERROR(DATEVALUE(TEXT(employee_data!E6,"dd/mm/yyyy")),TRIM("")) | F6: =TRIM(employee_data!F6) -> Area Sales Manager | G6: =TRIM(PROPER(employee_data!G6)) -> Jason Kim | H6: =TRIM(employee_data!H6) -> jasmine.onque@bilearner.com | I6: =TRIM(UPPER(employee_data!I6)) -> TNS | J6: =TRIM(PROPER(employee_data!J6)) -> Active | K6: =TRIM(PROPER(employee_data!K6)) -> Contract | L6: =TRIM(PROPER(employee_data!L6)) -> Zone A | M6: =TRIM(PROPER(employee_data!M6)) -> Temporary | N6: =TRIM(PROPER(employee_data!N6)) -> Unk | O6: =TRIM(employee_data!O6) | P6: =TRIM(PROPER(employee_data!P6)) -> Sales | Q6: =TRIM(PROPER(employee_data!Q6)) -> General - Con | R6: =DATEVALUE(TEXT(employee_data!R6,"dd/mm/yyyy")) -> 25444 | S6: =TRIM(UPPER(employee_data!S6)) -> FL | T6: =TRIM(PROPER(employee_data!T6)) -> Laborer | U6: =TRIM(PROPER(employee_data!U6)) -> Female | V6: =TRIM(employee_data!V6) -> 33174 | W6: =TRIM(PROPER(employee_data!W6)) -> Other | X6: =TRIM(PROPER(employee_data!X6)) -> Married | Y6: =TRIM(PROPER(employee_data!Y6)) -> Fully Meets | Z6: 3
A7: =TRIM(employee_data!A7) -> 3432 | B7: =TRIM(PROPER(employee_data!B7)) -> Maruk | C7: =TRIM(PROPER(employee_data!C7)) -> Fraval | D7: =DATEVALUE(TEXT(employee_data!D7,"dd/mm/yyyy")) -> 43847 | E7: =IFERROR(DATEVALUE(TEXT(employee_data!E7,"dd/mm/yyyy")),TRIM("")) | F7: =TRIM(employee_data!F7) -> Area Sales Manager | G7: =TRIM(PROPER(employee_data!G7)) -> Sheri Campos | H7: =TRIM(employee_data!H7) -> maruk.fraval@bilearner.com | I7: =TRIM(UPPER(employee_data!I7)) -> BPC | J7: =TRIM(PROPER(employee_data!J7)) -> Active | K7: =TRIM(PROPER(employee_data!K7)) -> Contract | L7: =TRIM(PROPER(employee_data!L7)) -> Zone B | M7: =TRIM(PROPER(employee_data!M7)) -> Full-Time | N7: =TRIM(PROPER(employee_data!N7)) -> Unk | O7: =TRIM(employee_data!O7) | P7: =TRIM(PROPER(employee_data!P7)) -> Sales | Q7: =TRIM(PROPER(employee_data!Q7)) -> Field Operations | R7: =DATEVALUE(TEXT(employee_data!R7,"dd/mm/yyyy")) -> 17991 | S7: =TRIM(UPPER(employee_data!S7)) -> CT | T7: =TRIM(PROPER(employee_data!T7)) -> Driver | U7: =TRIM(PROPER(employee_data!U7)) -> Male | V7: =TRIM(employee_data!V7) -> 6050 | W7: =TRIM(PROPER(employee_data!W7)) -> Black | X7: =TRIM(PROPER(employee_data!X7)) -> Married | Y7: =TRIM(PROPER(employee_data!Y7)) -> Fully Meets | Z7: 3
A8: =TRIM(employee_data!A8) -> 3433 | B8: =TRIM(PROPER(employee_data!B8)) -> Latia | C8: =TRIM(PROPER(employee_data!C8)) -> Costa | D8: =DATEVALUE(TEXT(employee_data!D8,"dd/mm/yyyy")) -> 44657 | E8: =IFERROR(DATEVALUE(TEXT(employee_data!E8,"dd/mm/yyyy")),TRIM("")) -> 45110 | F8: =TRIM(employee_data!F8) -> Area Sales Manager | G8: =TRIM(PROPER(employee_data!G8)) -> Jacob Braun | H8: =TRIM(employee_data!H8) -> latia.costa@bilearner.com | I8: =TRIM(UPPER(employee_data!I8)) -> WBL | J8: =TRIM(PROPER(employee_data!J8)) -> Active | K8: =TRIM(PROPER(employee_data!K8)) -> Full-Time | L8: =TRIM(PROPER(employee_data!L8)) -> Zone B | M8: =TRIM(PROPER(employee_data!M8)) -> Temporary | N8: =TRIM(PROPER(employee_data!N8)) -> Involuntary | O8: =TRIM(employee_data!O8) -> Me see picture nature degree benefit. | P8: =TRIM(PROPER(employee_data!P8)) -> Sales | Q8: =TRIM(PROPER(employee_data!Q8)) -> General - Eng | R8: =DATEVALUE(TEXT(employee_data!R8,"dd/mm/yyyy")) -> 15523 | S8: =TRIM(UPPER(employee_data!S8)) -> CA | T8: =TRIM(PROPER(employee_data!T8)) -> Technician | U8: =TRIM(PROPER(employee_data!U8)) -> Female | V8: =TRIM(employee_data!V8) -> 90007 | W8: =TRIM(PROPER(employee_data!W8)) -> Hispanic | X8: =TRIM(PROPER(employee_data!X8)) -> Divorced | Y8: =TRIM(PROPER(employee_data!Y8)) -> Exceeds | Z8: 4
A9: =TRIM(employee_data!A9) -> 3434 | B9: =TRIM(PROPER(employee_data!B9)) -> Sharlene | C9: =TRIM(PROPER(employee_data!C9)) -> Terry | D9: =DATEVALUE(TEXT(employee_data!D9,"dd/mm/yyyy")) -> 44141 | E9: =IFERROR(DATEVALUE(TEXT(employee_data!E9,"dd/mm/yyyy")),TRIM("")) -> 44955 | F9: =TRIM(employee_data!F9) -> Area Sales Manager | G9: =TRIM(PROPER(employee_data!G9)) -> Tracy Marquez | H9: =TRIM(employee_data!H9) -> sharlene.terry@bilearner.com | I9: =TRIM(UPPER(employee_data!I9)) -> CCDR | J9: =TRIM(PROPER(employee_data!J9)) -> Active | K9: =TRIM(PROPER(employee_data!K9)) -> Contract | L9: =TRIM(PROPER(employee_data!L9)) -> Zone C | M9: =TRIM(PROPER(employee_data!M9)) -> Full-Time | N9: =TRIM(PROPER(employee_data!N9)) -> Involuntary | O9: =TRIM(employee_data!O9) -> Blue community type skill story. | P9: =TRIM(PROPER(employee_data!P9)) -> Sales | Q9: =TRIM(PROPER(employee_data!Q9)) -> Engineers | R9: =DATEVALUE(TEXT(employee_data!R9,"dd/mm/yyyy")) -> 20886 | S9: =TRIM(UPPER(employee_data!S9)) -> OR | T9: =TRIM(PROPER(employee_data!T9)) -> Engineer | U9: =TRIM(PROPER(employee_data!U9)) -> Female | V9: =TRIM(employee_data!V9) -> 97756 | W9: =TRIM(PROPER(employee_data!W9)) -> White | X9: =TRIM(PROPER(employee_data!X9)) -> Divorced | Y9: =TRIM(PROPER(employee_data!Y9)) -> Fully Meets | Z9: 2
A10: =TRIM(employee_data!A10) -> 3435 | B10: =TRIM(PROPER(employee_data!B10)) -> Jac | C10: =TRIM(PROPER(employee_data!C10)) -> Mckinzie | D10: =DATEVALUE(TEXT(employee_data!D10,"dd/mm/yyyy")) -> 43330 | E10: =IFERROR(DATEVALUE(TEXT(employee_data!E10,"dd/mm/yyyy")),TRIM("")) | F10: =TRIM(employee_data!F10) -> Area Sales Manager | G10: =TRIM(PROPER(employee_data!G10)) -> Sharon Becker | H10: =TRIM(employee_data!H10) -> jac.mckinzie@bilearner.com | I10: =TRIM(UPPER(employee_data!I10)) -> NEL | J10: =TRIM(PROPER(employee_data!J10)) -> Active | K10: =TRIM(PROPER(employee_data!K10)) -> Contract | L10: =TRIM(PROPER(employee_data!L10)) -> Zone B | M10: =TRIM(PROPER(employee_data!M10)) -> Part-Time | N10: =TRIM(PROPER(employee_data!N10)) -> Unk | O10: =TRIM(employee_data!O10) | P10: =TRIM(PROPER(employee_data!P10)) -> Sales | Q10: =TRIM(PROPER(employee_data!Q10)) -> Executive | R10: =DATEVALUE(TEXT(employee_data!R10,"dd/mm/yyyy")) -> 27164 | S10: =TRIM(UPPER(employee_data!S10)) -> TX | T10: =TRIM(PROPER(employee_data!T10)) -> Executive Assistant | U10: =TRIM(PROPER(employee_data!U10)) -> Male | V10: =TRIM(employee_data!V10) -> 78789 | W10: =TRIM(PROPER(employee_data!W10)) -> Black | X10: =TRIM(PROPER(employee_data!X10)) -> Widowed | Y10: =TRIM(PROPER(employee_data!Y10)) -> Exceeds | Z10: 3
A11: =TRIM(employee_data!A11) -> 3436 | B11: =TRIM(PROPER(employee_data!B11)) -> Joseph | C11: =TRIM(PROPER(employee_data!C11)) -> Martins | D11: =DATEVALUE(TEXT(employee_data!D11,"dd/mm/yyyy")) -> 44582 | E11: =IFERROR(DATEVALUE(TEXT(employee_data!E11,"dd/mm/yyyy")),TRIM("")) -> 45106 | F11: =TRIM(employee_data!F11) -> Area Sales Manager | G11: =TRIM(PROPER(employee_data!G11)) -> George Jenkins | H11: =TRIM(employee_data!H11) -> joseph.martins@bilearner.com | I11: =TRIM(UPPER(employee_data!I11)) -> BPC | J11: =TRIM(PROPER(employee_data!J11)) -> Active | K11: =TRIM(PROPER(employee_data!K11)) -> Part-Time | L11: =TRIM(PROPER(employee_data!L11)) -> Zone B | M11: =TRIM(PROPER(employee_data!M11)) -> Temporary | N11: =TRIM(PROPER(employee_data!N11)) -> Resignation | O11: =TRIM(employee_data!O11) -> Summer personal bag. | P11: =TRIM(PROPER(employee_data!P11)) -> Sales | Q11: =TRIM(PROPER(employee_data!Q11)) -> Engineers | R11: =DATEVALUE(TEXT(employee_data!R11,"dd/mm/yyyy")) -> 18213 | S11: =TRIM(UPPER(employee_data!S11)) -> TX | T11: =TRIM(PROPER(employee_data!T11)) -> Engineer | U11: =TRIM(PROPER(employee_data!U11)) -> Male | V11: =TRIM(employee_data!V11) -> 78207 | W11: =TRIM(PROPER(employee_data!W11)) -> Asian | X11: =TRIM(PROPER(employee_data!X11)) -> Widowed | Y11: =TRIM(PROPER(employee_data!Y11)) -> Fully Meets | Z11: 5
A12: =TRIM(employee_data!A12) -> 3437 | B12: =TRIM(PROPER(employee_data!B12)) -> Myriam | C12: =TRIM(PROPER(employee_data!C12)) -> Givens | D12: =DATEVALUE(TEXT(employee_data!D12,"dd/mm/yyyy")) -> 45142 | E12: =IFERROR(DATEVALUE(TEXT(employee_data!E12,"dd/mm/yyyy")),TRIM("")) | F12: =TRIM(employee_data!F12) -> Area Sales Manager | G12: =TRIM(PROPER(employee_data!G12)) -> Troy White | H12: =TRIM(employee_data!H12) -> myriam.givens@bilearner.com | I12: =TRIM(UPPER(employee_data!I12)) -> SVG | J12: =TRIM(PROPER(employee_data!J12)) -> Active | K12: =TRIM(PROPER(employee_data!K12)) -> Contract | L12: =TRIM(PROPER(employee_data!L12)) -> Zone B | M12: =TRIM(PROPER(employee_data!M12)) -> Temporary | N12: =TRIM(PROPER(employee_data!N12)) -> Unk | O12: =TRIM(employee_data!O12) | P12: =TRIM(PROPER(employee_data!P12)) -> Sales | Q12: =TRIM(PROPER(employee_data!Q12)) -> Field Operations | R12: =DATEVALUE(TEXT(employee_data!R12,"dd/mm/yyyy")) -> 23402 | S12: =TRIM(UPPER(employee_data!S12)) -> IN | T12: =TRIM(PROPER(employee_data!T12)) -> Technician | U12: =TRIM(PROPER(employee_data!U12)) -> Female | V12: =TRIM(employee_data!V12) -> 46204 | W12: =TRIM(PROPER(employee_data!W12)) -> Other | X12: =TRIM(PROPER(employee_data!X12)) -> Single | Y12: =TRIM(PROPER(employee_data!Y12)) -> Fully Meets | Z12: 5
A13: =TRIM(employee_data!A13) -> 3438 | B13: =TRIM(PROPER(employee_data!B13)) -> Dheepa | C13: =TRIM(PROPER(employee_data!C13)) -> Nguyen | D13: =DATEVALUE(TEXT(employee_data!D13,"dd/mm/yyyy")) -> 43322 | E13: =IFERROR(DATEVALUE(TEXT(employee_data!E13,"dd/mm/yyyy")),TRIM("")) -> 43773 | F13: =TRIM(employee_data!F13) -> Area Sales Manager | G13: =TRIM(PROPER(employee_data!G13)) -> Brian Miller | H13: =TRIM(employee_data!H13) -> dheepa.nguyen@bilearner.com | I13: =TRIM(UPPER(employee_data!I13)) -> MSC | J13: =TRIM(PROPER(employee_data!J13)) -> Active | K13: =TRIM(PROPER(employee_data!K13)) -> Full-Time | L13: =TRIM(PROPER(employee_data!L13)) -> Zone C | M13: =TRIM(PROPER(employee_data!M13)) -> Temporary | N13: =TRIM(PROPER(employee_data!N13)) -> Retirement | O13: =TRIM(employee_data!O13) -> Alone once than. More condition pay far. | P13: =TRIM(PROPER(employee_data!P13)) -> Sales | Q13: =TRIM(PROPER(employee_data!Q13)) -> General - Con | R13: =DATEVALUE(TEXT(employee_data!R13,"dd/mm/yyyy")) -> 17629 | S13: =TRIM(UPPER(employee_data!S13)) -> GA | T13: =TRIM(PROPER(employee_data!T13)) -> Technician | U13: =TRIM(PROPER(employee_data!U13)) -> Female | V13: =TRIM(employee_data!V13) -> 30428 | W13: =TRIM(PROPER(employee_data!W13)) -> Asian | X13: =TRIM(PROPER(employee_data!X13)) -> Married | Y13: =TRIM(PROPER(employee_data!Y13)) -> Fully Meets | Z13: 3
... A3001: =TRIM(employee_data!A3001) -> 3426 | B3001: =TRIM(PROPER(employee_data!B3001)) -> Chace | C3001: =TRIM(PROPER(employee_data!C3001)) -> Kerr | D3001: =DATEVALUE(TEXT(employee_data!D3001,"dd/mm/yyyy")) -> 44678 | E3001: =IFERROR(DATEVALUE(TEXT(employee_data!E3001,"dd/mm/yyyy")),TRIM("")) | F3001: =TRIM(employee_data!F3001) -> Production Technician I | G3001: =TRIM(PROPER(employee_data!G3001)) -> Javier Mccall | H3001: =TRIM(employee_data!H3001) -> chace.kerr@bilearner.com | I3001: =TRIM(UPPER(employee_data!I3001)) -> BPC | J3001: =TRIM(PROPER(employee_data!J3001)) -> Active | K3001: =TRIM(PROPER(employee_data!K3001)) -> Full-Time | L3001: =TRIM(PROPER(employee_data!L3001)) -> Zone B | M3001: =TRIM(PROPER(employee_data!M3001)) -> Temporary | N3001: =TRIM(PROPER(employee_data!N3001)) -> Unk | O3001: =TRIM(employee_data!O3001) | P3001: =TRIM(PROPER(employee_data!P3001)) -> Production | Q3001: =TRIM(PROPER(employee_data!Q3001)) -> Field Operations | R3001: =DATEVALUE(TEXT(employee_data!R3001,"dd/mm/yyyy")) -> 33127 | S3001: =TRIM(UPPER(employee_data!S3001)) -> MA | T3001: =TRIM(PROPER(employee_data!T3001)) -> Warehouse Technician | U3001: =TRIM(PROPER(employee_data!U3001)) -> Female | V3001: =TRIM(employee_data!V3001) -> 57487 | W3001: =TRIM(PROPER(employee_data!W3001)) -> White | X3001: =TRIM(PROPER(employee_data!X3001)) -> Married | Y3001: =TRIM(PROPER(employee_data!Y3001)) -> Fully Meets | Z3001: 2

Sheet  FIX DATA PIVOT
A1: EmpID | B1: FirstName | C1: LastName | D1: StartDate | E1: ExitDate | F1: Title | G1: Supervisor | H1: ADEmail | I1: BusinessUnit | J1: EmployeeStatus | K1: EmployeeType | L1: PayZone | M1: EmployeeClassificationType | N1: TerminationType | O1: TerminationDescription | P1: DepartmentType | Q1: Division | R1: DOB | S1: State | T1: JobFunctionDescription | U1: GenderCode | V1: LocationCode | W1: RaceDesc | X1: MaritalDesc | Y1: Performance Score | Z1: Current Employee Rating | AA1: CurrentEmployeeStatus | AB1: Year of Birth | AC1: Umur | AD1: Generasi
A2: 3427 | B2: Uriah | C2: Bridges | D2: 43728 | F2: Production Technician I | G2: Peter Oneill | H2: uriah.bridges@bilearner.com | I2: CCDR | J2: Active | K2: Contract | L2: Zone C | M2: Temporary | N2: Unk | P2: Production | Q2: Finance & Accounting | R2: 25483 | S2: MA | T2: Accounting | U2: Female | V2: 34904 | W2: White | X2: Widowed | Y2: Fully Meets | Z2: 4 | AA2: =IF(E2="","Active","Non-Active") -> Active | AB2: =YEAR(R2) -> 1969 | AC2: =INT(YEARFRAC(R2,"20/04/2026")) -> 56 | AD2: {=_xlfn.IFS(AB2<1965,"Baby Boomers",AB2<1981,"Gen X",AB2<1997,"Millenial",TRUE,("Gen Z"))} -> Gen X
A3: 3428 | B3: Paula | C3: Small | D3: 44968 | F3: Production Technician I | G3: Renee Mccormick | H3: paula.small@bilearner.com | I3: EW | J3: Active | K3: Contract | L3: Zone A | M3: Part-Time | N3: Unk | P3: Production | Q3: Aerial | R3: 23984 | S3: MA | T3: Labor | U3: Male | V3: 6593 | W3: Hispanic | X3: Widowed | Y3: Fully Meets | Z3: 3 | AA3: =IF(E3="","Active","Non-Active") -> Active | AB3: =YEAR(R3) -> 1965 | AC3: =INT(YEARFRAC(R3,"20/04/2026")) -> 60 | AD3: {=_xlfn.IFS(AB3<1965,"Baby Boomers",AB3<1981,"Gen X",AB3<1997,"Millenial",TRUE,("Gen Z"))} -> Gen X | AF3: Formula COUNTIFS untuk menentukan jumlah karyawan yang mendapatkan rating
A4: 3429 | B4: Edward | C4: Buck | D4: 43444 | F4: Area Sales Manager | G4: Crystal Walker | H4: edward.buck@bilearner.com | I4: PL | J4: Active | K4: Full-Time | L4: Zone B | M4: Part-Time | N4: Unk | P4: Sales | Q4: General - Sga | R4: 33517 | S4: MA | T4: Assistant | U4: Male | V4: 2330 | W4: Hispanic | X4: Widowed | Y4: Fully Meets | Z4: 4 | AA4: =IF(E4="","Active","Non-Active") -> Active | AB4: =YEAR(R4) -> 1991 | AC4: =INT(YEARFRAC(R4,"20/04/2026")) -> 34 | AD4: {=_xlfn.IFS(AB4<1965,"Baby Boomers",AB4<1981,"Gen X",AB4<1997,"Millenial",TRUE,("Gen Z"))} -> Millenial
A5: 3430 | B5: Michael | C5: Riordan | D5: 44368 | F5: Area Sales Manager | G5: Rebekah Wright | H5: michael.riordan@bilearner.com | I5: CCDR | J5: Active | K5: Contract | L5: Zone A | M5: Full-Time | N5: Unk | P5: Sales | Q5: Finance & Accounting | R5: 35889 | S5: ND | T5: Clerk | U5: Male | V5: 58782 | W5: Other | X5: Single | Y5: Fully Meets | Z5: 2 | AA5: =IF(E5="","Active","Non-Active") -> Active | AB5: =YEAR(R5) -> 1998 | AC5: =INT(YEARFRAC(R5,"20/04/2026")) -> 28 | AD5: {=_xlfn.IFS(AB5<1965,"Baby Boomers",AB5<1981,"Gen X",AB5<1997,"Millenial",TRUE,("Gen Z"))} -> Gen Z | AF5: Rating | AG5: Jumlah
A6: 3431 | B6: Jasmine | C6: Onque | D6: 43645 | F6: Area Sales Manager | G6: Jason Kim | H6: jasmine.onque@bilearner.com | I6: TNS | J6: Active | K6: Contract | L6: Zone A | M6: Temporary | N6: Unk | P6: Sales | Q6: General - Con | R6: 25444 | S6: FL | T6: Laborer | U6: Female | V6: 33174 | W6: Other | X6: Married | Y6: Fully Meets | Z6: 3 | AA6: =IF(E6="","Active","Non-Active") -> Active | AB6: =YEAR(R6) -> 1969 | AC6: =INT(YEARFRAC(R6,"20/04/2026")) -> 56 | AD6: {=_xlfn.IFS(AB6<1965,"Baby Boomers",AB6<1981,"Gen X",AB6<1997,"Millenial",TRUE,("Gen Z"))} -> Gen X | AF6: {=_xlfn.UNIQUE(Table1[Current Employee Rating])} -> 4 | AG6: =COUNTIF(Table1[Current Employee Rating],"4") -> 419
A7: 3432 | B7: Maruk | C7: Fraval | D7: 43847 | F7: Area Sales Manager | G7: Sheri Campos | H7: maruk.fraval@bilearner.com | I7: BPC | J7: Active | K7: Contract | L7: Zone B | M7: Full-Time | N7: Unk | P7: Sales | Q7: Field Operations | R7: 17991 | S7: CT | T7: Driver | U7: Male | V7: 6050 | W7: Black | X7: Married | Y7: Fully Meets | Z7: 3 | AA7: =IF(E7="","Active","Non-Active") -> Active | AB7: =YEAR(R7) -> 1949 | AC7: =INT(YEARFRAC(R7,"20/04/2026")) -> 77 | AD7: {=_xlfn.IFS(AB7<1965,"Baby Boomers",AB7<1981,"Gen X",AB7<1997,"Millenial",TRUE,("Gen Z"))} -> Baby Boomers | AF7: 3 | AG7: =COUNTIF(Table1[Current Employee Rating],"3") -> 1530
A8: 3433 | B8: Latia | C8: Costa | D8: 44657 | E8: 45110 | F8: Area Sales Manager | G8: Jacob Braun | H8: latia.costa@bilearner.com | I8: WBL | J8: Active | K8: Full-Time | L8: Zone B | M8: Temporary | N8: Involuntary | O8: Me see picture nature degree benefit. | P8: Sales | Q8: General - Eng | R8: 15523 | S8: CA | T8: Technician | U8: Female | V8: 90007 | W8: Hispanic | X8: Divorced | Y8: Exceeds | Z8: 4 | AA8: =IF(E8="","Active","Non-Active") -> Non-Active | AB8: =YEAR(R8) -> 1942 | AC8: =INT(YEARFRAC(R8,"20/04/2026")) -> 83 | AD8: {=_xlfn.IFS(AB8<1965,"Baby Boomers",AB8<1981,"Gen X",AB8<1997,"Millenial",TRUE,("Gen Z"))} -> Baby Boomers | AF8: 2 | AG8: =COUNTIF(Table1[Current Employee Rating],"2") -> 510
A9: 3434 | B9: Sharlene | C9: Terry | D9: 44141 | E9: 44955 | F9: Area Sales Manager | G9: Tracy Marquez | H9: sharlene.terry@bilearner.com | I9: CCDR | J9: Active | K9: Contract | L9: Zone C | M9: Full-Time | N9: Involuntary | O9: Blue community type skill story. | P9: Sales | Q9: Engineers | R9: 20886 | S9: OR | T9: Engineer | U9: Female | V9: 97756 | W9: White | X9: Divorced | Y9: Fully Meets | Z9: 2 | AA9: =IF(E9="","Active","Non-Active") -> Non-Active | AB9: =YEAR(R9) -> 1957 | AC9: =INT(YEARFRAC(R9,"20/04/2026")) -> 69 | AD9: {=_xlfn.IFS(AB9<1965,"Baby Boomers",AB9<1981,"Gen X",AB9<1997,"Millenial",TRUE,("Gen Z"))} -> Baby Boomers | AF9: 5 | AG9: =COUNTIF(Table1[Current Employee Rating],"5") -> 270
A10: 3435 | B10: Jac | C10: Mckinzie | D10: 43330 | F10: Area Sales Manager | G10: Sharon Becker | H10: jac.mckinzie@bilearner.com | I10: NEL | J10: Active | K10: Contract | L10: Zone B | M10: Part-Time | N10: Unk | P10: Sales | Q10: Executive | R10: 27164 | S10: TX | T10: Executive Assistant | U10: Male | V10: 78789 | W10: Black | X10: Widowed | Y10: Exceeds | Z10: 3 | AA10: =IF(E10="","Active","Non-Active") -> Active | AB10: =YEAR(R10) -> 1974 | AC10: =INT(YEARFRAC(R10,"20/04/2026")) -> 51 | AD10: {=_xlfn.IFS(AB10<1965,"Baby Boomers",AB10<1981,"Gen X",AB10<1997,"Millenial",TRUE,("Gen Z"))} -> Gen X | AF10: 1 | AG10: =COUNTIF(Table1[Current Employee Rating],"1") -> 271
A11: 3436 | B11: Joseph | C11: Martins | D11: 44582 | E11: 45106 | F11: Area Sales Manager | G11: George Jenkins | H11: joseph.martins@bilearner.com | I11: BPC | J11: Active | K11: Part-Time | L11: Zone B | M11: Temporary | N11: Resignation | O11: Summer personal bag. | P11: Sales | Q11: Engineers | R11: 18213 | S11: TX | T11: Engineer | U11: Male | V11: 78207 | W11: Asian | X11: Widowed | Y11: Fully Meets | Z11: 5 | AA11: =IF(E11="","Active","Non-Active") -> Non-Active | AB11: =YEAR(R11) -> 1949 | AC11: =INT(YEARFRAC(R11,"20/04/2026")) -> 76 | AD11: {=_xlfn.IFS(AB11<1965,"Baby Boomers",AB11<1981,"Gen X",AB11<1997,"Millenial",TRUE,("Gen Z"))} -> Baby Boomers
A12: 3437 | B12: Myriam | C12: Givens | D12: 45142 | F12: Area Sales Manager | G12: Troy White | H12: myriam.givens@bilearner.com | I12: SVG | J12: Active | K12: Contract | L12: Zone B | M12: Temporary | N12: Unk | P12: Sales | Q12: Field Operations | R12: 23402 | S12: IN | T12: Technician | U12: Female | V12: 46204 | W12: Other | X12: Single | Y12: Fully Meets | Z12: 5 | AA12: =IF(E12="","Active","Non-Active") -> Active | AB12: =YEAR(R12) -> 1964 | AC12: =INT(YEARFRAC(R12,"20/04/2026")) -> 62 | AD12: {=_xlfn.IFS(AB12<1965,"Baby Boomers",AB12<1981,"Gen X",AB12<1997,"Millenial",TRUE,("Gen Z"))} -> Baby Boomers
A13: 3438 | B13: Dheepa | C13: Nguyen | D13: 43322 | E13: 43773 | F13: Area Sales Manager | G13: Brian Miller | H13: dheepa.nguyen@bilearner.com | I13: MSC | J13: Active | K13: Full-Time | L13: Zone C | M13: Temporary | N13: Retirement | O13: Alone once than. More condition pay far. | P13: Sales | Q13: General - Con | R13: 17629 | S13: GA | T13: Technician | U13: Female | V13: 30428 | W13: Asian | X13: Married | Y13: Fully Meets | Z13: 3 | AA13: =IF(E13="","Active","Non-Active") -> Non-Active | AB13: =YEAR(R13) -> 1948 | AC13: =INT(YEARFRAC(R13,"20/04/2026")) -> 78 | AD13: {=_xlfn.IFS(AB13<1965,"Baby Boomers",AB13<1981,"Gen X",AB13<1997,"Millenial",TRUE,("Gen Z"))} -> Baby Boomers
A14: 3439 | B14: Bartholemew | C14: Khemmich | D14: 44706 | E14: 44892 | F14: Area Sales Manager | G14: Charles Parks | H14: bartholemew.khemmich@bilearner.com | I14: EW | J14: Active | K14: Full-Time | L14: Zone A | M14: Temporary | N14: Involuntary | O14: Foot in theory minute recognize test. | P14: Sales | Q14: Splicing | R14: 29914 | S14: CO | T14: Splicer | U14: Male | V14: 80820 | W14: Other | X14: Single | Y14: Fully Meets | Z14: 3 | AA14: =IF(E14="","Active","Non-Active") -> Non-Active | AB14: =YEAR(R14) -> 1981 | AC14: =INT(YEARFRAC(R14,"20/04/2026")) -> 44 | AD14: {=_xlfn.IFS(AB14<1965,"Baby Boomers",AB14<1981,"Gen X",AB14<1997,"Millenial",TRUE,("Gen Z"))} -> Millenial
A15: 3440 | B15: Xana | C15: Potts | D15: 43804 | E15: 44974 | F15: Area Sales Manager | G15: Gregory Walker | H15: xana.potts@bilearner.com | I15: CCDR | J15: Active | K15: Contract | L15: Zone A | M15: Full-Time | N15: Resignation | O15: Degree wish science when thing week old. | P15: Sales | Q15: Finance & Accounting | R15: 18938 | S15: KY | T15: Controller | U15: Female | V15: 40220 | W15: White | X15: Divorced | Y15: Fully Meets | Z15: 3 | AA15: =IF(E15="","Active","Non-Active") -> Non-Active | AB15: =YEAR(R15) -> 1951 | AC15: =INT(YEARFRAC(R15,"20/04/2026")) -> 74 | AD15: {=_xlfn.IFS(AB15<1965,"Baby Boomers",AB15<1981,"Gen X",AB15<1997,"Millenial",TRUE,("Gen Z"))} -> Baby Boomers
A16: 3441 | B16: Prater | C16: Jeremy | D16: 43583 | F16: Area Sales Manager | G16: Tyler Lewis | H16: prater.jeremy@bilearner.com | I16: BPC | J16: Active | K16: Part-Time | L16: Zone A | M16: Part-Time | N16: Unk | P16: Sales | Q16: General - Con | R16: 32833 | S16: NV | T16: Lineman | U16: Male | V16: 89139 | W16: Asian | X16: Widowed | Y16: Exceeds | Z16: 4 | AA16: =IF(E16="","Active","Non-Active") -> Active | AB16: =YEAR(R16) -> 1989 | AC16: =INT(YEARFRAC(R16,"20/04/2026")) -> 36 | AD16: {=_xlfn.IFS(AB16<1965,"Baby Boomers",AB16<1981,"Gen X",AB16<1997,"Millenial",TRUE,("Gen Z"))} -> Millenial
A17: 3442 | B17: Kaylah | C17: Moon | D17: 43655 | E17: 44728 | F17: Area Sales Manager | G17: Ashley Scott | H17: kaylah.moon@bilearner.com | I17: PYZ | J17: Active | K17: Full-Time | L17: Zone A | M17: Full-Time | N17: Retirement | O17: Fear particular method stage. | P17: It/Is | Q17: Field Operations | R17: 19322 | S17: MA | T17: Laborer | U17: Male | V17: 2810 | W17: Black | X17: Single | Y17: Exceeds | Z17: 2 | AA17: =IF(E17="","Active","Non-Active") -> Non-Active | AB17: =YEAR(R17) -> 1952 | AC17: =INT(YEARFRAC(R17,"20/04/2026")) -> 73 | AD17: {=_xlfn.IFS(AB17<1965,"Baby Boomers",AB17<1981,"Gen X",AB17<1997,"Millenial",TRUE,("Gen Z"))} -> Baby Boomers
A18: 3443 | B18: Kristen | C18: Tate | D18: 44291 | E18: 45058 | F18: Area Sales Manager | G18: Lauren Jones | H18: kristen.tate@bilearner.com | I18: WBL | J18: Active | K18: Full-Time | L18: Zone C | M18: Part-Time | N18: Voluntary | O18: Wall body wonder successful. | P18: It/Is | Q18: Project Management - Con | R18: 34432 | S18: KY | T18: Coordinator | U18: Male | V18: 2621 | W18: Asian | X18: Widowed | Y18: Fully Meets | Z18: 3 | AA18: =IF(E18="","Active","Non-Active") -> Non-Active | AB18: =YEAR(R18) -> 1994 | AC18: =INT(YEARFRAC(R18,"20/04/2026")) -> 32 | AD18: {=_xlfn.IFS(AB18<1965,"Baby Boomers",AB18<1981,"Gen X",AB18<1997,"Millenial",TRUE,("Gen Z"))} -> Millenial
A19: 3444 | B19: Bobby | C19: Rodgers | D19: 44528 | E19: 44596 | F19: Area Sales Manager | G19: Matthew Jackson | H19: bobby.rodgers@bilearner.com | I19: NEL | J19: Active | K19: Contract | L19: Zone A | M19: Part-Time | N19: Voluntary | O19: Visit foot nearly radio treatment. | P19: Sales | Q19: Engineers | R19: 30635 | S19: KY | T19: Director | U19: Male | V19: 44553 | W19: Other | X19: Widowed | Y19: Fully Meets | Z19: 3 | AA19: =IF(E19="","Active","Non-Active") -> Non-Active | AB19: =YEAR(R19) -> 1983 | AC19: =INT(YEARFRAC(R19,"20/04/2026")) -> 42 | AD19: {=_xlfn.IFS(AB19<1965,"Baby Boomers",AB19<1981,"Gen X",AB19<1997,"Millenial",TRUE,("Gen Z"))} -> Millenial
A20: 3445 | B20: Reid | C20: Park | D20: 44212 | F20: Area Sales Manager | G20: Michelle Mitchell | H20: reid.park@bilearner.com | I20: PL | J20: Active | K20: Contract | L20: Zone C | M20: Full-Time | N20: Unk | P20: Sales | Q20: Project Management - Con | R20: 31388 | S20: KY | T20: Supervisor | U20: Female | V20: 5360 | W20: Other | X20: Married | Y20: Exceeds | Z20: 4 | AA20: =IF(E20="","Active","Non-Active") -> Active | AB20: =YEAR(R20) -> 1985 | AC20: =INT(YEARFRAC(R20,"20/04/2026")) -> 40 | AD20: {=_xlfn.IFS(AB20<1965,"Baby Boomers",AB20<1981,"Gen X",AB20<1997,"Millenial",TRUE,("Gen Z"))} -> Millenial
A21: 3446 | B21: Hector | C21: Dalton | D21: 44432 | F21: Area Sales Manager | G21: Sydney French | H21: hector.dalton@bilearner.com | I21: BPC | J21: Active | K21: Part-Time | L21: Zone A | M21: Part-Time | N21: Unk | P21: Sales | Q21: Field Operations | R21: 35186 | S21: TX | T21: Driller | U21: Female | V21: 16325 | W21: White | X21: Divorced | Y21: Exceeds | Z21: 2 | AA21: =IF(E21="","Active","Non-Active") -> Active | AB21: =YEAR(R21) -> 1996 | AC21: =INT(YEARFRAC(R21,"20/04/2026")) -> 29 | AD21: {=_xlfn.IFS(AB21<1965,"Baby Boomers",AB21<1981,"Gen X",AB21<1997,"Millenial",TRUE,("Gen Z"))} -> Millenial
A22: 3447 | B22: Mariela | C22: Schultz | D22: 43977 | E22: 45095 | F22: Area Sales Manager | G22: Michelle Evans Md | H22: mariela.schultz@bilearner.com | I22: CCDR | J22: Future Start | K22: Part-Time | L22: Zone C | M22: Part-Time | N22: Involuntary | O22: Unit pass office southern break one. | P22: Sales | Q22: General - Con | R22: 23424 | S22: TX | T22: Technician | U22: Female | V22: 43481 | W22: Asian | X22: Widowed | Y22: Fully Meets | Z22: 3 | AA22: =IF(E22="","Active","Non-Active") -> Non-Active | AB22: =YEAR(R22) -> 1964 | AC22: =INT(YEARFRAC(R22,"20/04/2026")) -> 62 | AD22: {=_xlfn.IFS(AB22<1965,"Baby Boomers",AB22<1981,"Gen X",AB22<1997,"Millenial",TRUE,("Gen Z"))} -> Baby Boomers
A23: 3448 | B23: Angela | C23: Molina | D23: 43739 | E23: 44141 | F23: Area Sales Manager | G23: Patricia Cook | H23: angela.molina@bilearner.com | I23: SVG | J23: Future Start | K23: Full-Time | L23: Zone A | M23: Temporary | N23: Retirement | O23: List class mind. | P23: Sales | Q23: Engineers | R23: 21317 | S23: TX | T23: Specialist | U23: Male | V23: 50705 | W23: Asian | X23: Widowed | Y23: Fully Meets | Z23: 3 | AA23: =IF(E23="","Active","Non-Active") -> Non-Active | AB23: =YEAR(R23) -> 1958 | AC23: =INT(YEARFRAC(R23,"20/04/2026")) -> 67 | AD23: {=_xlfn.IFS(AB23<1965,"Baby Boomers",AB23<1981,"Gen X",AB23<1997,"Millenial",TRUE,("Gen Z"))} -> Baby Boomers
A24: 3449 | B24: Gerald | C24: Preston | D24: 45056 | E24: 45073 | F24: Area Sales Manager | G24: Ashley Reeves | H24: gerald.preston@bilearner.com | I24: EW | J24: Future Start | K24: Contract | L24: Zone B | M24: Temporary | N24: Involuntary | O24: Price third parent evening. | P24: Sales | Q24: General - Eng | R24: 33865 | S24: CO | T24: Technician | U24: Male | V24: 5168 | W24: Black | X24: Single | Y24: Fully Meets | Z24: 5 | AA24: =IF(E24="","Active","Non-Active") -> Non-Active | AB24: =YEAR(R24) -> 1992 | AC24: =INT(YEARFRAC(R24,"20/04/2026")) -> 33 | AD24: {=_xlfn.IFS(AB24<1965,"Baby Boomers",AB24<1981,"Gen X",AB24<1997,"Millenial",TRUE,("Gen Z"))} -> Millenial
A25: 3450 | B25: Reilly | C25: Moyer | D25: 44075 | E25: 44899 | F25: Area Sales Manager | G25: Stanley Harvey | H25: reilly.moyer@bilearner.com | I25: MSC | J25: Active | K25: Contract | L25: Zone C | M25: Temporary | N25: Resignation | O25: Cause military a sense. Doctor property may. | P25: Sales | Q25: Field Operations | R25: 34557 | S25: CO | T25: Operator | U25: Male | V25: 11765 | W25: Other | X25: Single | Y25: Exceeds | Z25: 2 | AA25: =IF(E25="","Active","Non-Active") -> Non-Active | AB25: =YEAR(R25) -> 1994 | AC25: =INT(YEARFRAC(R25,"20/04/2026")) -> 31 | AD25: {=_xlfn.IFS(AB25<1965,"Baby Boomers",AB25<1981,"Gen X",AB25<1997,"Millenial",TRUE,("Gen Z"))} -> Millenial
A26: 3451 | B26: Carlee | C26: French | D26: 44245 | E26: 44876 | F26: Area Sales Manager | G26: Michael Bradshaw | H26: carlee.french@bilearner.com | I26: TNS | J26: Active | K26: Contract | L26: Zone C | M26: Full-Time | N26: Voluntary | O26: Station another son positive. | P26: Sales | Q26: General - Con | R26: 24852 | S26: CO | T26: Technician | U26: Male | V26: 71071 | W26: Other | X26: Divorced | Y26: Exceeds | Z26: 3 | AA26: =IF(E26="","Active","Non-Active") -> Non-Active | AB26: =YEAR(R26) -> 1968 | AC26: =INT(YEARFRAC(R26,"20/04/2026")) -> 58 | AD26: {=_xlfn.IFS(AB26<1965,"Baby Boomers",AB26<1981,"Gen X",AB26<1997,"Millenial",TRUE,("Gen Z"))} -> Gen X
A27: 3452 | B27: Jaydon | C27: Blackburn | D27: 44873 | F27: Area Sales Manager | G27: Debbie Crosby | H27: jaydon.blackburn@bilearner.com | I27: PYZ | J27: Active | K27: Part-Time | L27: Zone A | M27: Part-Time | N27: Unk | P27: Sales | Q27: General - Con | R27: 17174 | S27: IN | T27: Foreman | U27: Male | V27: 12122 | W27: Black | X27: Divorced | Y27: Fully Meets | Z27: 2 | AA27: =IF(E27="","Active","Non-Active") -> Active | AB27: =YEAR(R27) -> 1947 | AC27: =INT(YEARFRAC(R27,"20/04/2026")) -> 79 | AD27: {=_xlfn.IFS(AB27<1965,"Baby Boomers",AB27<1981,"Gen X",AB27<1997,"Millenial",TRUE,("Gen Z"))} -> Baby Boomers
A28: 3453 | B28: Bridger | C28: Carter | D28: 44847 | F28: Area Sales Manager | G28: Elizabeth Taylor | H28: bridger.carter@bilearner.com | I28: WBL | J28: Active | K28: Contract | L28: Zone C | M28: Part-Time | N28: Unk | P28: Sales | Q28: Fielders | R28: 30048 | S28: MA | T28: Engineer | U28: Male | V28: 87065 | W28: White | X28: Widowed | Y28: Fully Meets | Z28: 4 | AA28: =IF(E28="","Active","Non-Active") -> Active | AB28: =YEAR(R28) -> 1982 | AC28: =INT(YEARFRAC(R28,"20/04/2026")) -> 44 | AD28: {=_xlfn.IFS(AB28<1965,"Baby Boomers",AB28<1981,"Gen X",AB28<1997,"Millenial",TRUE,("Gen Z"))} -> Millenial
A29: 3454 | B29: Leon | C29: Beard | D29: 44815 | F29: Area Sales Manager | G29: Brian Dunlap | H29: leon.beard@bilearner.com | I29: PYZ | J29: Active | K29: Full-Time | L29: Zone C | M29: Full-Time | N29: Unk | P29: It/Is | Q29: General - Con | R29: 25597 | S29: KY | T29: Foreman | U29: Male | V29: 10415 | W29: Hispanic | X29: Married | Y29: Needs Improvement | Z29: 4 | AA29: =IF(E29="","Active","Non-Active") -> Active | AB29: =YEAR(R29) -> 1970 | AC29: =INT(YEARFRAC(R29,"20/04/2026")) -> 56 | AD29: {=_xlfn.IFS(AB29<1965,"Baby Boomers",AB29<1981,"Gen X",AB29<1997,"Millenial",TRUE,("Gen Z"))} -> Gen X
A30: 3455 | B30: Charity | C30: Miranda | D30: 44376 | E30: 44747 | F30: Area Sales Manager | G30: Daniel Rodriguez | H30: charity.miranda@bilearner.com | I30: WBL | J30: Active | K30: Full-Time | L30: Zone C | M30: Temporary | N30: Resignation | O30: Pm local take example fund. Small heavy listen. | P30: Sales | Q30: Project Management - Eng | R30: 36178 | S30: KY | T30: Manager | U30: Male | V30: 3763 | W30: Other | X30: Widowed | Y30: Exceeds | Z30: 4 | AA30: =IF(E30="","Active","Non-Active") -> Non-Active | AB30: =YEAR(R30) -> 1999 | AC30: =INT(YEARFRAC(R30,"20/04/2026")) -> 27 | AD30: {=_xlfn.IFS(AB30<1965,"Baby Boomers",AB30<1981,"Gen X",AB30<1997,"Millenial",TRUE,("Gen Z"))} -> Gen Z
A31: 3456 | B31: Axel | C31: Howe | D31: 44991 | F31: Area Sales Manager | G31: Martin Hammond | H31: axel.howe@bilearner.com | I31: NEL | J31: Active | K31: Full-Time | L31: Zone A | M31: Temporary | N31: Unk | P31: Sales | Q31: Field Operations | R31: 17070 | S31: KY | T31: Technician | U31: Female | V31: 79623 | W31: Black | X31: Divorced | Y31: Fully Meets | Z31: 3 | AA31: =IF(E31="","Active","Non-Active") -> Active | AB31: =YEAR(R31) -> 1946 | AC31: =INT(YEARFRAC(R31,"20/04/2026")) -> 79 | AD31: {=_xlfn.IFS(AB31<1965,"Baby Boomers",AB31<1981,"Gen X",AB31<1997,"Millenial",TRUE,("Gen Z"))} -> Baby Boomers
A32: 3457 | B32: Milton | C32: Wall | D32: 44099 | F32: Area Sales Manager | G32: Sara Bell | H32: milton.wall@bilearner.com | I32: PL | J32: Active | K32: Full-Time | L32: Zone B | M32: Temporary | N32: Unk | P32: Sales | Q32: Engineers | R32: 17402 | S32: KY | T32: Technician | U32: Female | V32: 69189 | W32: White | X32: Divorced | Y32: Needs Improvement | Z32: 3 | AA32: =IF(E32="","Active","Non-Active") -> Active | AB32: =YEAR(R32) -> 1947 | AC32: =INT(YEARFRAC(R32,"20/04/2026")) -> 78 | AD32: {=_xlfn.IFS(AB32<1965,"Baby Boomers",AB32<1981,"Gen X",AB32<1997,"Millenial",TRUE,("Gen Z"))} -> Baby Boomers
A33: 3458 | B33: Cory | C33: Robinson | D33: 44679 | E33: 45070 | F33: Area Sales Manager | G33: Elizabeth Anderson | H33: cory.robinson@bilearner.com | I33: BPC | J33: Future Start | K33: Contract | L33: Zone A | M33: Full-Time | N33: Voluntary | O33: Several young whether that expert. | P33: Sales | Q33: Field Operations | R33: 35289 | S33: TX | T33: Laborer | U33: Female | V33: 5194 | W33: Hispanic | X33: Single | Y33: Needs Improvement | Z33: 3 | AA33: =IF(E33="","Active","Non-Active") -> Non-Active | AB33: =YEAR(R33) -> 1996 | AC33: =INT(YEARFRAC(R33,"20/04/2026")) -> 29 | AD33: {=_xlfn.IFS(AB33<1965,"Baby Boomers",AB33<1981,"Gen X",AB33<1997,"Millenial",TRUE,("Gen Z"))} -> Millenial
A34: 3459 | B34: Saniya | C34: Yu | D34: 44304 | E34: 44733 | F34: Area Sales Manager | G34: Erin Bailey | H34: saniya.yu@bilearner.com | I34: CCDR | J34: Future Start | K34: Part-Time | L34: Zone A | M34: Full-Time | N34: Retirement | O34: Science end approach democratic treatment. | P34: Sales | Q34: General - Con | R34: 16111 | S34: TX | T34: Splicer | U34: Male | V34: 8779 | W34: Black | X34: Widowed | Y34: Exceeds | Z34: 2 | AA34: =IF(E34="","Active","Non-Active") -> Non-Active | AB34: =YEAR(R34) -> 1944 | AC34: =INT(YEARFRAC(R34,"20/04/2026")) -> 82 | AD34: {=_xlfn.IFS(AB34<1965,"Baby Boomers",AB34<1981,"Gen X",AB34<1997,"Millenial",TRUE,("Gen Z"))} -> Baby Boomers
A35: 3460 | B35: Alisa | C35: James | D35: 43880 | F35: Area Sales Manager | G35: Dennis Henderson | H35: alisa.james@bilearner.com | I35: SVG | J35: Active | K35: Full-Time | L35: Zone A | M35: Full-Time | N35: Unk | P35: Sales | Q35: Aerial | R35: 16112 | S35: TX | T35: Lineman | U35: Male | V35: 74682 | W35: Asian | X35: Married | Y35: Fully Meets | Z35: 3 | AA35: =IF(E35="","Active","Non-Active") -> Active | AB35: =YEAR(R35) -> 1944 | AC35: =INT(YEARFRAC(R35,"20/04/2026")) -> 82 | AD35: {=_xlfn.IFS(AB35<1965,"Baby Boomers",AB35<1981,"Gen X",AB35<1997,"Millenial",TRUE,("Gen Z"))} -> Baby Boomers
A36: 3461 | B36: Lincoln | C36: Compton | D36: 43664 | E36: 44470 | F36: Area Sales Manager | G36: Tammy Conner | H36: lincoln.compton@bilearner.com | I36: EW | J36: Future Start | K36: Full-Time | L36: Zone C | M36: Part-Time | N36: Resignation | O36: Base scene central unit per argue. Might last of. | P36: Sales | Q36: General - Con | R36: 35793 | S36: CO | T36: Foreman | U36: Male | V36: 78046 | W36: Hispanic | X36: Married | Y36: Needs Improvement | Z36: 1 | AA36: =IF(E36="","Active","Non-Active") -> Non-Active | AB36: =YEAR(R36) -> 1997 | AC36: =INT(YEARFRAC(R36,"20/04/2026")) -> 28 | AD36: {=_xlfn.IFS(AB36<1965,"Baby Boomers",AB36<1981,"Gen X",AB36<1997,"Millenial",TRUE,("Gen Z"))} -> Gen Z
A37: 3462 | B37: Aliana | C37: Nolan | D37: 43356 | E37: 44456 | F37: Area Sales Manager | G37: Brianna Mathews | H37: aliana.nolan@bilearner.com | I37: MSC | J37: Active | K37: Contract | L37: Zone A | M37: Full-Time | N37: Involuntary | O37: Yourself book budget product. | P37: Sales | Q37: Field Operations | R37: 15562 | S37: CO | T37: Coordinator | U37: Male | V37: 27270 | W37: Hispanic | X37: Divorced | Y37: Needs Improvement | Z37: 3 | AA37: =IF(E37="","Active","Non-Active") -> Non-Active | AB37: =YEAR(R37) -> 1942 | AC37: =INT(YEARFRAC(R37,"20/04/2026")) -> 83 | AD37: {=_xlfn.IFS(AB37<1965,"Baby Boomers",AB37<1981,"Gen X",AB37<1997,"Millenial",TRUE,("Gen Z"))} -> Baby Boomers
A38: 3463 | B38: Kayden | C38: Dodson | D38: 43951 | E38: 44395 | F38: Area Sales Manager | G38: Jessica Peters | H38: kayden.dodson@bilearner.com | I38: TNS | J38: Active | K38: Part-Time | L38: Zone A | M38: Temporary | N38: Retirement | O38: Paper can score else investment. | P38: Sales | Q38: Field Operations | R38: 18800 | S38: IN | T38: Tower Hand | U38: Male | V38: 12703 | W38: Hispanic | X38: Single | Y38: Fully Meets | Z38: 1 | AA38: =IF(E38="","Active","Non-Active") -> Non-Active | AB38: =YEAR(R38) -> 1951 | AC38: =INT(YEARFRAC(R38,"20/04/2026")) -> 74 | AD38: {=_xlfn.IFS(AB38<1965,"Baby Boomers",AB38<1981,"Gen X",AB38<1997,"Millenial",TRUE,("Gen Z"))} -> Baby Boomers
A39: 3464 | B39: James | C39: Duke | D39: 43437 | E39: 44813 | F39: Area Sales Manager | G39: Mark Harris | H39: james.duke@bilearner.com | I39: PYZ | J39: Active | K39: Contract | L39: Zone B | M39: Full-Time | N39: Involuntary | O39: Stuff different color how. | P39: Sales | Q39: Shop (Fleet) | R39: 35963 | S39: MA | T39: Mechanic | U39: Male | V39: 66835 | W39: Black | X39: Widowed | Y39: Needs Improvement | Z39: 5 | AA39: =IF(E39="","Active","Non-Active") -> Non-Active | AB39: =YEAR(R39) -> 1998 | AC39: =INT(YEARFRAC(R39,"20/04/2026")) -> 27 | AD39: {=_xlfn.IFS(AB39<1965,"Baby Boomers",AB39<1981,"Gen X",AB39<1997,"Millenial",TRUE,("Gen Z"))} -> Gen Z
A40: 3465 | B40: Willow | C40: Stuart | D40: 44508 | F40: Area Sales Manager | G40: Elizabeth Tapia | H40: willow.stuart@bilearner.com | I40: WBL | J40: Active | K40: Full-Time | L40: Zone B | M40: Full-Time | N40: Unk | P40: Sales | Q40: General - Con | R40: 22653 | S40: MA | T40: Flagger | U40: Male | V40: 66150 | W40: Asian | X40: Divorced | Y40: Needs Improvement | Z40: 3 | AA40: =IF(E40="","Active","Non-Active") -> Active | AB40: =YEAR(R40) -> 1962 | AC40: =INT(YEARFRAC(R40,"20/04/2026")) -> 64 | AD40: {=_xlfn.IFS(AB40<1965,"Baby Boomers",AB40<1981,"Gen X",AB40<1997,"Millenial",TRUE,("Gen Z"))} -> Baby Boomers
A41: 3466 | B41: Clayton | C41: Walker | D41: 44664 | E41: 45026 | F41: Area Sales Manager | G41: Jon Holden | H41: clayton.walker@bilearner.com | I41: PYZ | J41: Active | K41: Part-Time | L41: Zone C | M41: Full-Time | N41: Retirement | O41: Sign figure employee card education. | P41: It/Is | Q41: Aerial | R41: 28881 | S41: KY | T41: Supervisor | U41: Male | V41: 64288 | W41: Other | X41: Married | Y41: Exceeds | Z41: 4 | AA41: =IF(E41="","Active","Non-Active") -> Non-Active | AB41: =YEAR(R41) -> 1979 | AC41: =INT(YEARFRAC(R41,"20/04/2026")) -> 47 | AD41: {=_xlfn.IFS(AB41<1965,"Baby Boomers",AB41<1981,"Gen X",AB41<1997,"Millenial",TRUE,("Gen Z"))} -> Gen X
A42: 3467 | B42: Celia | C42: Curtis | D42: 43957 | F42: Area Sales Manager | G42: Michael Odonnell | H42: celia.curtis@bilearner.com | I42: WBL | J42: Active | K42: Contract | L42: Zone A | M42: Part-Time | N42: Unk | P42: Sales | Q42: Fielders | R42: 31911 | S42: KY | T42: Engineer | U42: Female | V42: 94333 | W42: Asian | X42: Divorced | Y42: Exceeds | Z42: 1 | AA42: =IF(E42="","Active","Non-Active") -> Active | AB42: =YEAR(R42) -> 1987 | AC42: =INT(YEARFRAC(R42,"20/04/2026")) -> 38 | AD42: {=_xlfn.IFS(AB42<1965,"Baby Boomers",AB42<1981,"Gen X",AB42<1997,"Millenial",TRUE,("Gen Z"))} -> Millenial
A43: 3468 | B43: Valentin | C43: Reilly | D43: 43717 | F43: Area Sales Manager | G43: Andres Parker | H43: valentin.reilly@bilearner.com | I43: NEL | J43: Active | K43: Contract | L43: Zone B | M43: Temporary | N43: Unk | P43: Sales | Q43: Wireline Construction | R43: 35911 | S43: KY | T43: Foreman | U43: Female | V43: 45453 | W43: Black | X43: Single | Y43: Fully Meets | Z43: 4 | AA43: =IF(E43="","Active","Non-Active") -> Active | AB43: =YEAR(R43) -> 1998 | AC43: =INT(YEARFRAC(R43,"20/04/2026")) -> 27 | AD43: {=_xlfn.IFS(AB43<1965,"Baby Boomers",AB43<1981,"Gen X",AB43<1997,"Millenial",TRUE,("Gen Z"))} -> Gen Z
A44: 3469 | B44: Ryland | C44: Shepherd | D44: 44041 | E44: 44931 | F44: Area Sales Manager | G44: James Berry | H44: ryland.shepherd@bilearner.com | I44: PL | J44: Future Start | K44: Contract | L44: Zone B | M44: Full-Time | N44: Resignation | O44: Right cut matter arrive difference. | P44: Sales | Q44: Field Operations | R44: 16489 | S44: TX | T44: Driver | U44: Female | V44: 81905 | W44: Asian | X44: Divorced | Y44: Needs Improvement | Z44: 3 | AA44: =IF(E44="","Active","Non-Active") -> Non-Active | AB44: =YEAR(R44) -> 1945 | AC44: =INT(YEARFRAC(R44,"20/04/2026")) -> 81 | AD44: {=_xlfn.IFS(AB44<1965,"Baby Boomers",AB44<1981,"Gen X",AB44<1997,"Millenial",TRUE,("Gen Z"))} -> Baby Boomers
A45: 3470 | B45: Esteban | C45: Gilbert | D45: 43418 | E45: 43766 | F45: Area Sales Manager | G45: Gail Ali | H45: esteban.gilbert@bilearner.com | I45: BPC | J45: Future Start | K45: Contract | L45: Zone C | M45: Part-Time | N45: Retirement | O45: Speak professor statement result. | P45: Sales | Q45: Field Operations | R45: 35581 | S45: TX | T45: Technician | U45: Female | V45: 12491 | W45: Black | X45: Married | Y45: Needs Improvement | Z45: 3 | AA45: =IF(E45="","Active","Non-Active") -> Non-Active | AB45: =YEAR(R45) -> 1997 | AC45: =INT(YEARFRAC(R45,"20/04/2026")) -> 28 | AD45: {=_xlfn.IFS(AB45<1965,"Baby Boomers",AB45<1981,"Gen X",AB45<1997,"Millenial",TRUE,("Gen Z"))} -> Gen Z
A46: 3471 | B46: Jonathan | C46: Adkins | D46: 43890 | F46: Area Sales Manager | G46: John Marshall | H46: jonathan.adkins@bilearner.com | I46: CCDR | J46: Active | K46: Part-Time | L46: Zone C | M46: Temporary | N46: Unk | P46: Sales | Q46: Field Operations | R46: 24475 | S46: TX | T46: Foreman | U46: Male | V46: 64350 | W46: Asian | X46: Married | Y46: Fully Meets | Z46: 4 | AA46: =IF(E46="","Active","Non-Active") -> Active | AB46: =YEAR(R46) -> 1967 | AC46: =INT(YEARFRAC(R46,"20/04/2026")) -> 59 | AD46: {=_xlfn.IFS(AB46<1965,"Baby Boomers",AB46<1981,"Gen X",AB46<1997,"Millenial",TRUE,("Gen Z"))} -> Gen X
A47: 3472 | B47: Nevaeh | C47: Soto | D47: 44941 | F47: Area Sales Manager | G47: Jessica Chang | H47: nevaeh.soto@bilearner.com | I47: SVG | J47: Active | K47: Contract | L47: Zone C | M47: Full-Time | N47: Unk | P47: Sales | Q47: Project Management - Con | R47: 29963 | S47: TX | T47: Director | U47: Male | V47: 74124 | W47: Other | X47: Married | Y47: Exceeds | Z47: 4 | AA47: =IF(E47="","Active","Non-Active") -> Active | AB47: =YEAR(R47) -> 1982 | AC47: =INT(YEARFRAC(R47,"20/04/2026")) -> 44 | AD47: {=_xlfn.IFS(AB47<1965,"Baby Boomers",AB47<1981,"Gen X",AB47<1997,"Millenial",TRUE,("Gen Z"))} -> Millenial
A48: 3473 | B48: Chaim | C48: Mata | D48: 45106 | F48: Area Sales Manager | G48: Desiree Vang | H48: chaim.mata@bilearner.com | I48: EW | J48: Active | K48: Part-Time | L48: Zone A | M48: Temporary | N48: Unk | P48: Sales | Q48: Shop (Fleet) | R48: 18537 | S48: CO | T48: Manager | U48: Male | V48: 33379 | W48: Hispanic | X48: Widowed | Y48: Exceeds | Z48: 2 | AA48: =IF(E48="","Active","Non-Active") -> Active | AB48: =YEAR(R48) -> 1950 | AC48: =INT(YEARFRAC(R48,"20/04/2026")) -> 75 | AD48: {=_xlfn.IFS(AB48<1965,"Baby Boomers",AB48<1981,"Gen X",AB48<1997,"Millenial",TRUE,("Gen Z"))} -> Baby Boomers
A49: 3474 | B49: Arely | C49: Patton | D49: 43899 | F49: Area Sales Manager | G49: Andrew Goodman | H49: arely.patton@bilearner.com | I49: MSC | J49: Active | K49: Full-Time | L49: Zone A | M49: Temporary | N49: Unk | P49: Sales | Q49: Catv | R49: 24092 | S49: CO | T49: Laborer | U49: Male | V49: 34481 | W49: Other | X49: Divorced | Y49: Fully Meets | Z49: 2 | AA49: =IF(E49="","Active","Non-Active") -> Active | AB49: =YEAR(R49) -> 1965 | AC49: =INT(YEARFRAC(R49,"20/04/2026")) -> 60 | AD49: {=_xlfn.IFS(AB49<1965,"Baby Boomers",AB49<1981,"Gen X",AB49<1997,"Millenial",TRUE,("Gen Z"))} -> Gen X
A50: 3475 | B50: Vance | C50: Trujillo | D50: 44460 | E50: 45029 | F50: Area Sales Manager | G50: Rebecca Simpson | H50: vance.trujillo@bilearner.com | I50: TNS | J50: Active | K50: Full-Time | L50: Zone C | M50: Temporary | N50: Resignation | O50: Expert challenge education air none money wide. | P50: Sales | Q50: General - Con | R50: 21179 | S50: IN | T50: Foreman | U50: Male | V50: 90406 | W50: Asian | X50: Widowed | Y50: Fully Meets | Z50: 2 | AA50: =IF(E50="","Active","Non-Active") -> Non-Active | AB50: =YEAR(R50) -> 1957 | AC50: =INT(YEARFRAC(R50,"20/04/2026")) -> 68 | AD50: {=_xlfn.IFS(AB50<1965,"Baby Boomers",AB50<1981,"Gen X",AB50<1997,"Millenial",TRUE,("Gen Z"))} -> Baby Boomers
A51: 3476 | B51: Charlie | C51: Koch | D51: 45089 | E51: 45113 | F51: Area Sales Manager | G51: Samantha Cardenas | H51: charlie.koch@bilearner.com | I51: PYZ | J51: Active | K51: Part-Time | L51: Zone A | M51: Temporary | N51: Voluntary | O51: Buy become improve guess business know. | P51: Sales | Q51: Fielders | R51: 16608 | S51: MA | T51: Engineer | U51: Male | V51: 95774 | W51: Asian | X51: Divorced | Y51: Needs Improvement | Z51: 2 | AA51: =IF(E51="","Active","Non-Active") -> Non-Active | AB51: =YEAR(R51) -> 1945 | AC51: =INT(YEARFRAC(R51,"20/04/2026")) -> 80 | AD51: {=_xlfn.IFS(AB51<1965,"Baby Boomers",AB51<1981,"Gen X",AB51<1997,"Millenial",TRUE,("Gen Z"))} -> Baby Boomers
A52: 3477 | B52: Sonny | C52: Horne | D52: 43562 | F52: Area Sales Manager | G52: Nancy Johnson | H52: sonny.horne@bilearner.com | I52: PYZ | J52: Active | K52: Part-Time | L52: Zone A | M52: Full-Time | N52: Unk | P52: It/Is | Q52: Aerial | R52: 25540 | S52: KY | T52: Laborer | U52: Female | V52: 16058 | W52: Asian | X52: Widowed | Y52: Needs Improvement | Z52: 2 | AA52: =IF(E52="","Active","Non-Active") -> Active | AB52: =YEAR(R52) -> 1969 | AC52: =INT(YEARFRAC(R52,"20/04/2026")) -> 56 | AD52: {=_xlfn.IFS(AB52<1965,"Baby Boomers",AB52<1981,"Gen X",AB52<1997,"Millenial",TRUE,("Gen Z"))} -> Gen X
A53: 3478 | B53: Thomas | C53: Chandler | D53: 43360 | E53: 43474 | F53: Area Sales Manager | G53: Richard Hodges | H53: thomas.chandler@bilearner.com | I53: WBL | J53: Active | K53: Full-Time | L53: Zone C | M53: Temporary | N53: Resignation | O53: Read family dark scene scene guess. | P53: Sales | Q53: Wireline Construction | R53: 21103 | S53: KY | T53: Groundman | U53: Female | V53: 45149 | W53: Hispanic | X53: Married | Y53: Fully Meets | Z53: 2 | AA53: =IF(E53="","Active","Non-Active") -> Non-Active | AB53: =YEAR(R53) -> 1957 | AC53: =INT(YEARFRAC(R53,"20/04/2026")) -> 68 | AD53: {=_xlfn.IFS(AB53<1965,"Baby Boomers",AB53<1981,"Gen X",AB53<1997,"Millenial",TRUE,("Gen Z"))} -> Baby Boomers
A54: 3479 | B54: Sarai | C54: Stone | D54: 44775 | E54: 45018 | F54: Area Sales Manager | G54: Madison Wilson | H54: sarai.stone@bilearner.com | I54: NEL | J54: Active | K54: Contract | L54: Zone A | M54: Part-Time | N54: Involuntary | O54: Somebody great could yet. | P54: Sales | Q54: Project Management - Con | R54: 22783 | S54: TX | T54: Technician | U54: Female | V54: 96336 | W54: Hispanic | X54: Widowed | Y54: Fully Meets | Z54: 2 | AA54: =IF(E54="","Active","Non-Active") -> Non-Active | AB54: =YEAR(R54) -> 1962 | AC54: =INT(YEARFRAC(R54,"20/04/2026")) -> 63 | AD54: {=_xlfn.IFS(AB54<1965,"Baby Boomers",AB54<1981,"Gen X",AB54<1997,"Millenial",TRUE,("Gen Z"))} -> Baby Boomers
A55: 3480 | B55: Jerimiah | C55: Harmon | D55: 44812 | E55: 44850 | F55: Area Sales Manager | G55: Eric King | H55: jerimiah.harmon@bilearner.com | I55: PL | J55: Future Start | K55: Full-Time | L55: Zone C | M55: Temporary | N55: Retirement | O55: View vote contain within fight cup party war. | P55: Sales | Q55: Catv | R55: 17023 | S55: TX | T55: Supervisor | U55: Female | V55: 75671 | W55: Black | X55: Widowed | Y55: Fully Meets | Z55: 1 | AA55: =IF(E55="","Active","Non-Active") -> Non-Active | AB55: =YEAR(R55) -> 1946 | AC55: =INT(YEARFRAC(R55,"20/04/2026")) -> 79 | AD55: {=_xlfn.IFS(AB55<1965,"Baby Boomers",AB55<1981,"Gen X",AB55<1997,"Millenial",TRUE,("Gen Z"))} -> Baby Boomers
A56: 3481 | B56: Leland | C56: Allen | D56: 43531 | E56: 44347 | F56: Area Sales Manager | G56: Brandon Harris | H56: leland.allen@bilearner.com | I56: BPC | J56: Future Start | K56: Full-Time | L56: Zone C | M56: Part-Time | N56: Voluntary | O56: Buy house certain wrong research chair. | P56: Sales | Q56: Wireline Construction | R56: 24087 | S56: TX | T56: Splicer | U56: Male | V56: 61149 | W56: Other | X56: Widowed | Y56: Fully Meets | Z56: 4 | AA56: =IF(E56="","Active","Non-Active") -> Non-Active | AB56: =YEAR(R56) -> 1965 | AC56: =INT(YEARFRAC(R56,"20/04/2026")) -> 60 | AD56: {=_xlfn.IFS(AB56<1965,"Baby Boomers",AB56<1981,"Gen X",AB56<1997,"Millenial",TRUE,("Gen Z"))} -> Gen X
A57: 3482 | B57: Cristal | C57: Bolton | D57: 43767 | E57: 44234 | F57: Area Sales Manager | G57: Matthew Flores | H57: cristal.bolton@bilearner.com | I57: CCDR | J57: Future Start | K57: Full-Time | L57: Zone A | M57: Temporary | N57: Resignation | O57: Miss onto none our discussion year. | P57: Sales | Q57: Catv | R57: 32915 | S57: TX | T57: Lineman | U57: Male | V57: 57302 | W57: Asian | X57: Divorced | Y57: Needs Improvement | Z57: 2 | AA57: =IF(E57="","Active","Non-Active") -> Non-Active | AB57: =YEAR(R57) -> 1990 | AC57: =INT(YEARFRAC(R57,"20/04/2026")) -> 36 | AD57: {=_xlfn.IFS(AB57<1965,"Baby Boomers",AB57<1981,"Gen X",AB57<1997,"Millenial",TRUE,("Gen Z"))} -> Millenial
A58: 3483 | B58: Jaslene | C58: Harding | D58: 44465 | F58: Area Sales Manager | G58: Krystal Hamilton | H58: jaslene.harding@bilearner.com | I58: SVG | J58: Active | K58: Part-Time | L58: Zone B | M58: Temporary | N58: Unk | P58: Sales | Q58: Project Management - Con | R58: 23547 | S58: CO | T58: Coordinator | U58: Male | V58: 42605 | W58: Asian | X58: Widowed | Y58: Fully Meets | Z58: 1 | AA58: =IF(E58="","Active","Non-Active") -> Active | AB58: =YEAR(R58) -> 1964 | AC58: =INT(YEARFRAC(R58,"20/04/2026")) -> 61 | AD58: {=_xlfn.IFS(AB58<1965,"Baby Boomers",AB58<1981,"Gen X",AB58<1997,"Millenial",TRUE,("Gen Z"))} -> Baby Boomers
A59: 3484 | B59: Albert | C59: Gonzalez | D59: 43341 | F59: Area Sales Manager | G59: Amber Hernandez | H59: albert.gonzalez@bilearner.com | I59: EW | J59: Active | K59: Part-Time | L59: Zone B | M59: Full-Time | N59: Unk | P59: Sales | Q59: General - Con | R59: 34898 | S59: CO | T59: Model Assistant | U59: Male | V59: 64036 | W59: Other | X59: Single | Y59: Fully Meets | Z59: 4 | AA59: =IF(E59="","Active","Non-Active") -> Active | AB59: =YEAR(R59) -> 1995 | AC59: =INT(YEARFRAC(R59,"20/04/2026")) -> 30 | AD59: {=_xlfn.IFS(AB59<1965,"Baby Boomers",AB59<1981,"Gen X",AB59<1997,"Millenial",TRUE,("Gen Z"))} -> Millenial
A60: 3485 | B60: Jaiden | C60: Johnson | D60: 44495 | F60: Area Sales Manager | G60: Patricia Smith | H60: jaiden.johnson@bilearner.com | I60: MSC | J60: Active | K60: Contract | L60: Zone C | M60: Full-Time | N60: Unk | P60: Sales | Q60: Field Operations | R60: 34568 | S60: CO | T60: Laborer | U60: Male | V60: 23173 | W60: White | X60: Widowed | Y60: Fully Meets | Z60: 5 | AA60: =IF(E60="","Active","Non-Active") -> Active | AB60: =YEAR(R60) -> 1994 | AC60: =INT(YEARFRAC(R60,"20/04/2026")) -> 31 | AD60: {=_xlfn.IFS(AB60<1965,"Baby Boomers",AB60<1981,"Gen X",AB60<1997,"Millenial",TRUE,("Gen Z"))} -> Millenial
A61: 3486 | B61: Brendon | C61: Mcconnell | D61: 44865 | E61: 45085 | F61: Area Sales Manager | G61: Victoria Krause | H61: brendon.mcconnell@bilearner.com | I61: TNS | J61: Active | K61: Part-Time | L61: Zone C | M61: Temporary | N61: Involuntary | O61: Nature finish modern push former American. | P61: Sales | Q61: Fielders | R61: 33191 | S61: IN | T61: Engineer | U61: Male | V61: 19665 | W61: Other | X61: Widowed | Y61: Fully Meets | Z61: 4 | AA61: =IF(E61="","Active","Non-Active") -> Non-Active | AB61: =YEAR(R61) -> 1990 | AC61: =INT(YEARFRAC(R61,"20/04/2026")) -> 35 | AD61: {=_xlfn.IFS(AB61<1965,"Baby Boomers",AB61<1981,"Gen X",AB61<1997,"Millenial",TRUE,("Gen Z"))} -> Millenial
A62: 3487 | B62: Kimora | C62: Parsons | D62: 45000 | F62: Area Sales Manager | G62: Jesse Hunt | H62: kimora.parsons@bilearner.com | I62: BPC | J62: Active | K62: Contract | L62: Zone B | M62: Part-Time | N62: Unk | P62: Sales | Q62: General - Sga | R62: 34366 | S62: KY | T62: Administrator | U62: Female | V62: 41161 | W62: Other | X62: Divorced | Y62: Fully Meets | Z62: 4 | AA62: =IF(E62="","Active","Non-Active") -> Active | AB62: =YEAR(R62) -> 1994 | AC62: =INT(YEARFRAC(R62,"20/04/2026")) -> 32 | AD62: {=_xlfn.IFS(AB62<1965,"Baby Boomers",AB62<1981,"Gen X",AB62<1997,"Millenial",TRUE,("Gen Z"))} -> Millenial
A63: 3488 | B63: Willie | C63: Patterson | D63: 44813 | F63: Area Sales Manager | G63: Shane Jones | H63: willie.patterson@bilearner.com | I63: CCDR | J63: Active | K63: Contract | L63: Zone B | M63: Full-Time | N63: Unk | P63: Sales | Q63: Wireline Construction | R63: 35746 | S63: KY | T63: Lineman | U63: Female | V63: 52499 | W63: Asian | X63: Single | Y63: Fully Meets | Z63: 2 | AA63: =IF(E63="","Active","Non-Active") -> Active | AB63: =YEAR(R63) -> 1997 | AC63: =INT(YEARFRAC(R63,"20/04/2026")) -> 28 | AD63: {=_xlfn.IFS(AB63<1965,"Baby Boomers",AB63<1981,"Gen X",AB63<1997,"Millenial",TRUE,("Gen Z"))} -> Gen Z
A64: 3489 | B64: Devyn | C64: Powers | D64: 44624 | F64: Area Sales Manager | G64: Jessica Murphy | H64: devyn.powers@bilearner.com | I64: EW | J64: Active | K64: Part-Time | L64: Zone A | M64: Temporary | N64: Unk | P64: Sales | Q64: Field Operations | R64: 19481 | S64: TX | T64: Laborer | U64: Female | V64: 25634 | W64: Black | X64: Divorced | Y64: Fully Meets | Z64: 2 | AA64: =IF(E64="","Active","Non-Active") -> Active | AB64: =YEAR(R64) -> 1953 | AC64: =INT(YEARFRAC(R64,"20/04/2026")) -> 72 | AD64: {=_xlfn.IFS(AB64<1965,"Baby Boomers",AB64<1981,"Gen X",AB64<1997,"Millenial",TRUE,("Gen Z"))} -> Baby Boomers
A65: 3490 | B65: Weston | C65: Preston | D65: 43507 | F65: Area Sales Manager | G65: Crystal Wallace | H65: weston.preston@bilearner.com | I65: MSC | J65: Active | K65: Part-Time | L65: Zone A | M65: Part-Time | N65: Unk | P65: Sales | Q65: General - Sga | R65: 33429 | S65: TX | T65: Director | U65: Female | V65: 37965 | W65: Hispanic | X65: Divorced | Y65: Fully Meets | Z65: 2 | AA65: =IF(E65="","Active","Non-Active") -> Active | AB65: =YEAR(R65) -> 1991 | AC65: =INT(YEARFRAC(R65,"20/04/2026")) -> 34 | AD65: {=_xlfn.IFS(AB65<1965,"Baby Boomers",AB65<1981,"Gen X",AB65<1997,"Millenial",TRUE,("Gen Z"))} -> Millenial
A66: 3491 | B66: Lennon | C66: Buchanan | D66: 44222 | F66: Area Sales Manager | G66: Tina Nelson | H66: lennon.buchanan@bilearner.com | I66: NEL | J66: Active | K66: Contract | L66: Zone B | M66: Full-Time | N66: Unk | P66: Sales | Q66: Field Operations | R66: 26817 | S66: TX | T66: Driver | U66: Male | V66: 39504 | W66: White | X66: Widowed | Y66: Fully Meets | Z66: 5 | AA66: =IF(E66="","Active","Non-Active") -> Active | AB66: =YEAR(R66) -> 1973 | AC66: =INT(YEARFRAC(R66,"20/04/2026")) -> 52 | AD66: {=_xlfn.IFS(AB66<1965,"Baby Boomers",AB66<1981,"Gen X",AB66<1997,"Millenial",TRUE,("Gen Z"))} -> Gen X
A67: 3492 | B67: Vicente | C67: Merritt | D67: 43795 | F67: Area Sales Manager | G67: Ashley Smith | H67: vicente.merritt@bilearner.com | I67: PL | J67: Active | K67: Full-Time | L67: Zone C | M67: Full-Time | N67: Unk | P67: Sales | Q67: General - Con | R67: 33977 | S67: CO | T67: Clerk | U67: Male | V67: 31676 | W67: Asian | X67: Married | Y67: Fully Meets | Z67: 1 | AA67: =IF(E67="","Active","Non-Active") -> Active | AB67: =YEAR(R67) -> 1993 | AC67: =INT(YEARFRAC(R67,"20/04/2026")) -> 33 | AD67: {=_xlfn.IFS(AB67<1965,"Baby Boomers",AB67<1981,"Gen X",AB67<1997,"Millenial",TRUE,("Gen Z"))} -> Millenial
A68: 3493 | B68: Hugo | C68: Clay | D68: 43661 | F68: Area Sales Manager | G68: Eric Taylor | H68: hugo.clay@bilearner.com | I68: PYZ | J68: Active | K68: Full-Time | L68: Zone C | M68: Full-Time | N68: Unk | P68: Sales | Q68: Project Management - Con | R68: 30789 | S68: CO | T68: Project Manager | U68: Male | V68: 28784 | W68: Asian | X68: Widowed | Y68: Fully Meets | Z68: 5 | AA68: =IF(E68="","Active","Non-Active") -> Active | AB68: =YEAR(R68) -> 1984 | AC68: =INT(YEARFRAC(R68,"20/04/2026")) -> 42 | AD68: {=_xlfn.IFS(AB68<1965,"Baby Boomers",AB68<1981,"Gen X",AB68<1997,"Millenial",TRUE,("Gen Z"))} -> Millenial
A69: 3494 | B69: Cohen | C69: Raymond | D69: 44000 | F69: Area Sales Manager | G69: Jacob Snyder | H69: cohen.raymond@bilearner.com | I69: SVG | J69: Active | K69: Contract | L69: Zone B | M69: Full-Time | N69: Unk | P69: Sales | Q69: General - Con | R69: 34373 | S69: CO | T69: Technician | U69: Male | V69: 90983 | W69: Black | X69: Single | Y69: Fully Meets | Z69: 4 | AA69: =IF(E69="","Active","Non-Active") -> Active | AB69: =YEAR(R69) -> 1994 | AC69: =INT(YEARFRAC(R69,"20/04/2026")) -> 32 | AD69: {=_xlfn.IFS(AB69<1965,"Baby Boomers",AB69<1981,"Gen X",AB69<1997,"Millenial",TRUE,("Gen Z"))} -> Millenial
A70: 3495 | B70: Tia | C70: Ellis | D70: 45099 | E70: 45129 | F70: Area Sales Manager | G70: Daniel Cabrera | H70: tia.ellis@bilearner.com | I70: TNS | J70: Active | K70: Part-Time | L70: Zone B | M70: Temporary | N70: Retirement | O70: Night company image able suggest. | P70: Sales | Q70: Wireline Construction | R70: 33996 | S70: IN | T70: Laborer | U70: Male | V70: 1115 | W70: Other | X70: Married | Y70: Fully Meets | Z70: 4 | AA70: =IF(E70="","Active","Non-Active") -> Non-Active | AB70: =YEAR(R70) -> 1993 | AC70: =INT(YEARFRAC(R70,"20/04/2026")) -> 33 | AD70: {=_xlfn.IFS(AB70<1965,"Baby Boomers",AB70<1981,"Gen X",AB70<1997,"Millenial",TRUE,("Gen Z"))} -> Millenial
A71: 3496 | B71: Aspen | C71: Bentley | D71: 44532 | F71: Area Sales Manager | G71: Barbara Garcia | H71: aspen.bentley@bilearner.com | I71: WBL | J71: Active | K71: Contract | L71: Zone A | M71: Part-Time | N71: Unk | P71: Sales | Q71: General - Sga | R71: 23639 | S71: CA | T71: Administrator | U71: Male | V71: 72233 | W71: Other | X71: Widowed | Y71: Fully Meets | Z71: 5 | AA71: =IF(E71="","Active","Non-Active") -> Active | AB71: =YEAR(R71) -> 1964 | AC71: =INT(YEARFRAC(R71,"20/04/2026")) -> 61 | AD71: {=_xlfn.IFS(AB71<1965,"Baby Boomers",AB71<1981,"Gen X",AB71<1997,"Millenial",TRUE,("Gen Z"))} -> Baby Boomers
A72: 3497 | B72: Graham | C72: Rodriguez | D72: 44538 | F72: Area Sales Manager | G72: Kendra Murray | H72: graham.rodriguez@bilearner.com | I72: TNS | J72: Active | K72: Part-Time | L72: Zone C | M72: Temporary | N72: Unk | P72: Sales | Q72: Project Management - Con | R72: 29635 | S72: OR | T72: Lineman | U72: Female | V72: 58210 | W72: Hispanic | X72: Widowed | Y72: Fully Meets | Z72: 1 | AA72: =IF(E72="","Active","Non-Active") -> Active | AB72: =YEAR(R72) -> 1981 | AC72: =INT(YEARFRAC(R72,"20/04/2026")) -> 45 | AD72: {=_xlfn.IFS(AB72<1965,"Baby Boomers",AB72<1981,"Gen X",AB72<1997,"Millenial",TRUE,("Gen Z"))} -> Millenial
A73: 3498 | B73: Joel | C73: Mcmillan | D73: 45042 | E73: 45099 | F73: Area Sales Manager | G73: Peter Harvey | H73: joel.mcmillan@bilearner.com | I73: PYZ | J73: Active | K73: Full-Time | L73: Zone A | M73: Full-Time | N73: Voluntary | O73: About allow article. For gas player magazine. | P73: Sales | Q73: General - Sga | R73: 36085 | S73: KY | T73: Laborer | U73: Female | V73: 36087 | W73: White | X73: Widowed | Y73: Fully Meets | Z73: 2 | AA73: =IF(E73="","Active","Non-Active") -> Non-Active | AB73: =YEAR(R73) -> 1998 | AC73: =INT(YEARFRAC(R73,"20/04/2026")) -> 27 | AD73: {=_xlfn.IFS(AB73<1965,"Baby Boomers",AB73<1981,"Gen X",AB73<1997,"Millenial",TRUE,("Gen Z"))} -> Gen Z
A74: 3499 | B74: Maci | C74: Frost | D74: 43368 | E74: 44550 | F74: Area Sales Manager | G74: Patrick Daniel | H74: maci.frost@bilearner.com | I74: WBL | J74: Active | K74: Part-Time | L74: Zone C | M74: Temporary | N74: Involuntary | O74: Seem hand dog. Us six beyond place fund well. | P74: Sales | Q74: Field Operations | R74: 25949 | S74: KY | T74: Technician | U74: Female | V74: 61457 | W74: Asian | X74: Widowed | Y74: Fully Meets | Z74: 5 | AA74: =IF(E74="","Active","Non-Active") -> Non-Active | AB74: =YEAR(R74) -> 1971 | AC74: =INT(YEARFRAC(R74,"20/04/2026")) -> 55 | AD74: {=_xlfn.IFS(AB74<1965,"Baby Boomers",AB74<1981,"Gen X",AB74<1997,"Millenial",TRUE,("Gen Z"))} -> Gen X
A75: 3500 | B75: Nevaeh | C75: Lucas | D75: 43424 | E75: 44003 | F75: Area Sales Manager | G75: Bryan Douglas | H75: nevaeh.lucas@bilearner.com | I75: NEL | J75: Active | K75: Full-Time | L75: Zone B | M75: Part-Time | N75: Voluntary | O75: Game hour boy not write somebody owner. | P75: Sales | Q75: Shop (Fleet) | R75: 36581 | S75: TX | T75: Mechanic | U75: Female | V75: 80424 | W75: White | X75: Divorced | Y75: Fully Meets | Z75: 1 | AA75: =IF(E75="","Active","Non-Active") -> Non-Active | AB75: =YEAR(R75) -> 2000 | AC75: =INT(YEARFRAC(R75,"20/04/2026")) -> 26 | AD75: {=_xlfn.IFS(AB75<1965,"Baby Boomers",AB75<1981,"Gen X",AB75<1997,"Millenial",TRUE,("Gen Z"))} -> Gen Z
A76: 3501 | B76: Garrett | C76: Zimmerman | D76: 44073 | E76: 44803 | F76: Area Sales Manager | G76: Destiny Hopkins | H76: garrett.zimmerman@bilearner.com | I76: PL | J76: Future Start | K76: Part-Time | L76: Zone A | M76: Part-Time | N76: Retirement | O76: Worker medical commercial participant tough leg. | P76: Sales | Q76: General - Con | R76: 21659 | S76: TX | T76: Technician | U76: Male | V76: 6240 | W76: Other | X76: Widowed | Y76: Fully Meets | Z76: 4 | AA76: =IF(E76="","Active","Non-Active") -> Non-Active | AB76: =YEAR(R76) -> 1959 | AC76: =INT(YEARFRAC(R76,"20/04/2026")) -> 67 | AD76: {=_xlfn.IFS(AB76<1965,"Baby Boomers",AB76<1981,"Gen X",AB76<1997,"Millenial",TRUE,("Gen Z"))} -> Baby Boomers
A77: 3502 | B77: Eugene | C77: Marks | D77: 43739 | F77: Area Sales Manager | G77: Angela Morris | H77: eugene.marks@bilearner.com | I77: BPC | J77: Active | K77: Full-Time | L77: Zone C | M77: Temporary | N77: Unk | P77: Sales | Q77: Splicing | R77: 27940 | S77: TX | T77: Electrician | U77: Male | V77: 49914 | W77: White | X77: Married | Y77: Fully Meets | Z77: 1 | AA77: =IF(E77="","Active","Non-Active") -> Active | AB77: =YEAR(R77) -> 1976 | AC77: =INT(YEARFRAC(R77,"20/04/2026")) -> 49 | AD77: {=_xlfn.IFS(AB77<1965,"Baby Boomers",AB77<1981,"Gen X",AB77<1997,"Millenial",TRUE,("Gen Z"))} -> Gen X
A78: 3503 | B78: Geovanni | C78: Pugh | D78: 44581 | F78: Area Sales Manager | G78: Erica Franklin | H78: geovanni.pugh@bilearner.com | I78: CCDR | J78: Active | K78: Part-Time | L78: Zone A | M78: Temporary | N78: Unk | P78: Sales | Q78: Project Management - Con | R78: 18836 | S78: CO | T78: Manager | U78: Male | V78: 71319 | W78: Other | X78: Single | Y78: Fully Meets | Z78: 4 | AA78: =IF(E78="","Active","Non-Active") -> Active | AB78: =YEAR(R78) -> 1951 | AC78: =INT(YEARFRAC(R78,"20/04/2026")) -> 74 | AD78: {=_xlfn.IFS(AB78<1965,"Baby Boomers",AB78<1981,"Gen X",AB78<1997,"Millenial",TRUE,("Gen Z"))} -> Baby Boomers
A79: 3504 | B79: Javon | C79: Kelley | D79: 44479 | F79: Area Sales Manager | G79: Gabriela Orr | H79: javon.kelley@bilearner.com | I79: SVG | J79: Active | K79: Full-Time | L79: Zone B | M79: Part-Time | N79: Unk | P79: Sales | Q79: General - Con | R79: 29456 | S79: CO | T79: Laborer | U79: Male | V79: 27992 | W79: Hispanic | X79: Married | Y79: Fully Meets | Z79: 2 | AA79: =IF(E79="","Active","Non-Active") -> Active | AB79: =YEAR(R79) -> 1980 | AC79: =INT(YEARFRAC(R79,"20/04/2026")) -> 45 | AD79: {=_xlfn.IFS(AB79<1965,"Baby Boomers",AB79<1981,"Gen X",AB79<1997,"Millenial",TRUE,("Gen Z"))} -> Gen X
A80: 3505 | B80: Amaya | C80: Hicks | D80: 44072 | F80: Area Sales Manager | G80: Michael Wilkins | H80: amaya.hicks@bilearner.com | I80: EW | J80: Active | K80: Contract | L80: Zone B | M80: Temporary | N80: Unk | P80: Sales | Q80: Field Operations | R80: 15911 | S80: IN | T80: Groundman | U80: Male | V80: 72324 | W80: Hispanic | X80: Widowed | Y80: Fully Meets | Z80: 1 | AA80: =IF(E80="","Active","Non-Active") -> Active | AB80: =YEAR(R80) -> 1943 | AC80: =INT(YEARFRAC(R80,"20/04/2026")) -> 82 | AD80: {=_xlfn.IFS(AB80<1965,"Baby Boomers",AB80<1981,"Gen X",AB80<1997,"Millenial",TRUE,("Gen Z"))} -> Baby Boomers
A81: 3506 | B81: Laila | C81: Woodard | D81: 43704 | E81: 45056 | F81: Area Sales Manager | G81: Jordan Vega | H81: laila.woodard@bilearner.com | I81: MSC | J81: Active | K81: Full-Time | L81: Zone B | M81: Temporary | N81: Voluntary | O81: Fund nor half early miss follow. | P81: Sales | Q81: Field Operations | R81: 32330 | S81: IN | T81: Technician | U81: Male | V81: 38740 | W81: Other | X81: Married | Y81: Fully Meets | Z81: 2 | AA81: =IF(E81="","Active","Non-Active") -> Non-Active | AB81: =YEAR(R81) -> 1988 | AC81: =INT(YEARFRAC(R81,"20/04/2026")) -> 37 | AD81: {=_xlfn.IFS(AB81<1965,"Baby Boomers",AB81<1981,"Gen X",AB81<1997,"Millenial",TRUE,("Gen Z"))} -> Millenial
A82: 3507 | B82: Ivan | C82: Huff | D82: 44252 | E82: 45023 | F82: Area Sales Manager | G82: John Miller | H82: ivan.huff@bilearner.com | I82: TNS | J82: Active | K82: Full-Time | L82: Zone A | M82: Full-Time | N82: Retirement | O82: Line later deal stand sometimes too mind. | P82: Sales | Q82: Project Management - Con | R82: 26747 | S82: CA | T82: Manager | U82: Male | V82: 9437 | W82: White | X82: Single | Y82: Fully Meets | Z82: 4 | AA82: =IF(E82="","Active","Non-Active") -> Non-Active | AB82: =YEAR(R82) -> 1973 | AC82: =INT(YEARFRAC(R82,"20/04/2026")) -> 53 | AD82: {=_xlfn.IFS(AB82<1965,"Baby Boomers",AB82<1981,"Gen X",AB82<1997,"Millenial",TRUE,("Gen Z"))} -> Gen X
A83: 3508 | B83: Aidan | C83: Harding | D83: 44390 | F83: Area Sales Manager | G83: Trevor Adkins | H83: aidan.harding@bilearner.com | I83: CCDR | J83: Active | K83: Full-Time | L83: Zone B | M83: Part-Time | N83: Unk | P83: Sales | Q83: Aerial | R83: 15487 | S83: OR | T83: Laborer | U83: Male | V83: 9385 | W83: Asian | X83: Single | Y83: Fully Meets | Z83: 5 | AA83: =IF(E83="","Active","Non-Active") -> Active | AB83: =YEAR(R83) -> 1942 | AC83: =INT(YEARFRAC(R83,"20/04/2026")) -> 83 | AD83: {=_xlfn.IFS(AB83<1965,"Baby Boomers",AB83<1981,"Gen X",AB83<1997,"Millenial",TRUE,("Gen Z"))} -> Baby Boomers
A84: 3509 | B84: Cruz | C84: Boyer | D84: 44300 | F84: Area Sales Manager | G84: Marcus Hunt | H84: cruz.boyer@bilearner.com | I84: BPC | J84: Active | K84: Part-Time | L84: Zone C | M84: Full-Time | N84: Unk | P84: Sales | Q84: General - Sga | R84: 28433 | S84: KY | T84: Project Controls | U84: Female | V84: 75993 | W84: Black | X84: Married | Y84: Fully Meets | Z84: 2 | AA84: =IF(E84="","Active","Non-Active") -> Active | AB84: =YEAR(R84) -> 1977 | AC84: =INT(YEARFRAC(R84,"20/04/2026")) -> 48 | AD84: {=_xlfn.IFS(AB84<1965,"Baby Boomers",AB84<1981,"Gen X",AB84<1997,"Millenial",TRUE,("Gen Z"))} -> Gen X
A85: 3510 | B85: Raven | C85: Koch | D85: 43871 | F85: Area Sales Manager | G85: Jennifer King | H85: raven.koch@bilearner.com | I85: PYZ | J85: Active | K85: Part-Time | L85: Zone A | M85: Full-Time | N85: Unk | P85: Sales | Q85: General - Con | R85: 20745 | S85: KY | T85: Laborer | U85: Female | V85: 65329 | W85: Hispanic | X85: Married | Y85: Fully Meets | Z85: 2 | AA85: =IF(E85="","Active","Non-Active") -> Active | AB85: =YEAR(R85) -> 1956 | AC85: =INT(YEARFRAC(R85,"20/04/2026")) -> 69 | AD85: {=_xlfn.IFS(AB85<1965,"Baby Boomers",AB85<1981,"Gen X",AB85<1997,"Millenial",TRUE,("Gen Z"))} -> Baby Boomers
A86: 3511 | B86: Karli | C86: Barker | D86: 44425 | E86: 44561 | F86: Area Sales Manager | G86: Shawn Dudley | H86: karli.barker@bilearner.com | I86: WBL | J86: Active | K86: Part-Time | L86: Zone B | M86: Full-Time | N86: Resignation | O86: Tell paper every. | P86: Sales | Q86: Finance & Accounting | R86: 35479 | S86: KY | T86: Director | U86: Female | V86: 41111 | W86: Asian | X86: Divorced | Y86: Fully Meets | Z86: 4 | AA86: =IF(E86="","Active","Non-Active") -> Non-Active | AB86: =YEAR(R86) -> 1997 | AC86: =INT(YEARFRAC(R86,"20/04/2026")) -> 29 | AD86: {=_xlfn.IFS(AB86<1965,"Baby Boomers",AB86<1981,"Gen X",AB86<1997,"Millenial",TRUE,("Gen Z"))} -> Gen Z
A87: 3512 | B87: Tyrone | C87: Sosa | D87: 45033 | E87: 45099 | F87: Area Sales Manager | G87: Lindsay Chang | H87: tyrone.sosa@bilearner.com | I87: NEL | J87: Future Start | K87: Contract | L87: Zone C | M87: Temporary | N87: Voluntary | O87: Why sport must page bad. | P87: Sales | Q87: Yard (Material Handling) | R87: 35363 | S87: TX | T87: Coordinator | U87: Female | V87: 58860 | W87: Black | X87: Single | Y87: Fully Meets | Z87: 2 | AA87: =IF(E87="","Active","Non-Active") -> Non-Active | AB87: =YEAR(R87) -> 1996 | AC87: =INT(YEARFRAC(R87,"20/04/2026")) -> 29 | AD87: {=_xlfn.IFS(AB87<1965,"Baby Boomers",AB87<1981,"Gen X",AB87<1997,"Millenial",TRUE,("Gen Z"))} -> Millenial
A88: 3513 | B88: Damaris | C88: Cisneros | D88: 44806 | E88: 45070 | F88: Area Sales Manager | G88: Sharon Ruiz | H88: damaris.cisneros@bilearner.com | I88: PL | J88: Future Start | K88: Contract | L88: Zone C | M88: Temporary | N88: Involuntary | O88: Something sense information final building. | P88: Sales | Q88: General - Con | R88: 21867 | S88: TX | T88: Laborer | U88: Male | V88: 93051 | W88: Other | X88: Married | Y88: Fully Meets | Z88: 5 | AA88: =IF(E88="","Active","Non-Active") -> Non-Active | AB88: =YEAR(R88) -> 1959 | AC88: =INT(YEARFRAC(R88,"20/04/2026")) -> 66 | AD88: {=_xlfn.IFS(AB88<1965,"Baby Boomers",AB88<1981,"Gen X",AB88<1997,"Millenial",TRUE,("Gen Z"))} -> Baby Boomers
A89: 3514 | B89: Alexus | C89: Estes | D89: 43936 | F89: Area Sales Manager | G89: April Randolph | H89: alexus.estes@bilearner.com | I89: BPC | J89: Active | K89: Full-Time | L89: Zone B | M89: Part-Time | N89: Unk | P89: Sales | Q89: Wireline Construction | R89: 21188 | S89: TX | T89: Manager | U89: Male | V89: 17419 | W89: Asian | X89: Married | Y89: Fully Meets | Z89: 1 | AA89: =IF(E89="","Active","Non-Active") -> Active | AB89: =YEAR(R89) -> 1958 | AC89: =INT(YEARFRAC(R89,"20/04/2026")) -> 68 | AD89: {=_xlfn.IFS(AB89<1965,"Baby Boomers",AB89<1981,"Gen X",AB89<1997,"Millenial",TRUE,("Gen Z"))} -> Baby Boomers
A90: 3515 | B90: Kinsley | C90: Flowers | D90: 44629 | E90: 44905 | F90: Area Sales Manager | G90: Mary Reilly | H90: kinsley.flowers@bilearner.com | I90: CCDR | J90: Future Start | K90: Part-Time | L90: Zone A | M90: Part-Time | N90: Retirement | O90: School see rest firm I. | P90: Sales | Q90: Finance & Accounting | R90: 35549 | S90: CO | T90: Controller | U90: Male | V90: 59593 | W90: White | X90: Single | Y90: Fully Meets | Z90: 4 | AA90: =IF(E90="","Active","Non-Active") -> Non-Active | AB90: =YEAR(R90) -> 1997 | AC90: =INT(YEARFRAC(R90,"20/04/2026")) -> 28 | AD90: {=_xlfn.IFS(AB90<1965,"Baby Boomers",AB90<1981,"Gen X",AB90<1997,"Millenial",TRUE,("Gen Z"))} -> Gen Z
A91: 3516 | B91: Deborah | C91: Love | D91: 44658 | E91: 44948 | F91: Area Sales Manager | G91: Eric Goodman | H91: deborah.love@bilearner.com | I91: SVG | J91: Active | K91: Contract | L91: Zone B | M91: Part-Time | N91: Retirement | O91: Source doctor rock group this. | P91: Sales | Q91: Project Management - Con | R91: 32319 | S91: CO | T91: Coordinator | U91: Male | V91: 96350 | W91: Asian | X91: Divorced | Y91: Fully Meets | Z91: 5 | AA91: =IF(E91="","Active","Non-Active") -> Non-Active | AB91: =YEAR(R91) -> 1988 | AC91: =INT(YEARFRAC(R91,"20/04/2026")) -> 37 | AD91: {=_xlfn.IFS(AB91<1965,"Baby Boomers",AB91<1981,"Gen X",AB91<1997,"Millenial",TRUE,("Gen Z"))} -> Millenial
A92: 3517 | B92: Milagros | C92: Francis | D92: 43880 | F92: Area Sales Manager | G92: Caleb Schneider | H92: milagros.francis@bilearner.com | I92: EW | J92: Active | K92: Part-Time | L92: Zone A | M92: Part-Time | N92: Unk | P92: Sales | Q92: Splicing | R92: 15345 | S92: IN | T92: Splicer | U92: Male | V92: 44469 | W92: Hispanic | X92: Widowed | Y92: Fully Meets | Z92: 4 | AA92: =IF(E92="","Active","Non-Active") -> Active | AB92: =YEAR(R92) -> 1942 | AC92: =INT(YEARFRAC(R92,"20/04/2026")) -> 84 | AD92: {=_xlfn.IFS(AB92<1965,"Baby Boomers",AB92<1981,"Gen X",AB92<1997,"Millenial",TRUE,("Gen Z"))} -> Baby Boomers
A93: 3518 | B93: Roberto | C93: Michael | D93: 44296 | E93: 44746 | F93: Area Sales Manager | G93: Cheryl Henry | H93: roberto.michael@bilearner.com | I93: MSC | J93: Active | K93: Contract | L93: Zone B | M93: Part-Time | N93: Involuntary | O93: Little imagine career he produce program. | P93: Sales | Q93: General - Eng | R93: 25347 | S93: CA | T93: Coordinator | U93: Female | V93: 13249 | W93: Hispanic | X93: Married | Y93: Fully Meets | Z93: 2 | AA93: =IF(E93="","Active","Non-Active") -> Non-Active | AB93: =YEAR(R93) -> 1969 | AC93: =INT(YEARFRAC(R93,"20/04/2026")) -> 56 | AD93: {=_xlfn.IFS(AB93<1965,"Baby Boomers",AB93<1981,"Gen X",AB93<1997,"Millenial",TRUE,("Gen Z"))} -> Gen X
A94: 3519 | B94: Elaine | C94: Ewing | D94: 44549 | E94: 44622 | F94: Area Sales Manager | G94: Dan Hernandez | H94: elaine.ewing@bilearner.com | I94: TNS | J94: Active | K94: Part-Time | L94: Zone C | M94: Temporary | N94: Resignation | O94: Your very trip successful memory to while out. | P94: Sales | Q94: Aerial | R94: 18715 | S94: CA | T94: Groundman | U94: Male | V94: 17123 | W94: Hispanic | X94: Widowed | Y94: Fully Meets | Z94: 2 | AA94: =IF(E94="","Active","Non-Active") -> Non-Active | AB94: =YEAR(R94) -> 1951 | AC94: =INT(YEARFRAC(R94,"20/04/2026")) -> 75 | AD94: {=_xlfn.IFS(AB94<1965,"Baby Boomers",AB94<1981,"Gen X",AB94<1997,"Millenial",TRUE,("Gen Z"))} -> Baby Boomers
A95: 3520 | B95: Caiden | C95: Munoz | D95: 44178 | E95: 44939 | F95: Area Sales Manager | G95: Teresa Daniel | H95: caiden.munoz@bilearner.com | I95: TNS | J95: Active | K95: Full-Time | L95: Zone C | M95: Temporary | N95: Involuntary | O95: Red some option. | P95: Sales | Q95: Project Management - Con | R95: 23071 | S95: ND | T95: Manager | U95: Female | V95: 18983 | W95: Black | X95: Divorced | Y95: Fully Meets | Z95: 1 | AA95: =IF(E95="","Active","Non-Active") -> Non-Active | AB95: =YEAR(R95) -> 1963 | AC95: =INT(YEARFRAC(R95,"20/04/2026")) -> 63 | AD95: {=_xlfn.IFS(AB95<1965,"Baby Boomers",AB95<1981,"Gen X",AB95<1997,"Millenial",TRUE,("Gen Z"))} -> Baby Boomers
A96: 3521 | B96: Jocelyn | C96: Bradford | D96: 43522 | F96: Area Sales Manager | G96: Melissa Decker | H96: jocelyn.bradford@bilearner.com | I96: WBL | J96: Active | K96: Contract | L96: Zone C | M96: Part-Time | N96: Unk | P96: Sales | Q96: General - Con | R96: 18004 | S96: KY | T96: Electrician | U96: Female | V96: 51795 | W96: Asian | X96: Divorced | Y96: Fully Meets | Z96: 4 | AA96: =IF(E96="","Active","Non-Active") -> Active | AB96: =YEAR(R96) -> 1949 | AC96: =INT(YEARFRAC(R96,"20/04/2026")) -> 77 | AD96: {=_xlfn.IFS(AB96<1965,"Baby Boomers",AB96<1981,"Gen X",AB96<1997,"Millenial",TRUE,("Gen Z"))} -> Baby Boomers
A97: 3522 | B97: Marques | C97: Armstrong | D97: 43892 | F97: Area Sales Manager | G97: Michael Nguyen | H97: marques.armstrong@bilearner.com | I97: BPC | J97: Active | K97: Full-Time | L97: Zone C | M97: Part-Time | N97: Unk | P97: Sales | Q97: Splicing | R97: 30601 | S97: KY | T97: Splicer | U97: Female | V97: 34369 | W97: Other | X97: Single | Y97: Fully Meets | Z97: 1 | AA97: =IF(E97="","Active","Non-Active") -> Active | AB97: =YEAR(R97) -> 1983 | AC97: =INT(YEARFRAC(R97,"20/04/2026")) -> 42 | AD97: {=_xlfn.IFS(AB97<1965,"Baby Boomers",AB97<1981,"Gen X",AB97<1997,"Millenial",TRUE,("Gen Z"))} -> Millenial
A98: 3523 | B98: Rohan | C98: Chapman | D98: 44372 | E98: 44798 | F98: Area Sales Manager | G98: Tony Mcconnell | H98: rohan.chapman@bilearner.com | I98: CCDR | J98: Active | K98: Full-Time | L98: Zone A | M98: Temporary | N98: Resignation | O98: Theory grow future week house. | P98: Sales | Q98: General - Con | R98: 28843 | S98: KY | T98: Laborer | U98: Female | V98: 23092 | W98: Other | X98: Single | Y98: Fully Meets | Z98: 2 | AA98: =IF(E98="","Active","Non-Active") -> Non-Active | AB98: =YEAR(R98) -> 1978 | AC98: =INT(YEARFRAC(R98,"20/04/2026")) -> 47 | AD98: {=_xlfn.IFS(AB98<1965,"Baby Boomers",AB98<1981,"Gen X",AB98<1997,"Millenial",TRUE,("Gen Z"))} -> Gen X
A99: 3524 | B99: Emmanuel | C99: Franklin | D99: 44403 | E99: 44685 | F99: Area Sales Manager | G99: Adam Gibson | H99: emmanuel.franklin@bilearner.com | I99: EW | J99: Future Start | K99: Contract | L99: Zone B | M99: Full-Time | N99: Resignation | O99: Inside week also so. | P99: Sales | Q99: Field Operations | R99: 36475 | S99: TX | T99: Laborer | U99: Male | V99: 6074 | W99: Asian | X99: Divorced | Y99: Fully Meets | Z99: 2 | AA99: =IF(E99="","Active","Non-Active") -> Non-Active | AB99: =YEAR(R99) -> 1999 | AC99: =INT(YEARFRAC(R99,"20/04/2026")) -> 26 | AD99: {=_xlfn.IFS(AB99<1965,"Baby Boomers",AB99<1981,"Gen X",AB99<1997,"Millenial",TRUE,("Gen Z"))} -> Gen Z
A100: 3525 | B100: Clayton | C100: Mccormick | D100: 44745 | E100: 44936 | F100: Area Sales Manager | G100: Stephanie Duke | H100: clayton.mccormick@bilearner.com | I100: MSC | J100: Future Start | K100: Contract | L100: Zone B | M100: Temporary | N100: Retirement | O100: Surface vote old picture. | P100: Sales | Q100: General - Con | R100: 24501 | S100: TX | T100: Foreman | U100: Male | V100: 72264 | W100: Hispanic | X100: Single | Y100: Fully Meets | Z100: 2 | AA100: =IF(E100="","Active","Non-Active") -> Non-Active | AB100: =YEAR(R100) -> 1967 | AC100: =INT(YEARFRAC(R100,"20/04/2026")) -> 59 | AD100: {=_xlfn.IFS(AB100<1965,"Baby Boomers",AB100<1981,"Gen X",AB100<1997,"Millenial",TRUE,("Gen Z"))} -> Gen X
...

Sheet DATA FORMULASI
A1: EmpID | B1: FirstName | C1: LastName | D1: Full Name | E1: StartDate | F1: ExitDate | G1: EmployeeStatus | H1: EmployeeType | I1: PayZone | J1: EmployeeClassificationType | K1: DepartmentType | L1: Division | M1: DOB | N1: JobFunctionDescription | O1: Current Employee Rating | P1: CurrentEmployeeStatus | Q1: Year of Birth | R1: Umur | S1: Generasi
A2: 3427 | B2: Uriah | C2: Bridges | D2: =Table13[[#This Row],[FirstName]]&" "&Table13[[#This Row],[LastName]] -> Uriah Bridges | E2: 43728 | G2: Active | H2: Contract | I2: Zone C | J2: Temporary | K2: Production | L2: Finance & Accounting | M2: 25483 | N2: Accounting | O2: 4 | P2: =IF(F2="","Active","Non-Active") -> Active | Q2: =YEAR(M2) -> 1969 | R2: =INT(YEARFRAC(M2,"20/04/2026")) -> 56 | S2: {=_xlfn.IFS(Q2<1965,"Baby Boomers",Q2<1981,"Gen X",Q2<1997,"Millenial",TRUE,("Gen Z"))} -> Gen X | U2: Formula COUNTIFS untuk menentukan jumlah karyawan yang mendapatkan rating
A3: 3428 | B3: Paula | C3: Small | D3: =Table13[[#This Row],[FirstName]]&" "&Table13[[#This Row],[LastName]] -> Paula Small | E3: 44968 | G3: Active | H3: Contract | I3: Zone A | J3: Part-Time | K3: Production | L3: Aerial | M3: 23984 | N3: Labor | O3: 3 | P3: =IF(F3="","Active","Non-Active") -> Active | Q3: =YEAR(M3) -> 1965 | R3: =INT(YEARFRAC(M3,"20/04/2026")) -> 60 | S3: {=_xlfn.IFS(Q3<1965,"Baby Boomers",Q3<1981,"Gen X",Q3<1997,"Millenial",TRUE,("Gen Z"))} -> Gen X
A4: 3429 | B4: Edward | C4: Buck | D4: =Table13[[#This Row],[FirstName]]&" "&Table13[[#This Row],[LastName]] -> Edward Buck | E4: 43444 | G4: Active | H4: Full-Time | I4: Zone B | J4: Part-Time | K4: Sales | L4: General - Sga | M4: 33517 | N4: Assistant | O4: 4 | P4: =IF(F4="","Active","Non-Active") -> Active | Q4: =YEAR(M4) -> 1991 | R4: =INT(YEARFRAC(M4,"20/04/2026")) -> 34 | S4: {=_xlfn.IFS(Q4<1965,"Baby Boomers",Q4<1981,"Gen X",Q4<1997,"Millenial",TRUE,("Gen Z"))} -> Millenial | U4: Rating | V4: Jumlah Karyawan
A5: 3430 | B5: Michael | C5: Riordan | D5: =Table13[[#This Row],[FirstName]]&" "&Table13[[#This Row],[LastName]] -> Michael Riordan | E5: 44368 | G5: Active | H5: Contract | I5: Zone A | J5: Full-Time | K5: Sales | L5: Finance & Accounting | M5: 35889 | N5: Clerk | O5: 2 | P5: =IF(F5="","Active","Non-Active") -> Active | Q5: =YEAR(M5) -> 1998 | R5: =INT(YEARFRAC(M5,"20/04/2026")) -> 28 | S5: {=_xlfn.IFS(Q5<1965,"Baby Boomers",Q5<1981,"Gen X",Q5<1997,"Millenial",TRUE,("Gen Z"))} -> Gen Z | U5: 5 | V5: =COUNTIFS(Table13[Current Employee Rating],"5") -> 270
A6: 3431 | B6: Jasmine | C6: Onque | D6: =Table13[[#This Row],[FirstName]]&" "&Table13[[#This Row],[LastName]] -> Jasmine Onque | E6: 43645 | G6: Active | H6: Contract | I6: Zone A | J6: Temporary | K6: Sales | L6: General - Con | M6: 25444 | N6: Laborer | O6: 3 | P6: =IF(F6="","Active","Non-Active") -> Active | Q6: =YEAR(M6) -> 1969 | R6: =INT(YEARFRAC(M6,"20/04/2026")) -> 56 | S6: {=_xlfn.IFS(Q6<1965,"Baby Boomers",Q6<1981,"Gen X",Q6<1997,"Millenial",TRUE,("Gen Z"))} -> Gen X | U6: 4 | V6: =COUNTIFS(Table13[Current Employee Rating],"4") -> 419
A7: 3432 | B7: Maruk | C7: Fraval | D7: =Table13[[#This Row],[FirstName]]&" "&Table13[[#This Row],[LastName]] -> Maruk Fraval | E7: 43847 | G7: Active | H7: Contract | I7: Zone B | J7: Full-Time | K7: Sales | L7: Field Operations | M7: 17991 | N7: Driver | O7: 3 | P7: =IF(F7="","Active","Non-Active") -> Active | Q7: =YEAR(M7) -> 1949 | R7: =INT(YEARFRAC(M7,"20/04/2026")) -> 77 | S7: {=_xlfn.IFS(Q7<1965,"Baby Boomers",Q7<1981,"Gen X",Q7<1997,"Millenial",TRUE,("Gen Z"))} -> Baby Boomers | U7: 3 | V7: =COUNTIFS(Table13[Current Employee Rating],"3") -> 1530
A8: 3433 | B8: Latia | C8: Costa | D8: =Table13[[#This Row],[FirstName]]&" "&Table13[[#This Row],[LastName]] -> Latia Costa | E8: 44657 | F8: 45110 | G8: Active | H8: Full-Time | I8: Zone B | J8: Temporary | K8: Sales | L8: General - Eng | M8: 15523 | N8: Technician | O8: 4 | P8: =IF(F8="","Active","Non-Active") -> Non-Active | Q8: =YEAR(M8) -> 1942 | R8: =INT(YEARFRAC(M8,"20/04/2026")) -> 83 | S8: {=_xlfn.IFS(Q8<1965,"Baby Boomers",Q8<1981,"Gen X",Q8<1997,"Millenial",TRUE,("Gen Z"))} -> Baby Boomers | U8: 2 | V8: =COUNTIFS(Table13[Current Employee Rating],"2") -> 510
A9: 3434 | B9: Sharlene | C9: Terry | D9: =Table13[[#This Row],[FirstName]]&" "&Table13[[#This Row],[LastName]] -> Sharlene Terry | E9: 44141 | F9: 44955 | G9: Active | H9: Contract | I9: Zone C | J9: Full-Time | K9: Sales | L9: Engineers | M9: 20886 | N9: Engineer | O9: 2 | P9: =IF(F9="","Active","Non-Active") -> Non-Active | Q9: =YEAR(M9) -> 1957 | R9: =INT(YEARFRAC(M9,"20/04/2026")) -> 69 | S9: {=_xlfn.IFS(Q9<1965,"Baby Boomers",Q9<1981,"Gen X",Q9<1997,"Millenial",TRUE,("Gen Z"))} -> Baby Boomers | U9: 1 | V9: =COUNTIFS(Table13[Current Employee Rating],"1") -> 271
A10: 3435 | B10: Jac | C10: Mckinzie | D10: =Table13[[#This Row],[FirstName]]&" "&Table13[[#This Row],[LastName]] -> Jac Mckinzie | E10: 43330 | G10: Active | H10: Contract | I10: Zone B | J10: Part-Time | K10: Sales | L10: Executive | M10: 27164 | N10: Executive Assistant | O10: 3 | P10: =IF(F10="","Active","Non-Active") -> Active | Q10: =YEAR(M10) -> 1974 | R10: =INT(YEARFRAC(M10,"20/04/2026")) -> 51 | S10: {=_xlfn.IFS(Q10<1965,"Baby Boomers",Q10<1981,"Gen X",Q10<1997,"Millenial",TRUE,("Gen Z"))} -> Gen X
A11: 3436 | B11: Joseph | C11: Martins | D11: =Table13[[#This Row],[FirstName]]&" "&Table13[[#This Row],[LastName]] -> Joseph Martins | E11: 44582 | F11: 45106 | G11: Active | H11: Part-Time | I11: Zone B | J11: Temporary | K11: Sales | L11: Engineers | M11: 18213 | N11: Engineer | O11: 5 | P11: =IF(F11="","Active","Non-Active") -> Non-Active | Q11: =YEAR(M11) -> 1949 | R11: =INT(YEARFRAC(M11,"20/04/2026")) -> 76 | S11: {=_xlfn.IFS(Q11<1965,"Baby Boomers",Q11<1981,"Gen X",Q11<1997,"Millenial",TRUE,("Gen Z"))} -> Baby Boomers
A12: 3437 | B12: Myriam | C12: Givens | D12: =Table13[[#This Row],[FirstName]]&" "&Table13[[#This Row],[LastName]] -> Myriam Givens | E12: 45142 | G12: Active | H12: Contract | I12: Zone B | J12: Temporary | K12: Sales | L12: Field Operations | M12: 23402 | N12: Technician | O12: 5 | P12: =IF(F12="","Active","Non-Active") -> Active | Q12: =YEAR(M12) -> 1964 | R12: =INT(YEARFRAC(M12,"20/04/2026")) -> 62 | S12: {=_xlfn.IFS(Q12<1965,"Baby Boomers",Q12<1981,"Gen X",Q12<1997,"Millenial",TRUE,("Gen Z"))} -> Baby Boomers | U12: Formula COUNTIFS untuk menentukan jumlah karyawan yang mendapatkan rating
A13: 3438 | B13: Dheepa | C13: Nguyen | D13: =Table13[[#This Row],[FirstName]]&" "&Table13[[#This Row],[LastName]] -> Dheepa Nguyen | E13: 43322 | F13: 43773 | G13: Active | H13: Full-Time | I13: Zone C | J13: Temporary | K13: Sales | L13: General - Con | M13: 17629 | N13: Technician | O13: 3 | P13: =IF(F13="","Active","Non-Active") -> Non-Active | Q13: =YEAR(M13) -> 1948 | R13: =INT(YEARFRAC(M13,"20/04/2026")) -> 78 | S13: {=_xlfn.IFS(Q13<1965,"Baby Boomers",Q13<1981,"Gen X",Q13<1997,"Millenial",TRUE,("Gen Z"))} -> Baby Boomers
A14: 3439 | B14: Bartholemew | C14: Khemmich | D14: =Table13[[#This Row],[FirstName]]&" "&Table13[[#This Row],[LastName]] -> Bartholemew Khemmich | E14: 44706 | F14: 44892 | G14: Active | H14: Full-Time | I14: Zone A | J14: Temporary | K14: Sales | L14: Splicing | M14: 29914 | N14: Splicer | O14: 3 | P14: =IF(F14="","Active","Non-Active") -> Non-Active | Q14: =YEAR(M14) -> 1981 | R14: =INT(YEARFRAC(M14,"20/04/2026")) -> 44 | S14: {=_xlfn.IFS(Q14<1965,"Baby Boomers",Q14<1981,"Gen X",Q14<1997,"Millenial",TRUE,("Gen Z"))} -> Millenial | U14: EmployeeClassificationType | V14: Jumlah
A15: 3440 | B15: Xana | C15: Potts | D15: =Table13[[#This Row],[FirstName]]&" "&Table13[[#This Row],[LastName]] -> Xana Potts | E15: 43804 | F15: 44974 | G15: Active | H15: Contract | I15: Zone A | J15: Full-Time | K15: Sales | L15: Finance & Accounting | M15: 18938 | N15: Controller | O15: 3 | P15: =IF(F15="","Active","Non-Active") -> Non-Active | Q15: =YEAR(M15) -> 1951 | R15: =INT(YEARFRAC(M15,"20/04/2026")) -> 74 | S15: {=_xlfn.IFS(Q15<1965,"Baby Boomers",Q15<1981,"Gen X",Q15<1997,"Millenial",TRUE,("Gen Z"))} -> Baby Boomers | U15: {=_xlfn.UNIQUE(Table13[EmployeeClassificationType])} -> Temporary | V15: =COUNTIFS(Table13[EmployeeClassificationType],"Temporary") -> 1033
A16: 3441 | B16: Prater | C16: Jeremy | D16: =Table13[[#This Row],[FirstName]]&" "&Table13[[#This Row],[LastName]] -> Prater Jeremy | E16: 43583 | G16: Active | H16: Part-Time | I16: Zone A | J16: Part-Time | K16: Sales | L16: General - Con | M16: 32833 | N16: Lineman | O16: 4 | P16: =IF(F16="","Active","Non-Active") -> Active | Q16: =YEAR(M16) -> 1989 | R16: =INT(YEARFRAC(M16,"20/04/2026")) -> 36 | S16: {=_xlfn.IFS(Q16<1965,"Baby Boomers",Q16<1981,"Gen X",Q16<1997,"Millenial",TRUE,("Gen Z"))} -> Millenial | U16: Part-Time | V16: =COUNTIFS(Table13[EmployeeType],"Part-Time") -> 954
A17: 3442 | B17: Kaylah | C17: Moon | D17: =Table13[[#This Row],[FirstName]]&" "&Table13[[#This Row],[LastName]] -> Kaylah Moon | E17: 43655 | F17: 44728 | G17: Active | H17: Full-Time | I17: Zone A | J17: Full-Time | K17: It/Is | L17: Field Operations | M17: 19322 | N17: Laborer | O17: 2 | P17: =IF(F17="","Active","Non-Active") -> Non-Active | Q17: =YEAR(M17) -> 1952 | R17: =INT(YEARFRAC(M17,"20/04/2026")) -> 73 | S17: {=_xlfn.IFS(Q17<1965,"Baby Boomers",Q17<1981,"Gen X",Q17<1997,"Millenial",TRUE,("Gen Z"))} -> Baby Boomers | U17: Full-Time | V17: =COUNTIFS(Table13[EmployeeClassificationType],"Full-Time") -> 1013
A18: 3443 | B18: Kristen | C18: Tate | D18: =Table13[[#This Row],[FirstName]]&" "&Table13[[#This Row],[LastName]] -> Kristen Tate | E18: 44291 | F18: 45058 | G18: Active | H18: Full-Time | I18: Zone C | J18: Part-Time | K18: It/Is | L18: Project Management - Con | M18: 34432 | N18: Coordinator | O18: 3 | P18: =IF(F18="","Active","Non-Active") -> Non-Active | Q18: =YEAR(M18) -> 1994 | R18: =INT(YEARFRAC(M18,"20/04/2026")) -> 32 | S18: {=_xlfn.IFS(Q18<1965,"Baby Boomers",Q18<1981,"Gen X",Q18<1997,"Millenial",TRUE,("Gen Z"))} -> Millenial
A19: 3444 | B19: Bobby | C19: Rodgers | D19: =Table13[[#This Row],[FirstName]]&" "&Table13[[#This Row],[LastName]] -> Bobby Rodgers | E19: 44528 | F19: 44596 | G19: Active | H19: Contract | I19: Zone A | J19: Part-Time | K19: Sales | L19: Engineers | M19: 30635 | N19: Director | O19: 3 | P19: =IF(F19="","Active","Non-Active") -> Non-Active | Q19: =YEAR(M19) -> 1983 | R19: =INT(YEARFRAC(M19,"20/04/2026")) -> 42 | S19: {=_xlfn.IFS(Q19<1965,"Baby Boomers",Q19<1981,"Gen X",Q19<1997,"Millenial",TRUE,("Gen Z"))} -> Millenial
A20: 3445 | B20: Reid | C20: Park | D20: =Table13[[#This Row],[FirstName]]&" "&Table13[[#This Row],[LastName]] -> Reid Park | E20: 44212 | G20: Active | H20: Contract | I20: Zone C | J20: Full-Time | K20: Sales | L20: Project Management - Con | M20: 31388 | N20: Supervisor | O20: 4 | P20: =IF(F20="","Active","Non-Active") -> Active | Q20: =YEAR(M20) -> 1985 | R20: =INT(YEARFRAC(M20,"20/04/2026")) -> 40 | S20: {=_xlfn.IFS(Q20<1965,"Baby Boomers",Q20<1981,"Gen X",Q20<1997,"Millenial",TRUE,("Gen Z"))} -> Millenial
A21: 3446 | B21: Hector | C21: Dalton | D21: =Table13[[#This Row],[FirstName]]&" "&Table13[[#This Row],[LastName]] -> Hector Dalton | E21: 44432 | G21: Active | H21: Part-Time | I21: Zone A | J21: Part-Time | K21: Sales | L21: Field Operations | M21: 35186 | N21: Driller | O21: 2 | P21: =IF(F21="","Active","Non-Active") -> Active | Q21: =YEAR(M21) -> 1996 | R21: =INT(YEARFRAC(M21,"20/04/2026")) -> 29 | S21: {=_xlfn.IFS(Q21<1965,"Baby Boomers",Q21<1981,"Gen X",Q21<1997,"Millenial",TRUE,("Gen Z"))} -> Millenial
A22: 3447 | B22: Mariela | C22: Schultz | D22: =Table13[[#This Row],[FirstName]]&" "&Table13[[#This Row],[LastName]] -> Mariela Schultz | E22: 43977 | F22: 45095 | G22: Future Start | H22: Part-Time | I22: Zone C | J22: Part-Time | K22: Sales | L22: General - Con | M22: 23424 | N22: Technician | O22: 3 | P22: =IF(F22="","Active","Non-Active") -> Non-Active | Q22: =YEAR(M22) -> 1964 | R22: =INT(YEARFRAC(M22,"20/04/2026")) -> 62 | S22: {=_xlfn.IFS(Q22<1965,"Baby Boomers",Q22<1981,"Gen X",Q22<1997,"Millenial",TRUE,("Gen Z"))} -> Baby Boomers
A23: 3448 | B23: Angela | C23: Molina | D23: =Table13[[#This Row],[FirstName]]&" "&Table13[[#This Row],[LastName]] -> Angela Molina | E23: 43739 | F23: 44141 | G23: Future Start | H23: Full-Time | I23: Zone A | J23: Temporary | K23: Sales | L23: Engineers | M23: 21317 | N23: Specialist | O23: 3 | P23: =IF(F23="","Active","Non-Active") -> Non-Active | Q23: =YEAR(M23) -> 1958 | R23: =INT(YEARFRAC(M23,"20/04/2026")) -> 67 | S23: {=_xlfn.IFS(Q23<1965,"Baby Boomers",Q23<1981,"Gen X",Q23<1997,"Millenial",TRUE,("Gen Z"))} -> Baby Boomers
A24: 3449 | B24: Gerald | C24: Preston | D24: =Table13[[#This Row],[FirstName]]&" "&Table13[[#This Row],[LastName]] -> Gerald Preston | E24: 45056 | F24: 45073 | G24: Future Start | H24: Contract | I24: Zone B | J24: Temporary | K24: Sales | L24: General - Eng | M24: 33865 | N24: Technician | O24: 5 | P24: =IF(F24="","Active","Non-Active") -> Non-Active | Q24: =YEAR(M24) -> 1992 | R24: =INT(YEARFRAC(M24,"20/04/2026")) -> 33 | S24: {=_xlfn.IFS(Q24<1965,"Baby Boomers",Q24<1981,"Gen X",Q24<1997,"Millenial",TRUE,("Gen Z"))} -> Millenial
A25: 3450 | B25: Reilly | C25: Moyer | D25: =Table13[[#This Row],[FirstName]]&" "&Table13[[#This Row],[LastName]] -> Reilly Moyer | E25: 44075 | F25: 44899 | G25: Active | H25: Contract | I25: Zone C | J25: Temporary | K25: Sales | L25: Field Operations | M25: 34557 | N25: Operator | O25: 2 | P25: =IF(F25="","Active","Non-Active") -> Non-Active | Q25: =YEAR(M25) -> 1994 | R25: =INT(YEARFRAC(M25,"20/04/2026")) -> 31 | S25: {=_xlfn.IFS(Q25<1965,"Baby Boomers",Q25<1981,"Gen X",Q25<1997,"Millenial",TRUE,("Gen Z"))} -> Millenial
A26: 3451 | B26: Carlee | C26: French | D26: =Table13[[#This Row],[FirstName]]&" "&Table13[[#This Row],[LastName]] -> Carlee French | E26: 44245 | F26: 44876 | G26: Active | H26: Contract | I26: Zone C | J26: Full-Time | K26: Sales | L26: General - Con | M26: 24852 | N26: Technician | O26: 3 | P26: =IF(F26="","Active","Non-Active") -> Non-Active | Q26: =YEAR(M26) -> 1968 | R26: =INT(YEARFRAC(M26,"20/04/2026")) -> 58 | S26: {=_xlfn.IFS(Q26<1965,"Baby Boomers",Q26<1981,"Gen X",Q26<1997,"Millenial",TRUE,("Gen Z"))} -> Gen X
A27: 3452 | B27: Jaydon | C27: Blackburn | D27: =Table13[[#This Row],[FirstName]]&" "&Table13[[#This Row],[LastName]] -> Jaydon Blackburn | E27: 44873 | G27: Active | H27: Part-Time | I27: Zone A | J27: Part-Time | K27: Sales | L27: General - Con | M27: 17174 | N27: Foreman | O27: 2 | P27: =IF(F27="","Active","Non-Active") -> Active | Q27: =YEAR(M27) -> 1947 | R27: =INT(YEARFRAC(M27,"20/04/2026")) -> 79 | S27: {=_xlfn.IFS(Q27<1965,"Baby Boomers",Q27<1981,"Gen X",Q27<1997,"Millenial",TRUE,("Gen Z"))} -> Baby Boomers
A28: 3453 | B28: Bridger | C28: Carter | D28: =Table13[[#This Row],[FirstName]]&" "&Table13[[#This Row],[LastName]] -> Bridger Carter | E28: 44847 | G28: Active | H28: Contract | I28: Zone C | J28: Part-Time | K28: Sales | L28: Fielders | M28: 30048 | N28: Engineer | O28: 4 | P28: =IF(F28="","Active","Non-Active") -> Active | Q28: =YEAR(M28) -> 1982 | R28: =INT(YEARFRAC(M28,"20/04/2026")) -> 44 | S28: {=_xlfn.IFS(Q28<1965,"Baby Boomers",Q28<1981,"Gen X",Q28<1997,"Millenial",TRUE,("Gen Z"))} -> Millenial
A29: 3454 | B29: Leon | C29: Beard | D29: =Table13[[#This Row],[FirstName]]&" "&Table13[[#This Row],[LastName]] -> Leon Beard | E29: 44815 | G29: Active | H29: Full-Time | I29: Zone C | J29: Full-Time | K29: It/Is | L29: General - Con | M29: 25597 | N29: Foreman | O29: 4 | P29: =IF(F29="","Active","Non-Active") -> Active | Q29: =YEAR(M29) -> 1970 | R29: =INT(YEARFRAC(M29,"20/04/2026")) -> 56 | S29: {=_xlfn.IFS(Q29<1965,"Baby Boomers",Q29<1981,"Gen X",Q29<1997,"Millenial",TRUE,("Gen Z"))} -> Gen X
A30: 3455 | B30: Charity | C30: Miranda | D30: =Table13[[#This Row],[FirstName]]&" "&Table13[[#This Row],[LastName]] -> Charity Miranda | E30: 44376 | F30: 44747 | G30: Active | H30: Full-Time | I30: Zone C | J30: Temporary | K30: Sales | L30: Project Management - Eng | M30: 36178 | N30: Manager | O30: 4 | P30: =IF(F30="","Active","Non-Active") -> Non-Active | Q30: =YEAR(M30) -> 1999 | R30: =INT(YEARFRAC(M30,"20/04/2026")) -> 27 | S30: {=_xlfn.IFS(Q30<1965,"Baby Boomers",Q30<1981,"Gen X",Q30<1997,"Millenial",TRUE,("Gen Z"))} -> Gen Z
A31: 3456 | B31: Axel | C31: Howe | D31: =Table13[[#This Row],[FirstName]]&" "&Table13[[#This Row],[LastName]] -> Axel Howe | E31: 44991 | G31: Active | H31: Full-Time | I31: Zone A | J31: Temporary | K31: Sales | L31: Field Operations | M31: 17070 | N31: Technician | O31: 3 | P31: =IF(F31="","Active","Non-Active") -> Active | Q31: =YEAR(M31) -> 1946 | R31: =INT(YEARFRAC(M31,"20/04/2026")) -> 79 | S31: {=_xlfn.IFS(Q31<1965,"Baby Boomers",Q31<1981,"Gen X",Q31<1997,"Millenial",TRUE,("Gen Z"))} -> Baby Boomers
A32: 3457 | B32: Milton | C32: Wall | D32: =Table13[[#This Row],[FirstName]]&" "&Table13[[#This Row],[LastName]] -> Milton Wall | E32: 44099 | G32: Active | H32: Full-Time | I32: Zone B | J32: Temporary | K32: Sales | L32: Engineers | M32: 17402 | N32: Technician | O32: 3 | P32: =IF(F32="","Active","Non-Active") -> Active | Q32: =YEAR(M32) -> 1947 | R32: =INT(YEARFRAC(M32,"20/04/2026")) -> 78 | S32: {=_xlfn.IFS(Q32<1965,"Baby Boomers",Q32<1981,"Gen X",Q32<1997,"Millenial",TRUE,("Gen Z"))} -> Baby Boomers
A33: 3458 | B33: Cory | C33: Robinson | D33: =Table13[[#This Row],[FirstName]]&" "&Table13[[#This Row],[LastName]] -> Cory Robinson | E33: 44679 | F33: 45070 | G33: Future Start | H33: Contract | I33: Zone A | J33: Full-Time | K33: Sales | L33: Field Operations | M33: 35289 | N33: Laborer | O33: 3 | P33: =IF(F33="","Active","Non-Active") -> Non-Active | Q33: =YEAR(M33) -> 1996 | R33: =INT(YEARFRAC(M33,"20/04/2026")) -> 29 | S33: {=_xlfn.IFS(Q33<1965,"Baby Boomers",Q33<1981,"Gen X",Q33<1997,"Millenial",TRUE,("Gen Z"))} -> Millenial
A34: 3459 | B34: Saniya | C34: Yu | D34: =Table13[[#This Row],[FirstName]]&" "&Table13[[#This Row],[LastName]] -> Saniya Yu | E34: 44304 | F34: 44733 | G34: Future Start | H34: Part-Time | I34: Zone A | J34: Full-Time | K34: Sales | L34: General - Con | M34: 16111 | N34: Splicer | O34: 2 | P34: =IF(F34="","Active","Non-Active") -> Non-Active | Q34: =YEAR(M34) -> 1944 | R34: =INT(YEARFRAC(M34,"20/04/2026")) -> 82 | S34: {=_xlfn.IFS(Q34<1965,"Baby Boomers",Q34<1981,"Gen X",Q34<1997,"Millenial",TRUE,("Gen Z"))} -> Baby Boomers
A35: 3460 | B35: Alisa | C35: James | D35: =Table13[[#This Row],[FirstName]]&" "&Table13[[#This Row],[LastName]] -> Alisa James | E35: 43880 | G35: Active | H35: Full-Time | I35: Zone A | J35: Full-Time | K35: Sales | L35: Aerial | M35: 16112 | N35: Lineman | O35: 3 | P35: =IF(F35="","Active","Non-Active") -> Active | Q35: =YEAR(M35) -> 1944 | R35: =INT(YEARFRAC(M35,"20/04/2026")) -> 82 | S35: {=_xlfn.IFS(Q35<1965,"Baby Boomers",Q35<1981,"Gen X",Q35<1997,"Millenial",TRUE,("Gen Z"))} -> Baby Boomers
A36: 3461 | B36: Lincoln | C36: Compton | D36: =Table13[[#This Row],[FirstName]]&" "&Table13[[#This Row],[LastName]] -> Lincoln Compton | E36: 43664 | F36: 44470 | G36: Future Start | H36: Full-Time | I36: Zone C | J36: Part-Time | K36: Sales | L36: General - Con | M36: 35793 | N36: Foreman | O36: 1 | P36: =IF(F36="","Active","Non-Active") -> Non-Active | Q36: =YEAR(M36) -> 1997 | R36: =INT(YEARFRAC(M36,"20/04/2026")) -> 28 | S36: {=_xlfn.IFS(Q36<1965,"Baby Boomers",Q36<1981,"Gen X",Q36<1997,"Millenial",TRUE,("Gen Z"))} -> Gen Z
A37: 3462 | B37: Aliana | C37: Nolan | D37: =Table13[[#This Row],[FirstName]]&" "&Table13[[#This Row],[LastName]] -> Aliana Nolan | E37: 43356 | F37: 44456 | G37: Active | H37: Contract | I37: Zone A | J37: Full-Time | K37: Sales | L37: Field Operations | M37: 15562 | N37: Coordinator | O37: 3 | P37: =IF(F37="","Active","Non-Active") -> Non-Active | Q37: =YEAR(M37) -> 1942 | R37: =INT(YEARFRAC(M37,"20/04/2026")) -> 83 | S37: {=_xlfn.IFS(Q37<1965,"Baby Boomers",Q37<1981,"Gen X",Q37<1997,"Millenial",TRUE,("Gen Z"))} -> Baby Boomers
A38: 3463 | B38: Kayden | C38: Dodson | D38: =Table13[[#This Row],[FirstName]]&" "&Table13[[#This Row],[LastName]] -> Kayden Dodson | E38: 43951 | F38: 44395 | G38: Active | H38: Part-Time | I38: Zone A | J38: Temporary | K38: Sales | L38: Field Operations | M38: 18800 | N38: Tower Hand | O38: 1 | P38: =IF(F38="","Active","Non-Active") -> Non-Active | Q38: =YEAR(M38) -> 1951 | R38: =INT(YEARFRAC(M38,"20/04/2026")) -> 74 | S38: {=_xlfn.IFS(Q38<1965,"Baby Boomers",Q38<1981,"Gen X",Q38<1997,"Millenial",TRUE,("Gen Z"))} -> Baby Boomers
A39: 3464 | B39: James | C39: Duke | D39: =Table13[[#This Row],[FirstName]]&" "&Table13[[#This Row],[LastName]] -> James Duke | E39: 43437 | F39: 44813 | G39: Active | H39: Contract | I39: Zone B | J39: Full-Time | K39: Sales | L39: Shop (Fleet) | M39: 35963 | N39: Mechanic | O39: 5 | P39: =IF(F39="","Active","Non-Active") -> Non-Active | Q39: =YEAR(M39) -> 1998 | R39: =INT(YEARFRAC(M39,"20/04/2026")) -> 27 | S39: {=_xlfn.IFS(Q39<1965,"Baby Boomers",Q39<1981,"Gen X",Q39<1997,"Millenial",TRUE,("Gen Z"))} -> Gen Z
A40: 3465 | B40: Willow | C40: Stuart | D40: =Table13[[#This Row],[FirstName]]&" "&Table13[[#This Row],[LastName]] -> Willow Stuart | E40: 44508 | G40: Active | H40: Full-Time | I40: Zone B | J40: Full-Time | K40: Sales | L40: General - Con | M40: 22653 | N40: Flagger | O40: 3 | P40: =IF(F40="","Active","Non-Active") -> Active | Q40: =YEAR(M40) -> 1962 | R40: =INT(YEARFRAC(M40,"20/04/2026")) -> 64 | S40: {=_xlfn.IFS(Q40<1965,"Baby Boomers",Q40<1981,"Gen X",Q40<1997,"Millenial",TRUE,("Gen Z"))} -> Baby Boomers
A41: 3466 | B41: Clayton | C41: Walker | D41: =Table13[[#This Row],[FirstName]]&" "&Table13[[#This Row],[LastName]] -> Clayton Walker | E41: 44664 | F41: 45026 | G41: Active | H41: Part-Time | I41: Zone C | J41: Full-Time | K41: It/Is | L41: Aerial | M41: 28881 | N41: Supervisor | O41: 4 | P41: =IF(F41="","Active","Non-Active") -> Non-Active | Q41: =YEAR(M41) -> 1979 | R41: =INT(YEARFRAC(M41,"20/04/2026")) -> 47 | S41: {=_xlfn.IFS(Q41<1965,"Baby Boomers",Q41<1981,"Gen X",Q41<1997,"Millenial",TRUE,("Gen Z"))} -> Gen X
A42: 3467 | B42: Celia | C42: Curtis | D42: =Table13[[#This Row],[FirstName]]&" "&Table13[[#This Row],[LastName]] -> Celia Curtis | E42: 43957 | G42: Active | H42: Contract | I42: Zone A | J42: Part-Time | K42: Sales | L42: Fielders | M42: 31911 | N42: Engineer | O42: 1 | P42: =IF(F42="","Active","Non-Active") -> Active | Q42: =YEAR(M42) -> 1987 | R42: =INT(YEARFRAC(M42,"20/04/2026")) -> 38 | S42: {=_xlfn.IFS(Q42<1965,"Baby Boomers",Q42<1981,"Gen X",Q42<1997,"Millenial",TRUE,("Gen Z"))} -> Millenial
A43: 3468 | B43: Valentin | C43: Reilly | D43: =Table13[[#This Row],[FirstName]]&" "&Table13[[#This Row],[LastName]] -> Valentin Reilly | E43: 43717 | G43: Active | H43: Contract | I43: Zone B | J43: Temporary | K43: Sales | L43: Wireline Construction | M43: 35911 | N43: Foreman | O43: 4 | P43: =IF(F43="","Active","Non-Active") -> Active | Q43: =YEAR(M43) -> 1998 | R43: =INT(YEARFRAC(M43,"20/04/2026")) -> 27 | S43: {=_xlfn.IFS(Q43<1965,"Baby Boomers",Q43<1981,"Gen X",Q43<1997,"Millenial",TRUE,("Gen Z"))} -> Gen Z
A44: 3469 | B44: Ryland | C44: Shepherd | D44: =Table13[[#This Row],[FirstName]]&" "&Table13[[#This Row],[LastName]] -> Ryland Shepherd | E44: 44041 | F44: 44931 | G44: Future Start | H44: Contract | I44: Zone B | J44: Full-Time | K44: Sales | L44: Field Operations | M44: 16489 | N44: Driver | O44: 3 | P44: =IF(F44="","Active","Non-Active") -> Non-Active | Q44: =YEAR(M44) -> 1945 | R44: =INT(YEARFRAC(M44,"20/04/2026")) -> 81 | S44: {=_xlfn.IFS(Q44<1965,"Baby Boomers",Q44<1981,"Gen X",Q44<1997,"Millenial",TRUE,("Gen Z"))} -> Baby Boomers
A45: 3470 | B45: Esteban | C45: Gilbert | D45: =Table13[[#This Row],[FirstName]]&" "&Table13[[#This Row],[LastName]] -> Esteban Gilbert | E45: 43418 | F45: 43766 | G45: Future Start | H45: Contract | I45: Zone C | J45: Part-Time | K45: Sales | L45: Field Operations | M45: 35581 | N45: Technician | O45: 3 | P45: =IF(F45="","Active","Non-Active") -> Non-Active | Q45: =YEAR(M45) -> 1997 | R45: =INT(YEARFRAC(M45,"20/04/2026")) -> 28 | S45: {=_xlfn.IFS(Q45<1965,"Baby Boomers",Q45<1981,"Gen X",Q45<1997,"Millenial",TRUE,("Gen Z"))} -> Gen Z
A46: 3471 | B46: Jonathan | C46: Adkins | D46: =Table13[[#This Row],[FirstName]]&" "&Table13[[#This Row],[LastName]] -> Jonathan Adkins | E46: 43890 | G46: Active | H46: Part-Time | I46: Zone C | J46: Temporary | K46: Sales | L46: Field Operations | M46: 24475 | N46: Foreman | O46: 4 | P46: =IF(F46="","Active","Non-Active") -> Active | Q46: =YEAR(M46) -> 1967 | R46: =INT(YEARFRAC(M46,"20/04/2026")) -> 59 | S46: {=_xlfn.IFS(Q46<1965,"Baby Boomers",Q46<1981,"Gen X",Q46<1997,"Millenial",TRUE,("Gen Z"))} -> Gen X
A47: 3472 | B47: Nevaeh | C47: Soto | D47: =Table13[[#This Row],[FirstName]]&" "&Table13[[#This Row],[LastName]] -> Nevaeh Soto | E47: 44941 | G47: Active | H47: Contract | I47: Zone C | J47: Full-Time | K47: Sales | L47: Project Management - Con | M47: 29963 | N47: Director | O47: 4 | P47: =IF(F47="","Active","Non-Active") -> Active | Q47: =YEAR(M47) -> 1982 | R47: =INT(YEARFRAC(M47,"20/04/2026")) -> 44 | S47: {=_xlfn.IFS(Q47<1965,"Baby Boomers",Q47<1981,"Gen X",Q47<1997,"Millenial",TRUE,("Gen Z"))} -> Millenial
A48: 3473 | B48: Chaim | C48: Mata | D48: =Table13[[#This Row],[FirstName]]&" "&Table13[[#This Row],[LastName]] -> Chaim Mata | E48: 45106 | G48: Active | H48: Part-Time | I48: Zone A | J48: Temporary | K48: Sales | L48: Shop (Fleet) | M48: 18537 | N48: Manager | O48: 2 | P48: =IF(F48="","Active","Non-Active") -> Active | Q48: =YEAR(M48) -> 1950 | R48: =INT(YEARFRAC(M48,"20/04/2026")) -> 75 | S48: {=_xlfn.IFS(Q48<1965,"Baby Boomers",Q48<1981,"Gen X",Q48<1997,"Millenial",TRUE,("Gen Z"))} -> Baby Boomers
A49: 3474 | B49: Arely | C49: Patton | D49: =Table13[[#This Row],[FirstName]]&" "&Table13[[#This Row],[LastName]] -> Arely Patton | E49: 43899 | G49: Active | H49: Full-Time | I49: Zone A | J49: Temporary | K49: Sales | L49: Catv | M49: 24092 | N49: Laborer | O49: 2 | P49: =IF(F49="","Active","Non-Active") -> Active | Q49: =YEAR(M49) -> 1965 | R49: =INT(YEARFRAC(M49,"20/04/2026")) -> 60 | S49: {=_xlfn.IFS(Q49<1965,"Baby Boomers",Q49<1981,"Gen X",Q49<1997,"Millenial",TRUE,("Gen Z"))} -> Gen X
A50: 3475 | B50: Vance | C50: Trujillo | D50: =Table13[[#This Row],[FirstName]]&" "&Table13[[#This Row],[LastName]] -> Vance Trujillo | E50: 44460 | F50: 45029 | G50: Active | H50: Full-Time | I50: Zone C | J50: Temporary | K50: Sales | L50: General - Con | M50: 21179 | N50: Foreman | O50: 2 | P50: =IF(F50="","Active","Non-Active") -> Non-Active | Q50: =YEAR(M50) -> 1957 | R50: =INT(YEARFRAC(M50,"20/04/2026")) -> 68 | S50: {=_xlfn.IFS(Q50<1965,"Baby Boomers",Q50<1981,"Gen X",Q50<1997,"Millenial",TRUE,("Gen Z"))} -> Baby Boomers
A51: 3476 | B51: Charlie | C51: Koch | D51: =Table13[[#This Row],[FirstName]]&" "&Table13[[#This Row],[LastName]] -> Charlie Koch | E51: 45089 | F51: 45113 | G51: Active | H51: Part-Time | I51: Zone A | J51: Temporary | K51: Sales | L51: Fielders | M51: 16608 | N51: Engineer | O51: 2 | P51: =IF(F51="","Active","Non-Active") -> Non-Active | Q51: =YEAR(M51) -> 1945 | R51: =INT(YEARFRAC(M51,"20/04/2026")) -> 80 | S51: {=_xlfn.IFS(Q51<1965,"Baby Boomers",Q51<1981,"Gen X",Q51<1997,"Millenial",TRUE,("Gen Z"))} -> Baby Boomers
A52: 3477 | B52: Sonny | C52: Horne | D52: =Table13[[#This Row],[FirstName]]&" "&Table13[[#This Row],[LastName]] -> Sonny Horne | E52: 43562 | G52: Active | H52: Part-Time | I52: Zone A | J52: Full-Time | K52: It/Is | L52: Aerial | M52: 25540 | N52: Laborer | O52: 2 | P52: =IF(F52="","Active","Non-Active") -> Active | Q52: =YEAR(M52) -> 1969 | R52: =INT(YEARFRAC(M52,"20/04/2026")) -> 56 | S52: {=_xlfn.IFS(Q52<1965,"Baby Boomers",Q52<1981,"Gen X",Q52<1997,"Millenial",TRUE,("Gen Z"))} -> Gen X
A53: 3478 | B53: Thomas | C53: Chandler | D53: =Table13[[#This Row],[FirstName]]&" "&Table13[[#This Row],[LastName]] -> Thomas Chandler | E53: 43360 | F53: 43474 | G53: Active | H53: Full-Time | I53: Zone C | J53: Temporary | K53: Sales | L53: Wireline Construction | M53: 21103 | N53: Groundman | O53: 2 | P53: =IF(F53="","Active","Non-Active") -> Non-Active | Q53: =YEAR(M53) -> 1957 | R53: =INT(YEARFRAC(M53,"20/04/2026")) -> 68 | S53: {=_xlfn.IFS(Q53<1965,"Baby Boomers",Q53<1981,"Gen X",Q53<1997,"Millenial",TRUE,("Gen Z"))} -> Baby Boomers
A54: 3479 | B54: Sarai | C54: Stone | D54: =Table13[[#This Row],[FirstName]]&" "&Table13[[#This Row],[LastName]] -> Sarai Stone | E54: 44775 | F54: 45018 | G54: Active | H54: Contract | I54: Zone A | J54: Part-Time | K54: Sales | L54: Project Management - Con | M54: 22783 | N54: Technician | O54: 2 | P54: =IF(F54="","Active","Non-Active") -> Non-Active | Q54: =YEAR(M54) -> 1962 | R54: =INT(YEARFRAC(M54,"20/04/2026")) -> 63 | S54: {=_xlfn.IFS(Q54<1965,"Baby Boomers",Q54<1981,"Gen X",Q54<1997,"Millenial",TRUE,("Gen Z"))} -> Baby Boomers
A55: 3480 | B55: Jerimiah | C55: Harmon | D55: =Table13[[#This Row],[FirstName]]&" "&Table13[[#This Row],[LastName]] -> Jerimiah Harmon | E55: 44812 | F55: 44850 | G55: Future Start | H55: Full-Time | I55: Zone C | J55: Temporary | K55: Sales | L55: Catv | M55: 17023 | N55: Supervisor | O55: 1 | P55: =IF(F55="","Active","Non-Active") -> Non-Active | Q55: =YEAR(M55) -> 1946 | R55: =INT(YEARFRAC(M55,"20/04/2026")) -> 79 | S55: {=_xlfn.IFS(Q55<1965,"Baby Boomers",Q55<1981,"Gen X",Q55<1997,"Millenial",TRUE,("Gen Z"))} -> Baby Boomers
A56: 3481 | B56: Leland | C56: Allen | D56: =Table13[[#This Row],[FirstName]]&" "&Table13[[#This Row],[LastName]] -> Leland Allen | E56: 43531 | F56: 44347 | G56: Future Start | H56: Full-Time | I56: Zone C | J56: Part-Time | K56: Sales | L56: Wireline Construction | M56: 24087 | N56: Splicer | O56: 4 | P56: =IF(F56="","Active","Non-Active") -> Non-Active | Q56: =YEAR(M56) -> 1965 | R56: =INT(YEARFRAC(M56,"20/04/2026")) -> 60 | S56: {=_xlfn.IFS(Q56<1965,"Baby Boomers",Q56<1981,"Gen X",Q56<1997,"Millenial",TRUE,("Gen Z"))} -> Gen X
A57: 3482 | B57: Cristal | C57: Bolton | D57: =Table13[[#This Row],[FirstName]]&" "&Table13[[#This Row],[LastName]] -> Cristal Bolton | E57: 43767 | F57: 44234 | G57: Future Start | H57: Full-Time | I57: Zone A | J57: Temporary | K57: Sales | L57: Catv | M57: 32915 | N57: Lineman | O57: 2 | P57: =IF(F57="","Active","Non-Active") -> Non-Active | Q57: =YEAR(M57) -> 1990 | R57: =INT(YEARFRAC(M57,"20/04/2026")) -> 36 | S57: {=_xlfn.IFS(Q57<1965,"Baby Boomers",Q57<1981,"Gen X",Q57<1997,"Millenial",TRUE,("Gen Z"))} -> Millenial
A58: 3483 | B58: Jaslene | C58: Harding | D58: =Table13[[#This Row],[FirstName]]&" "&Table13[[#This Row],[LastName]] -> Jaslene Harding | E58: 44465 | G58: Active | H58: Part-Time | I58: Zone B | J58: Temporary | K58: Sales | L58: Project Management - Con | M58: 23547 | N58: Coordinator | O58: 1 | P58: =IF(F58="","Active","Non-Active") -> Active | Q58: =YEAR(M58) -> 1964 | R58: =INT(YEARFRAC(M58,"20/04/2026")) -> 61 | S58: {=_xlfn.IFS(Q58<1965,"Baby Boomers",Q58<1981,"Gen X",Q58<1997,"Millenial",TRUE,("Gen Z"))} -> Baby Boomers
A59: 3484 | B59: Albert | C59: Gonzalez | D59: =Table13[[#This Row],[FirstName]]&" "&Table13[[#This Row],[LastName]] -> Albert Gonzalez | E59: 43341 | G59: Active | H59: Part-Time | I59: Zone B | J59: Full-Time | K59: Sales | L59: General - Con | M59: 34898 | N59: Model Assistant | O59: 4 | P59: =IF(F59="","Active","Non-Active") -> Active | Q59: =YEAR(M59) -> 1995 | R59: =INT(YEARFRAC(M59,"20/04/2026")) -> 30 | S59: {=_xlfn.IFS(Q59<1965,"Baby Boomers",Q59<1981,"Gen X",Q59<1997,"Millenial",TRUE,("Gen Z"))} -> Millenial
A60: 3485 | B60: Jaiden | C60: Johnson | D60: =Table13[[#This Row],[FirstName]]&" "&Table13[[#This Row],[LastName]] -> Jaiden Johnson | E60: 44495 | G60: Active | H60: Contract | I60: Zone C | J60: Full-Time | K60: Sales | L60: Field Operations | M60: 34568 | N60: Laborer | O60: 5 | P60: =IF(F60="","Active","Non-Active") -> Active | Q60: =YEAR(M60) -> 1994 | R60: =INT(YEARFRAC(M60,"20/04/2026")) -> 31 | S60: {=_xlfn.IFS(Q60<1965,"Baby Boomers",Q60<1981,"Gen X",Q60<1997,"Millenial",TRUE,("Gen Z"))} -> Millenial
A61: 3486 | B61: Brendon | C61: Mcconnell | D61: =Table13[[#This Row],[FirstName]]&" "&Table13[[#This Row],[LastName]] -> Brendon Mcconnell | E61: 44865 | F61: 45085 | G61: Active | H61: Part-Time | I61: Zone C | J61: Temporary | K61: Sales | L61: Fielders | M61: 33191 | N61: Engineer | O61: 4 | P61: =IF(F61="","Active","Non-Active") -> Non-Active | Q61: =YEAR(M61) -> 1990 | R61: =INT(YEARFRAC(M61,"20/04/2026")) -> 35 | S61: {=_xlfn.IFS(Q61<1965,"Baby Boomers",Q61<1981,"Gen X",Q61<1997,"Millenial",TRUE,("Gen Z"))} -> Millenial
A62: 3487 | B62: Kimora | C62: Parsons | D62: =Table13[[#This Row],[FirstName]]&" "&Table13[[#This Row],[LastName]] -> Kimora Parsons | E62: 45000 | G62: Active | H62: Contract | I62: Zone B | J62: Part-Time | K62: Sales | L62: General - Sga | M62: 34366 | N62: Administrator | O62: 4 | P62: =IF(F62="","Active","Non-Active") -> Active | Q62: =YEAR(M62) -> 1994 | R62: =INT(YEARFRAC(M62,"20/04/2026")) -> 32 | S62: {=_xlfn.IFS(Q62<1965,"Baby Boomers",Q62<1981,"Gen X",Q62<1997,"Millenial",TRUE,("Gen Z"))} -> Millenial
A63: 3488 | B63: Willie | C63: Patterson | D63: =Table13[[#This Row],[FirstName]]&" "&Table13[[#This Row],[LastName]] -> Willie Patterson | E63: 44813 | G63: Active | H63: Contract | I63: Zone B | J63: Full-Time | K63: Sales | L63: Wireline Construction | M63: 35746 | N63: Lineman | O63: 2 | P63: =IF(F63="","Active","Non-Active") -> Active | Q63: =YEAR(M63) -> 1997 | R63: =INT(YEARFRAC(M63,"20/04/2026")) -> 28 | S63: {=_xlfn.IFS(Q63<1965,"Baby Boomers",Q63<1981,"Gen X",Q63<1997,"Millenial",TRUE,("Gen Z"))} -> Gen Z
A64: 3489 | B64: Devyn | C64: Powers | D64: =Table13[[#This Row],[FirstName]]&" "&Table13[[#This Row],[LastName]] -> Devyn Powers | E64: 44624 | G64: Active | H64: Part-Time | I64: Zone A | J64: Temporary | K64: Sales | L64: Field Operations | M64: 19481 | N64: Laborer | O64: 2 | P64: =IF(F64="","Active","Non-Active") -> Active | Q64: =YEAR(M64) -> 1953 | R64: =INT(YEARFRAC(M64,"20/04/2026")) -> 72 | S64: {=_xlfn.IFS(Q64<1965,"Baby Boomers",Q64<1981,"Gen X",Q64<1997,"Millenial",TRUE,("Gen Z"))} -> Baby Boomers
A65: 3490 | B65: Weston | C65: Preston | D65: =Table13[[#This Row],[FirstName]]&" "&Table13[[#This Row],[LastName]] -> Weston Preston | E65: 43507 | G65: Active | H65: Part-Time | I65: Zone A | J65: Part-Time | K65: Sales | L65: General - Sga | M65: 33429 | N65: Director | O65: 2 | P65: =IF(F65="","Active","Non-Active") -> Active | Q65: =YEAR(M65) -> 1991 | R65: =INT(YEARFRAC(M65,"20/04/2026")) -> 34 | S65: {=_xlfn.IFS(Q65<1965,"Baby Boomers",Q65<1981,"Gen X",Q65<1997,"Millenial",TRUE,("Gen Z"))} -> Millenial
A66: 3491 | B66: Lennon | C66: Buchanan | D66: =Table13[[#This Row],[FirstName]]&" "&Table13[[#This Row],[LastName]] -> Lennon Buchanan | E66: 44222 | G66: Active | H66: Contract | I66: Zone B | J66: Full-Time | K66: Sales | L66: Field Operations | M66: 26817 | N66: Driver | O66: 5 | P66: =IF(F66="","Active","Non-Active") -> Active | Q66: =YEAR(M66) -> 1973 | R66: =INT(YEARFRAC(M66,"20/04/2026")) -> 52 | S66: {=_xlfn.IFS(Q66<1965,"Baby Boomers",Q66<1981,"Gen X",Q66<1997,"Millenial",TRUE,("Gen Z"))} -> Gen X
A67: 3492 | B67: Vicente | C67: Merritt | D67: =Table13[[#This Row],[FirstName]]&" "&Table13[[#This Row],[LastName]] -> Vicente Merritt | E67: 43795 | G67: Active | H67: Full-Time | I67: Zone C | J67: Full-Time | K67: Sales | L67: General - Con | M67: 33977 | N67: Clerk | O67: 1 | P67: =IF(F67="","Active","Non-Active") -> Active | Q67: =YEAR(M67) -> 1993 | R67: =INT(YEARFRAC(M67,"20/04/2026")) -> 33 | S67: {=_xlfn.IFS(Q67<1965,"Baby Boomers",Q67<1981,"Gen X",Q67<1997,"Millenial",TRUE,("Gen Z"))} -> Millenial
A68: 3493 | B68: Hugo | C68: Clay | D68: =Table13[[#This Row],[FirstName]]&" "&Table13[[#This Row],[LastName]] -> Hugo Clay | E68: 43661 | G68: Active | H68: Full-Time | I68: Zone C | J68: Full-Time | K68: Sales | L68: Project Management - Con | M68: 30789 | N68: Project Manager | O68: 5 | P68: =IF(F68="","Active","Non-Active") -> Active | Q68: =YEAR(M68) -> 1984 | R68: =INT(YEARFRAC(M68,"20/04/2026")) -> 42 | S68: {=_xlfn.IFS(Q68<1965,"Baby Boomers",Q68<1981,"Gen X",Q68<1997,"Millenial",TRUE,("Gen Z"))} -> Millenial
A69: 3494 | B69: Cohen | C69: Raymond | D69: =Table13[[#This Row],[FirstName]]&" "&Table13[[#This Row],[LastName]] -> Cohen Raymond | E69: 44000 | G69: Active | H69: Contract | I69: Zone B | J69: Full-Time | K69: Sales | L69: General - Con | M69: 34373 | N69: Technician | O69: 4 | P69: =IF(F69="","Active","Non-Active") -> Active | Q69: =YEAR(M69) -> 1994 | R69: =INT(YEARFRAC(M69,"20/04/2026")) -> 32 | S69: {=_xlfn.IFS(Q69<1965,"Baby Boomers",Q69<1981,"Gen X",Q69<1997,"Millenial",TRUE,("Gen Z"))} -> Millenial
A70: 3495 | B70: Tia | C70: Ellis | D70: =Table13[[#This Row],[FirstName]]&" "&Table13[[#This Row],[LastName]] -> Tia Ellis | E70: 45099 | F70: 45129 | G70: Active | H70: Part-Time | I70: Zone B | J70: Temporary | K70: Sales | L70: Wireline Construction | M70: 33996 | N70: Laborer | O70: 4 | P70: =IF(F70="","Active","Non-Active") -> Non-Active | Q70: =YEAR(M70) -> 1993 | R70: =INT(YEARFRAC(M70,"20/04/2026")) -> 33 | S70: {=_xlfn.IFS(Q70<1965,"Baby Boomers",Q70<1981,"Gen X",Q70<1997,"Millenial",TRUE,("Gen Z"))} -> Millenial
A71: 3496 | B71: Aspen | C71: Bentley | D71: =Table13[[#This Row],[FirstName]]&" "&Table13[[#This Row],[LastName]] -> Aspen Bentley | E71: 44532 | G71: Active | H71: Contract | I71: Zone A | J71: Part-Time | K71: Sales | L71: General - Sga | M71: 23639 | N71: Administrator | O71: 5 | P71: =IF(F71="","Active","Non-Active") -> Active | Q71: =YEAR(M71) -> 1964 | R71: =INT(YEARFRAC(M71,"20/04/2026")) -> 61 | S71: {=_xlfn.IFS(Q71<1965,"Baby Boomers",Q71<1981,"Gen X",Q71<1997,"Millenial",TRUE,("Gen Z"))} -> Baby Boomers
A72: 3497 | B72: Graham | C72: Rodriguez | D72: =Table13[[#This Row],[FirstName]]&" "&Table13[[#This Row],[LastName]] -> Graham Rodriguez | E72: 44538 | G72: Active | H72: Part-Time | I72: Zone C | J72: Temporary | K72: Sales | L72: Project Management - Con | M72: 29635 | N72: Lineman | O72: 1 | P72: =IF(F72="","Active","Non-Active") -> Active | Q72: =YEAR(M72) -> 1981 | R72: =INT(YEARFRAC(M72,"20/04/2026")) -> 45 | S72: {=_xlfn.IFS(Q72<1965,"Baby Boomers",Q72<1981,"Gen X",Q72<1997,"Millenial",TRUE,("Gen Z"))} -> Millenial
A73: 3498 | B73: Joel | C73: Mcmillan | D73: =Table13[[#This Row],[FirstName]]&" "&Table13[[#This Row],[LastName]] -> Joel Mcmillan | E73: 45042 | F73: 45099 | G73: Active | H73: Full-Time | I73: Zone A | J73: Full-Time | K73: Sales | L73: General - Sga | M73: 36085 | N73: Laborer | O73: 2 | P73: =IF(F73="","Active","Non-Active") -> Non-Active | Q73: =YEAR(M73) -> 1998 | R73: =INT(YEARFRAC(M73,"20/04/2026")) -> 27 | S73: {=_xlfn.IFS(Q73<1965,"Baby Boomers",Q73<1981,"Gen X",Q73<1997,"Millenial",TRUE,("Gen Z"))} -> Gen Z
A74: 3499 | B74: Maci | C74: Frost | D74: =Table13[[#This Row],[FirstName]]&" "&Table13[[#This Row],[LastName]] -> Maci Frost | E74: 43368 | F74: 44550 | G74: Active | H74: Part-Time | I74: Zone C | J74: Temporary | K74: Sales | L74: Field Operations | M74: 25949 | N74: Technician | O74: 5 | P74: =IF(F74="","Active","Non-Active") -> Non-Active | Q74: =YEAR(M74) -> 1971 | R74: =INT(YEARFRAC(M74,"20/04/2026")) -> 55 | S74: {=_xlfn.IFS(Q74<1965,"Baby Boomers",Q74<1981,"Gen X",Q74<1997,"Millenial",TRUE,("Gen Z"))} -> Gen X
A75: 3500 | B75: Nevaeh | C75: Lucas | D75: =Table13[[#This Row],[FirstName]]&" "&Table13[[#This Row],[LastName]] -> Nevaeh Lucas | E75: 43424 | F75: 44003 | G75: Active | H75: Full-Time | I75: Zone B | J75: Part-Time | K75: Sales | L75: Shop (Fleet) | M75: 36581 | N75: Mechanic | O75: 1 | P75: =IF(F75="","Active","Non-Active") -> Non-Active | Q75: =YEAR(M75) -> 2000 | R75: =INT(YEARFRAC(M75,"20/04/2026")) -> 26 | S75: {=_xlfn.IFS(Q75<1965,"Baby Boomers",Q75<1981,"Gen X",Q75<1997,"Millenial",TRUE,("Gen Z"))} -> Gen Z
A76: 3501 | B76: Garrett | C76: Zimmerman | D76: =Table13[[#This Row],[FirstName]]&" "&Table13[[#This Row],[LastName]] -> Garrett Zimmerman | E76: 44073 | F76: 44803 | G76: Future Start | H76: Part-Time | I76: Zone A | J76: Part-Time | K76: Sales | L76: General - Con | M76: 21659 | N76: Technician | O76: 4 | P76: =IF(F76="","Active","Non-Active") -> Non-Active | Q76: =YEAR(M76) -> 1959 | R76: =INT(YEARFRAC(M76,"20/04/2026")) -> 67 | S76: {=_xlfn.IFS(Q76<1965,"Baby Boomers",Q76<1981,"Gen X",Q76<1997,"Millenial",TRUE,("Gen Z"))} -> Baby Boomers
A77: 3502 | B77: Eugene | C77: Marks | D77: =Table13[[#This Row],[FirstName]]&" "&Table13[[#This Row],[LastName]] -> Eugene Marks | E77: 43739 | G77: Active | H77: Full-Time | I77: Zone C | J77: Temporary | K77: Sales | L77: Splicing | M77: 27940 | N77: Electrician | O77: 1 | P77: =IF(F77="","Active","Non-Active") -> Active | Q77: =YEAR(M77) -> 1976 | R77: =INT(YEARFRAC(M77,"20/04/2026")) -> 49 | S77: {=_xlfn.IFS(Q77<1965,"Baby Boomers",Q77<1981,"Gen X",Q77<1997,"Millenial",TRUE,("Gen Z"))} -> Gen X
A78: 3503 | B78: Geovanni | C78: Pugh | D78: =Table13[[#This Row],[FirstName]]&" "&Table13[[#This Row],[LastName]] -> Geovanni Pugh | E78: 44581 | G78: Active | H78: Part-Time | I78: Zone A | J78: Temporary | K78: Sales | L78: Project Management - Con | M78: 18836 | N78: Manager | O78: 4 | P78: =IF(F78="","Active","Non-Active") -> Active | Q78: =YEAR(M78) -> 1951 | R78: =INT(YEARFRAC(M78,"20/04/2026")) -> 74 | S78: {=_xlfn.IFS(Q78<1965,"Baby Boomers",Q78<1981,"Gen X",Q78<1997,"Millenial",TRUE,("Gen Z"))} -> Baby Boomers
A79: 3504 | B79: Javon | C79: Kelley | D79: =Table13[[#This Row],[FirstName]]&" "&Table13[[#This Row],[LastName]] -> Javon Kelley | E79: 44479 | G79: Active | H79: Full-Time | I79: Zone B | J79: Part-Time | K79: Sales | L79: General - Con | M79: 29456 | N79: Laborer | O79: 2 | P79: =IF(F79="","Active","Non-Active") -> Active | Q79: =YEAR(M79) -> 1980 | R79: =INT(YEARFRAC(M79,"20/04/2026")) -> 45 | S79: {=_xlfn.IFS(Q79<1965,"Baby Boomers",Q79<1981,"Gen X",Q79<1997,"Millenial",TRUE,("Gen Z"))} -> Gen X
A80: 3505 | B80: Amaya | C80: Hicks | D80: =Table13[[#This Row],[FirstName]]&" "&Table13[[#This Row],[LastName]] -> Amaya Hicks | E80: 44072 | G80: Active | H80: Contract | I80: Zone B | J80: Temporary | K80: Sales | L80: Field Operations | M80: 15911 | N80: Groundman | O80: 1 | P80: =IF(F80="","Active","Non-Active") -> Active | Q80: =YEAR(M80) -> 1943 | R80: =INT(YEARFRAC(M80,"20/04/2026")) -> 82 | S80: {=_xlfn.IFS(Q80<1965,"Baby Boomers",Q80<1981,"Gen X",Q80<1997,"Millenial",TRUE,("Gen Z"))} -> Baby Boomers
A81: 3506 | B81: Laila | C81: Woodard | D81: =Table13[[#This Row],[FirstName]]&" "&Table13[[#This Row],[LastName]] -> Laila Woodard | E81: 43704 | F81: 45056 | G81: Active | H81: Full-Time | I81: Zone B | J81: Temporary | K81: Sales | L81: Field Operations | M81: 32330 | N81: Technician | O81: 2 | P81: =IF(F81="","Active","Non-Active") -> Non-Active | Q81: =YEAR(M81) -> 1988 | R81: =INT(YEARFRAC(M81,"20/04/2026")) -> 37 | S81: {=_xlfn.IFS(Q81<1965,"Baby Boomers",Q81<1981,"Gen X",Q81<1997,"Millenial",TRUE,("Gen Z"))} -> Millenial
A82: 3507 | B82: Ivan | C82: Huff | D82: =Table13[[#This Row],[FirstName]]&" "&Table13[[#This Row],[LastName]] -> Ivan Huff | E82: 44252 | F82: 45023 | G82: Active | H82: Full-Time | I82: Zone A | J82: Full-Time | K82: Sales | L82: Project Management - Con | M82: 26747 | N82: Manager | O82: 4 | P82: =IF(F82="","Active","Non-Active") -> Non-Active | Q82: =YEAR(M82) -> 1973 | R82: =INT(YEARFRAC(M82,"20/04/2026")) -> 53 | S82: {=_xlfn.IFS(Q82<1965,"Baby Boomers",Q82<1981,"Gen X",Q82<1997,"Millenial",TRUE,("Gen Z"))} -> Gen X
A83: 3508 | B83: Aidan | C83: Harding | D83: =Table13[[#This Row],[FirstName]]&" "&Table13[[#This Row],[LastName]] -> Aidan Harding | E83: 44390 | G83: Active | H83: Full-Time | I83: Zone B | J83: Part-Time | K83: Sales | L83: Aerial | M83: 15487 | N83: Laborer | O83: 5 | P83: =IF(F83="","Active","Non-Active") -> Active | Q83: =YEAR(M83) -> 1942 | R83: =INT(YEARFRAC(M83,"20/04/2026")) -> 83 | S83: {=_xlfn.IFS(Q83<1965,"Baby Boomers",Q83<1981,"Gen X",Q83<1997,"Millenial",TRUE,("Gen Z"))} -> Baby Boomers
A84: 3509 | B84: Cruz | C84: Boyer | D84: =Table13[[#This Row],[FirstName]]&" "&Table13[[#This Row],[LastName]] -> Cruz Boyer | E84: 44300 | G84: Active | H84: Part-Time | I84: Zone C | J84: Full-Time | K84: Sales | L84: General - Sga | M84: 28433 | N84: Project Controls | O84: 2 | P84: =IF(F84="","Active","Non-Active") -> Active | Q84: =YEAR(M84) -> 1977 | R84: =INT(YEARFRAC(M84,"20/04/2026")) -> 48 | S84: {=_xlfn.IFS(Q84<1965,"Baby Boomers",Q84<1981,"Gen X",Q84<1997,"Millenial",TRUE,("Gen Z"))} -> Gen X
A85: 3510 | B85: Raven | C85: Koch | D85: =Table13[[#This Row],[FirstName]]&" "&Table13[[#This Row],[LastName]] -> Raven Koch | E85: 43871 | G85: Active | H85: Part-Time | I85: Zone A | J85: Full-Time | K85: Sales | L85: General - Con | M85: 20745 | N85: Laborer | O85: 2 | P85: =IF(F85="","Active","Non-Active") -> Active | Q85: =YEAR(M85) -> 1956 | R85: =INT(YEARFRAC(M85,"20/04/2026")) -> 69 | S85: {=_xlfn.IFS(Q85<1965,"Baby Boomers",Q85<1981,"Gen X",Q85<1997,"Millenial",TRUE,("Gen Z"))} -> Baby Boomers
A86: 3511 | B86: Karli | C86: Barker | D86: =Table13[[#This Row],[FirstName]]&" "&Table13[[#This Row],[LastName]] -> Karli Barker | E86: 44425 | F86: 44561 | G86: Active | H86: Part-Time | I86: Zone B | J86: Full-Time | K86: Sales | L86: Finance & Accounting | M86: 35479 | N86: Director | O86: 4 | P86: =IF(F86="","Active","Non-Active") -> Non-Active | Q86: =YEAR(M86) -> 1997 | R86: =INT(YEARFRAC(M86,"20/04/2026")) -> 29 | S86: {=_xlfn.IFS(Q86<1965,"Baby Boomers",Q86<1981,"Gen X",Q86<1997,"Millenial",TRUE,("Gen Z"))} -> Gen Z
A87: 3512 | B87: Tyrone | C87: Sosa | D87: =Table13[[#This Row],[FirstName]]&" "&Table13[[#This Row],[LastName]] -> Tyrone Sosa | E87: 45033 | F87: 45099 | G87: Future Start | H87: Contract | I87: Zone C | J87: Temporary | K87: Sales | L87: Yard (Material Handling) | M87: 35363 | N87: Coordinator | O87: 2 | P87: =IF(F87="","Active","Non-Active") -> Non-Active | Q87: =YEAR(M87) -> 1996 | R87: =INT(YEARFRAC(M87,"20/04/2026")) -> 29 | S87: {=_xlfn.IFS(Q87<1965,"Baby Boomers",Q87<1981,"Gen X",Q87<1997,"Millenial",TRUE,("Gen Z"))} -> Millenial
A88: 3513 | B88: Damaris | C88: Cisneros | D88: =Table13[[#This Row],[FirstName]]&" "&Table13[[#This Row],[LastName]] -> Damaris Cisneros | E88: 44806 | F88: 45070 | G88: Future Start | H88: Contract | I88: Zone C | J88: Temporary | K88: Sales | L88: General - Con | M88: 21867 | N88: Laborer | O88: 5 | P88: =IF(F88="","Active","Non-Active") -> Non-Active | Q88: =YEAR(M88) -> 1959 | R88: =INT(YEARFRAC(M88,"20/04/2026")) -> 66 | S88: {=_xlfn.IFS(Q88<1965,"Baby Boomers",Q88<1981,"Gen X",Q88<1997,"Millenial",TRUE,("Gen Z"))} -> Baby Boomers
A89: 3514 | B89: Alexus | C89: Estes | D89: =Table13[[#This Row],[FirstName]]&" "&Table13[[#This Row],[LastName]] -> Alexus Estes | E89: 43936 | G89: Active | H89: Full-Time | I89: Zone B | J89: Part-Time | K89: Sales | L89: Wireline Construction | M89: 21188 | N89: Manager | O89: 1 | P89: =IF(F89="","Active","Non-Active") -> Active | Q89: =YEAR(M89) -> 1958 | R89: =INT(YEARFRAC(M89,"20/04/2026")) -> 68 | S89: {=_xlfn.IFS(Q89<1965,"Baby Boomers",Q89<1981,"Gen X",Q89<1997,"Millenial",TRUE,("Gen Z"))} -> Baby Boomers
A90: 3515 | B90: Kinsley | C90: Flowers | D90: =Table13[[#This Row],[FirstName]]&" "&Table13[[#This Row],[LastName]] -> Kinsley Flowers | E90: 44629 | F90: 44905 | G90: Future Start | H90: Part-Time | I90: Zone A | J90: Part-Time | K90: Sales | L90: Finance & Accounting | M90: 35549 | N90: Controller | O90: 4 | P90: =IF(F90="","Active","Non-Active") -> Non-Active | Q90: =YEAR(M90) -> 1997 | R90: =INT(YEARFRAC(M90,"20/04/2026")) -> 28 | S90: {=_xlfn.IFS(Q90<1965,"Baby Boomers",Q90<1981,"Gen X",Q90<1997,"Millenial",TRUE,("Gen Z"))} -> Gen Z
A91: 3516 | B91: Deborah | C91: Love | D91: =Table13[[#This Row],[FirstName]]&" "&Table13[[#This Row],[LastName]] -> Deborah Love | E91: 44658 | F91: 44948 | G91: Active | H91: Contract | I91: Zone B | J91: Part-Time | K91: Sales | L91: Project Management - Con | M91: 32319 | N91: Coordinator | O91: 5 | P91: =IF(F91="","Active","Non-Active") -> Non-Active | Q91: =YEAR(M91) -> 1988 | R91: =INT(YEARFRAC(M91,"20/04/2026")) -> 37 | S91: {=_xlfn.IFS(Q91<1965,"Baby Boomers",Q91<1981,"Gen X",Q91<1997,"Millenial",TRUE,("Gen Z"))} -> Millenial
A92: 3517 | B92: Milagros | C92: Francis | D92: =Table13[[#This Row],[FirstName]]&" "&Table13[[#This Row],[LastName]] -> Milagros Francis | E92: 43880 | G92: Active | H92: Part-Time | I92: Zone A | J92: Part-Time | K92: Sales | L92: Splicing | M92: 15345 | N92: Splicer | O92: 4 | P92: =IF(F92="","Active","Non-Active") -> Active | Q92: =YEAR(M92) -> 1942 | R92: =INT(YEARFRAC(M92,"20/04/2026")) -> 84 | S92: {=_xlfn.IFS(Q92<1965,"Baby Boomers",Q92<1981,"Gen X",Q92<1997,"Millenial",TRUE,("Gen Z"))} -> Baby Boomers
A93: 3518 | B93: Roberto | C93: Michael | D93: =Table13[[#This Row],[FirstName]]&" "&Table13[[#This Row],[LastName]] -> Roberto Michael | E93: 44296 | F93: 44746 | G93: Active | H93: Contract | I93: Zone B | J93: Part-Time | K93: Sales | L93: General - Eng | M93: 25347 | N93: Coordinator | O93: 2 | P93: =IF(F93="","Active","Non-Active") -> Non-Active | Q93: =YEAR(M93) -> 1969 | R93: =INT(YEARFRAC(M93,"20/04/2026")) -> 56 | S93: {=_xlfn.IFS(Q93<1965,"Baby Boomers",Q93<1981,"Gen X",Q93<1997,"Millenial",TRUE,("Gen Z"))} -> Gen X
A94: 3519 | B94: Elaine | C94: Ewing | D94: =Table13[[#This Row],[FirstName]]&" "&Table13[[#This Row],[LastName]] -> Elaine Ewing | E94: 44549 | F94: 44622 | G94: Active | H94: Part-Time | I94: Zone C | J94: Temporary | K94: Sales | L94: Aerial | M94: 18715 | N94: Groundman | O94: 2 | P94: =IF(F94="","Active","Non-Active") -> Non-Active | Q94: =YEAR(M94) -> 1951 | R94: =INT(YEARFRAC(M94,"20/04/2026")) -> 75 | S94: {=_xlfn.IFS(Q94<1965,"Baby Boomers",Q94<1981,"Gen X",Q94<1997,"Millenial",TRUE,("Gen Z"))} -> Baby Boomers
A95: 3520 | B95: Caiden | C95: Munoz | D95: =Table13[[#This Row],[FirstName]]&" "&Table13[[#This Row],[LastName]] -> Caiden Munoz | E95: 44178 | F95: 44939 | G95: Active | H95: Full-Time | I95: Zone C | J95: Temporary | K95: Sales | L95: Project Management - Con | M95: 23071 | N95: Manager | O95: 1 | P95: =IF(F95="","Active","Non-Active") -> Non-Active | Q95: =YEAR(M95) -> 1963 | R95: =INT(YEARFRAC(M95,"20/04/2026")) -> 63 | S95: {=_xlfn.IFS(Q95<1965,"Baby Boomers",Q95<1981,"Gen X",Q95<1997,"Millenial",TRUE,("Gen Z"))} -> Baby Boomers
A96: 3521 | B96: Jocelyn | C96: Bradford | D96: =Table13[[#This Row],[FirstName]]&" "&Table13[[#This Row],[LastName]] -> Jocelyn Bradford | E96: 43522 | G96: Active | H96: Contract | I96: Zone C | J96: Part-Time | K96: Sales | L96: General - Con | M96: 18004 | N96: Electrician | O96: 4 | P96: =IF(F96="","Active","Non-Active") -> Active | Q96: =YEAR(M96) -> 1949 | R96: =INT(YEARFRAC(M96,"20/04/2026")) -> 77 | S96: {=_xlfn.IFS(Q96<1965,"Baby Boomers",Q96<1981,"Gen X",Q96<1997,"Millenial",TRUE,("Gen Z"))} -> Baby Boomers
A97: 3522 | B97: Marques | C97: Armstrong | D97: =Table13[[#This Row],[FirstName]]&" "&Table13[[#This Row],[LastName]] -> Marques Armstrong | E97: 43892 | G97: Active | H97: Full-Time | I97: Zone C | J97: Part-Time | K97: Sales | L97: Splicing | M97: 30601 | N97: Splicer | O97: 1 | P97: =IF(F97="","Active","Non-Active") -> Active | Q97: =YEAR(M97) -> 1983 | R97: =INT(YEARFRAC(M97,"20/04/2026")) -> 42 | S97: {=_xlfn.IFS(Q97<1965,"Baby Boomers",Q97<1981,"Gen X",Q97<1997,"Millenial",TRUE,("Gen Z"))} -> Millenial
A98: 3523 | B98: Rohan | C98: Chapman | D98: =Table13[[#This Row],[FirstName]]&" "&Table13[[#This Row],[LastName]] -> Rohan Chapman | E98: 44372 | F98: 44798 | G98: Active | H98: Full-Time | I98: Zone A | J98: Temporary | K98: Sales | L98: General - Con | M98: 28843 | N98: Laborer | O98: 2 | P98: =IF(F98="","Active","Non-Active") -> Non-Active | Q98: =YEAR(M98) -> 1978 | R98: =INT(YEARFRAC(M98,"20/04/2026")) -> 47 | S98: {=_xlfn.IFS(Q98<1965,"Baby Boomers",Q98<1981,"Gen X",Q98<1997,"Millenial",TRUE,("Gen Z"))} -> Gen X
A99: 3524 | B99: Emmanuel | C99: Franklin | D99: =Table13[[#This Row],[FirstName]]&" "&Table13[[#This Row],[LastName]] -> Emmanuel Franklin | E99: 44403 | F99: 44685 | G99: Future Start | H99: Contract | I99: Zone B | J99: Full-Time | K99: Sales | L99: Field Operations | M99: 36475 | N99: Laborer | O99: 2 | P99: =IF(F99="","Active","Non-Active") -> Non-Active | Q99: =YEAR(M99) -> 1999 | R99: =INT(YEARFRAC(M99,"20/04/2026")) -> 26 | S99: {=_xlfn.IFS(Q99<1965,"Baby Boomers",Q99<1981,"Gen X",Q99<1997,"Millenial",TRUE,("Gen Z"))} -> Gen Z
A100: 3525 | B100: Clayton | C100: Mccormick | D100: =Table13[[#This Row],[FirstName]]&" "&Table13[[#This Row],[LastName]] -> Clayton Mccormick | E100: 44745 | F100: 44936 | G100: Future Start | H100: Contract | I100: Zone B | J100: Temporary | K100: Sales | L100: General - Con | M100: 24501 | N100: Foreman | O100: 2 | P100: =IF(F100="","Active","Non-Active") -> Non-Active | Q100: =YEAR(M100) -> 1967 | R100: =INT(YEARFRAC(M100,"20/04/2026")) -> 59 | S100: {=_xlfn.IFS(Q100<1965,"Baby Boomers",Q100<1981,"Gen X",Q100<1997,"Millenial",TRUE,("Gen Z"))} -> Gen X
...

Sheet PIVOT TABLE
A1: PIVOT TABLE | M1: Generasi vs Rata-rata rating | Q1: Generasi vs Employee Classification Type
A3: Generasi vs Jumlah karyawan | G3: Generasi vs status kerja | M3: CurrentEmployeeStatus | N3: (All) | Q3: CurrentEmployeeStatus | R3: (All)
A5: Row Labels | B5: Count of EmpID | G5: Count of EmpID | H5: Column Labels | M5: Row Labels | N5: Average of Current Employee Rating | Q5: Count of EmpID | R5: Column Labels
A6: Baby Boomers | B6: 1212 | G6: Row Labels | H6: Active | I6: Non-Active | J6: Grand Total | M6: Baby Boomers | N6: 2.959571 | Q6: Row Labels | R6: Full-Time | S6: Part-Time | T6: Temporary | U6: Grand Total
A7: Gen X | B7: 733 | G7: Baby Boomers | H7: 584 | I7: 628 | J7: 1212 | M7: Gen X | N7: 2.9154161 | Q7: Baby Boomers | R7: 375 | S7: 391 | T7: 446 | U7: 1212
A8: Gen Z | B8: 242 | G8: Gen X | H8: 371 | I8: 362 | J8: 733 | M8: Gen Z | N8: 2.9958678 | Q8: Gen X | R8: 265 | S8: 242 | T8: 226 | U8: 733
A9: Millenial | B9: 813 | G9: Gen Z | H9: 124 | I9: 118 | J9: 242 | M9: Millenial | N9: 3.0233702 | Q9: Gen Z | R9: 82 | S9: 73 | T9: 87 | U9: 242
A10: Grand Total | B10: 3000 | G10: Millenial | H10: 388 | I10: 425 | J10: 813 | M10: Grand Total | N10: 2.969 | Q10: Millenial | R10: 291 | S10: 248 | T10: 274 | U10: 813
G11: Grand Total | H11: 1467 | I11: 1533 | J11: 3000 | Q11: Grand Total | R11: 1013 | S11: 954 | T11: 1033 | U11: 3000
L26: METRICS
L27: TOT EMP | M27: =GETPIVOTDATA("EmpID",$A$5) -> 3000
L28: RATING | M28: =GETPIVOTDATA("Current Employee Rating",$M$5) -> 2.969

Sheet DASHBOARD
